Workbook
Name Alimentacao: Aux_Listas!$H$2:$H$5
Name Alimentação: Aux_Listas!$H$2:$H$20
Name Beneficio: Aux_Listas!$C$2:$C$2
Name Benefício: Aux_Listas!$C$2:$C$20
Name Caridade: Aux_Listas!$O$2:$O$20
Name Cartoes_Credito: FATURAS_CARTAO!$A$4:$A$6
Name Categorias_Despesa: Aux_Listas!$A$6:$A$16
Name Categorias_Receita: Aux_Listas!$A$1:$A$5
Name Convênio: Aux_Listas!$E$2:$E$20
Name Convenios: Aux_Listas!$E$2:$E$2
Name Convênios: Aux_Listas!$E$2:$E$20
Name Dividas: Aux_Listas!$P$2:$P$3
Name Dívidas: Aux_Listas!$P$2:$P$20
Name Educacao: Aux_Listas!$K$2:$K$7
Name Educação: Aux_Listas!$K$2:$K$20
Name Extra: Aux_Listas!$F$2:$F$20
Name Habitacao: Aux_Listas!$G$2:$G$16
Name Habitação: Aux_Listas!$G$2:$G$20
Name Invest_Alternativos: Aux_Listas!$U$2:$U$20
Name Lazer: Aux_Listas!$M$2:$M$20
Name listaCategorias: Aux_Listas!$A$1:INDEX(Aux_Listas!$A:$A,COUNTA(Aux_Listas!$A:$A))
Name Outras_Despesas: Aux_Listas!$Q$2:$Q$20
Name Outros: Aux_Listas!$Q$2:$Q$20
Name Previdência: Aux_Listas!$T$2:$T$20
Name Renda_Fixa: Aux_Listas!$R$2:$R$20
Name Renda_Variável: Aux_Listas!$S$2:$S$20
Name Rentda_Fixa: Aux_Listas!$R$2:$R$20
Name Salario: Aux_Listas!$B$2:$B$7
Name Salário: Aux_Listas!$B$2:$B$7
Name Saude: Aux_Listas!$J$2:$J$6
Name Saúde: Aux_Listas!$J$2:$J$20
Name Servico: Aux_Listas!$D$2:$D$2
Name tbReceitas: LAN_RECEITAS!$A$4:$E$57
Name Trabalho: Aux_Listas!$N$2:$N$20
Name Transporte: Aux_Listas!$I$2:$I$20
Name Vestuario: Aux_Listas!$L$2:$L$4
Name Vestuário: Aux_Listas!$L$2:$L$20

Sheet INICIO
A1: 📊 SISTEMA DE ORÇAMENTO DOMÉSTICO - GUIA DE USO
A2: Controle Financeiro Pessoal - Versão 1.0 | Template para GitHub
A4: 📝 COMO LANÇAR SEUS DADOS
A6: Aba | B6: O que lançar | C6: Campos obrigatórios | D6: Observações
A7: LAN_RECEITAS | B7: Salários, benefícios, rendas extras | C7: Data, Categoria, Subcategoria, Valor, Status | D7: Observação opcional
A8: LAN_DESPESAS | B8: Despesas pagas à vista (Débito/PIX) | C8: Data, Categoria, Subcategoria, Valor, Observação, Status | D8: Use para pagamentos imediatos
A9: LAN_CARTOES | B9: Compras no cartão de crédito | C9: Data_Compra, Categoria, Valor_Total, N_Parcelas, Cartão | D9: Parcelas geradas automaticamente
A10: LAN_INVESTIMENTOS | B10: Aportes e resgates | C10: Data, Ativo, Movimento, Valor | D10: Tipo_Ativo preenche automaticamente
A12: 💳 SISTEMA DE CARTÃO DE CRÉDITO
A14: ✅ PASSO 1: Lance a compra na aba LAN_CARTOES (colunas A-H)
A15: ✅ PASSO 2: Verifique a coluna I (Status_Parcelas)
A16: → ✅ Gerada = Parcelas já existem na aba PARCELAS
A17: → ⚠️ Pendente = Peça para gerar parcelas
A18: ✅ PASSO 3: Se houver pendentes, peça: 'Gerar parcelas'
A19: ✅ PASSO 4: FLUXO_CAIXA mostra saídas nas datas de vencimento
A20: 💡 DICA: O contador no topo da aba mostra quantas estão pendentes!
A22: 📊 VISUALIZAÇÃO E RELATÓRIOS
A24: Aba | B24: Função | C24: Como usar
A25: DASHBOARD | B25: KPIs, gráficos e comparativos | C25: Use filtros ANO e MÊS
A26: ORCAMENTO | B26: Previsto x Realizado mensal | C26: Selecione ANO em R1
A27: FLUXO_CAIXA | B27: Fluxo de caixa MENSAL + PRÓXIMOS 30 DIAS | C27: B4 = Saldo em 01/01 | Saldo atual calculado automaticamente
A29: ⚙️ CADASTROS E CONFIGURAÇÕES
A31: • CAD_Categorias - Cadastro de categorias e subcategorias
A32: • FATURAS_CARTAO - Configuração dos cartões de crédito (corte/vencimento) e lista de cartões
A33: • CAD_Ativos - Tipos de ativos para investimentos
A34: • Aux_Listas - Listas auxiliares para dropdowns (não alterar)
A36: 📊 SISTEMA DE PREVISÕES
A38: A aba PREVISOES contém todas as previsões de receitas e despesas futuras.
A39: Cada mês tem uma linha separada para fácil controle.
A41: Como usar:
A42: 1. As previsões são lançadas diretamente na aba PREVISOES
A43: 2. Cada linha = 1 mês de previsão
A44: 3. Quando realizar um lançamento, marque a previsão como 'Cancelada'
... A115: • Se já existir previsão para o mês, será substituída

Sheet ORCAMENTO
A1: ORÇAMENTO 2025
A2: 📋 Categoria | B2: 💰 Prev.Mensal | C2: =DATE($R$2,1,1) -> 45658 | D2: =DATE($R$2,2,1) -> 45689 | E2: =DATE($R$2,3,1) -> 45717 | F2: =DATE($R$2,4,1) -> 45748 | G2: =DATE($R$2,5,1) -> 45778 | H2: =DATE($R$2,6,1) -> 45809 | I2: =DATE($R$2,7,1) -> 45839 | J2: =DATE($R$2,8,1) -> 45870 | K2: =DATE($R$2,9,1) -> 45901 | L2: =DATE($R$2,10,1) -> 45931 | M2: =DATE($R$2,11,1) -> 45962 | N2: =DATE($R$2,12,1) -> 45992 | O2: 📊 Anual | P2: 📈 Média | Q2: 📅 ANO: | R2: 2025
A3: Receitas | B3: =B4+B11+B12+B13+B14 -> 16000 | C3: =C4+C11+C12+C13+C14 -> 16200 | D3: =D4+D11+D12+D13+D14 -> 15900 | E3: =E4+E11+E12+E13+E14 -> 16400 | F3: =F4+F11+F12+F13+F14 -> 16000 | G3: =G4+G11+G12+G13+G14 -> 16150 | H3: =H4+H11+H12+H13+H14 -> 15950 | I3: =I4+I11+I12+I13+I14 -> 16000 | ... N3: =N4+N11+N12+N13+N14 -> 17100 | O3: =SUM(C3:N3) -> 194500 | P3: =IF(MONTH(TODAY())>0, O3/MONTH(TODAY()), 0) -> 38900
A4: Salário | B4: =SUM(B5:B10) -> 15000 | C4: =SUM(C5:C10) -> 15000 | D4: =SUM(D5:D10) -> 15000 | E4: =SUM(E5:E10) -> 15000 | F4: =SUM(F5:F10) -> 15000 | G4: =SUM(G5:G10) -> 15000 | H4: =SUM(H5:H10) -> 15000 | I4: =SUM(I5:I10) -> 15000 | ... N4: =SUM(N5:N10) -> 15000 | O4: =SUM(C4:N4) -> 180000 | P4: =IF(MONTH(TODAY())>0, O4/MONTH(TODAY()), 0) -> 36000
A5: Salário Marido | B5: 8500 | C5: 8500 | D5: 8500 | E5: 8500 | F5: 8500 | G5: 8500 | H5: 8500 | I5: 8500 | J5: 8500 | K5: 8500 | L5: 8500 | M5: 8500 | N5: 8500 | O5: =SUM(C5:N5) -> 102000 | P5: =IF(MONTH(TODAY())>0, O5/MONTH(TODAY()), 0) -> 20400
A6: Salário Esposa | B6: 6500 | C6: 6500 | D6: 6500 | E6: 6500 | F6: 6500 | G6: 6500 | H6: 6500 | I6: 6500 | J6: 6500 | K6: 6500 | L6: 6500 | M6: 6500 | N6: 6500 | O6: =SUM(C6:N6) -> 78000 | P6: =IF(MONTH(TODAY())>0, O6/MONTH(TODAY()), 0) -> 15600
B7: 0 | C7: 0 | D7: 0 | E7: 0 | F7: 0 | G7: 0 | H7: 0 | I7: 0 | J7: 0 | K7: 0 | L7: 0 | M7: 0 | N7: 0 | O7: =SUM(C7:N7) -> 0 | P7: =IF(MONTH(TODAY())>0, O7/MONTH(TODAY()), 0) -> 0
B8: 0 | C8: 0 | D8: 0 | E8: 0 | F8: 0 | G8: 0 | H8: 0 | I8: 0 | J8: 0 | K8: 0 | L8: 0 | M8: 0 | N8: 0 | O8: =SUM(C8:N8) -> 0 | P8: =IF(MONTH(TODAY())>0, O8/MONTH(TODAY()), 0) -> 0
B9: 0 | C9: 0 | D9: 0 | E9: 0 | F9: 0 | G9: 0 | H9: 0 | I9: 0 | J9: 0 | K9: 0 | L9: 0 | M9: 0 | N9: 0 | O9: =SUM(C9:N9) -> 0 | P9: =IF(MONTH(TODAY())>0, O9/MONTH(TODAY()), 0) -> 0
B10: 0 | C10: 0 | D10: 0 | E10: 0 | F10: 0 | G10: 0 | H10: 0 | I10: 0 | J10: 0 | K10: 0 | L10: 0 | M10: 0 | N10: 0 | O10: =SUM(C10:N10) -> 0 | P10: =IF(MONTH(TODAY())>0, O10/MONTH(TODAY()), 0) -> 0
A11: Benefício | B11: 500 | C11: 500 | D11: 500 | E11: 500 | F11: 500 | G11: 500 | H11: 500 | I11: 500 | J11: 500 | K11: 500 | L11: 500 | M11: 500 | N11: 500 | O11: =SUM(C11:N11) -> 6000 | P11: =IF(MONTH(TODAY())>0, O11/MONTH(TODAY()), 0) -> 1200
A12: Convênios | B12: 0 | C12: 0 | D12: 0 | E12: 0 | F12: 0 | G12: 0 | H12: 0 | I12: 0 | J12: 0 | K12: 0 | L12: 0 | M12: 0 | N12: 0 | O12: =SUM(C12:N12) -> 0 | P12: =IF(MONTH(TODAY())>0, O12/MONTH(TODAY()), 0) -> 0
A13: Extra | B13: 0 | C13: 200 | D13: 0 | E13: 300 | F13: 0 | G13: 150 | H13: 0 | I13: 0 | J13: 250 | K13: 0 | L13: 0 | M13: 500 | N13: 1000 | O13: =SUM(C13:N13) -> 2400 | P13: =IF(MONTH(TODAY())>0, O13/MONTH(TODAY()), 0) -> 480
A14: Prestação Serviço Extra | B14: 500 | C14: 500 | D14: 400 | E14: 600 | F14: 500 | G14: 500 | H14: 450 | I14: 500 | J14: 500 | K14: 550 | L14: 500 | M14: 500 | N14: 600 | O14: =SUM(C14:N14) -> 6100 | P14: =IF(MONTH(TODAY())>0, O14/MONTH(TODAY()), 0) -> 1220
A15: Investimentos | B15: 500 | C15: =SUM(C16:C19) -> 500 | D15: =SUM(D16:D19) -> 500 | E15: =SUM(E16:E19) -> 500 | F15: =SUM(F16:F19) -> 500 | G15: =SUM(G16:G19) -> 500 | H15: =SUM(H16:H19) -> 500 | I15: =SUM(I16:I19) -> 500 | J15: =SUM(J16:J19) -> 500 | ... N15: =SUM(N16:N19) -> 700 | O15: =SUM(C15:N15) -> 6200 | P15: =IF(MONTH(TODAY())>0, O15/MONTH(TODAY()), 0) -> 1240
A16: Renda Fixa | B16: 300 | C16: 300 | D16: 300 | E16: 300 | F16: 300 | G16: 300 | H16: 300 | I16: 300 | J16: 300 | K16: 300 | L16: 300 | M16: 300 | N16: 500 | O16: =SUM(C16:N16) -> 3800 | P16: =IF(MONTH(TODAY())>0, O16/MONTH(TODAY()), 0) -> 760
A17: Renda Variável | B17: 100 | C17: 100 | D17: 100 | E17: 100 | F17: 100 | G17: 100 | H17: 100 | I17: 100 | J17: 100 | K17: 100 | L17: 100 | M17: 100 | N17: 100 | O17: =SUM(C17:N17) -> 1200 | P17: =IF(MONTH(TODAY())>0, O17/MONTH(TODAY()), 0) -> 240
A18: Previdência | B18: 100 | C18: 100 | D18: 100 | E18: 100 | F18: 100 | G18: 100 | H18: 100 | I18: 100 | J18: 100 | K18: 100 | L18: 100 | M18: 100 | N18: 100 | O18: =SUM(C18:N18) -> 1200 | P18: =IF(MONTH(TODAY())>0, O18/MONTH(TODAY()), 0) -> 240
A19: Alternativos | B19: 0 | C19: 0 | D19: 0 | E19: 0 | F19: 0 | G19: 0 | H19: 0 | I19: 0 | J19: 0 | K19: 0 | L19: 0 | M19: 0 | N19: 0 | O19: =SUM(C19:N19) -> 0 | P19: =IF(MONTH(TODAY())>0, O19/MONTH(TODAY()), 0) -> 0
A20: Despesas | B20: =SUM(B21:B31) -> 12500 | C20: =SUM(C21:C31) -> 12130 | D20: =SUM(D21:D31) -> 13020 | E20: =SUM(E21:E31) -> 11750 | F20: =SUM(F21:F31) -> 13100 | G20: =SUM(G21:G31) -> 12500 | H20: =SUM(H21:H31) -> 12320 | I20: =SUM(I21:I31) -> 12760 | ... N20: =SUM(N21:N31) -> 13800 | O20: =SUM(C20:N20) -> 151680 | P20: =IF(MONTH(TODAY())>0, O20/MONTH(TODAY()), 0) -> 30336
A21: Habitação | B21: 4800 | C21: 4750 | D21: 4850 | E21: 4700 | F21: 4900 | G21: 4800 | H21: 4750 | I21: 4850 | J21: 4700 | K21: 4800 | L21: 4900 | M21: 4750 | N21: 5000 | O21: =SUM(C21:N21) -> 57750 | P21: =IF(MONTH(TODAY())>0, O21/MONTH(TODAY()), 0) -> 11550
A22: Alimentação | B22: 2000 | C22: 1950 | D22: 2100 | E22: 1900 | F22: 2050 | G22: 2000 | H22: 1980 | I22: 2100 | J22: 1900 | K22: 2000 | L22: 2050 | M22: 2100 | N22: 2200 | O22: =SUM(C22:N22) -> 24330 | P22: =IF(MONTH(TODAY())>0, O22/MONTH(TODAY()), 0) -> 4866
A23: Transporte | B23: 1200 | C23: 1150 | D23: 1250 | E23: 1100 | F23: 1300 | G23: 1200 | H23: 1180 | I23: 1220 | J23: 1150 | K23: 1200 | L23: 1250 | M23: 1200 | N23: 1300 | O23: =SUM(C23:N23) -> 14500 | P23: =IF(MONTH(TODAY())>0, O23/MONTH(TODAY()), 0) -> 2900
A24: Saúde | B24: 800 | C24: 750 | D24: 850 | E24: 700 | F24: 900 | G24: 800 | H24: 780 | I24: 820 | J24: 750 | K24: 800 | L24: 850 | M24: 800 | N24: 900 | O24: =SUM(C24:N24) -> 9700 | P24: =IF(MONTH(TODAY())>0, O24/MONTH(TODAY()), 0) -> 1940
A25: Educação | B25: 1500 | C25: 1500 | D25: 1500 | E25: 1500 | F25: 1500 | G25: 1500 | H25: 1500 | I25: 1500 | J25: 1500 | K25: 1500 | L25: 1500 | M25: 1500 | N25: 1500 | O25: =SUM(C25:N25) -> 18000 | P25: =IF(MONTH(TODAY())>0, O25/MONTH(TODAY()), 0) -> 3600
A26: Vestuário | B26: 300 | C26: 250 | D26: 350 | E26: 200 | F26: 400 | G26: 300 | H26: 280 | I26: 320 | J26: 250 | K26: 300 | L26: 350 | M26: 400 | N26: 500 | O26: =SUM(C26:N26) -> 3900 | P26: =IF(MONTH(TODAY())>0, O26/MONTH(TODAY()), 0) -> 780
A27: Lazer | B27: 600 | C27: 550 | D27: 700 | E27: 500 | F27: 650 | G27: 600 | H27: 580 | I27: 620 | J27: 550 | K27: 600 | L27: 650 | M27: 700 | N27: 800 | O27: =SUM(C27:N27) -> 7500 | P27: =IF(MONTH(TODAY())>0, O27/MONTH(TODAY()), 0) -> 1500
A28: Caridade | B28: 100 | C28: 100 | D28: 100 | E28: 100 | F28: 100 | G28: 100 | H28: 100 | I28: 100 | J28: 100 | K28: 100 | L28: 100 | M28: 100 | N28: 150 | O28: =SUM(C28:N28) -> 1250 | P28: =IF(MONTH(TODAY())>0, O28/MONTH(TODAY()), 0) -> 250
A29: Gastos Profissionais | B29: 200 | C29: 180 | D29: 220 | E29: 150 | F29: 250 | G29: 200 | H29: 190 | I29: 210 | J29: 180 | K29: 200 | L29: 220 | M29: 200 | N29: 250 | O29: =SUM(C29:N29) -> 2450 | P29: =IF(MONTH(TODAY())>0, O29/MONTH(TODAY()), 0) -> 490
A30: Dívidas | B30: 0 | C30: 0 | D30: 0 | E30: 0 | F30: 0 | G30: 0 | H30: 0 | I30: 0 | J30: 0 | K30: 0 | L30: 0 | M30: 0 | N30: 0 | O30: =SUM(C30:N30) -> 0 | P30: =IF(MONTH(TODAY())>0, O30/MONTH(TODAY()), 0) -> 0
A31: Outros | B31: 1000 | C31: 950 | D31: 1100 | E31: 900 | F31: 1050 | G31: 1000 | H31: 980 | I31: 1020 | J31: 950 | K31: 1000 | L31: 1050 | M31: 1100 | N31: 1200 | O31: =SUM(C31:N31) -> 12300 | P31: =IF(MONTH(TODAY())>0, O31/MONTH(TODAY()), 0) -> 2460
A32: Resultado Operacional | B32: =B3-B20 -> 3500 | C32: =C3-C20 -> 4070 | D32: =D3-D20 -> 2880 | E32: =E3-E20 -> 4650 | F32: =F3-F20 -> 2900 | G32: =G3-G20 -> 3650 | H32: =H3-H20 -> 3630 | I32: =I3-I20 -> 3240 | ... N32: =N3-N20 -> 3300 | O32: =SUM(C32:N32) -> 42820 | P32: =IF(MONTH(TODAY())>0, O32/MONTH(TODAY()), 0) -> 8564
A33: Resultado c/ Investimentos | B33: =B3-B20-B15 -> 3000 | C33: =C3-C20-C15 -> 3570 | D33: =D3-D20-D15 -> 2380 | E33: =E3-E20-E15 -> 4150 | F33: =F3-F20-F15 -> 2400 | G33: =G3-G20-G15 -> 3150 | H33: =H3-H20-H15 -> 3130 | I33: =I3-I20-I15 -> 2740 | ... N33: =N3-N20-N15 -> 2600 | O33: =SUM(C33:N33) -> 36620 | P33: =IF(MONTH(TODAY())>0, O33/MONTH(TODAY()), 0) -> 7324

Sheet LAN_RECEITAS
A1: 📥 LANÇAMENTOS DE RECEITAS
A2: Controle de Entradas Financeiras - Salários, Benefícios, Serviços e Extras
A3: 📅 Data | B3: 📂 Categoria | C3: 📋 Subcategoria | D3: 💵 Valor | E3: 📝 Observação | F3: 📊 Status
A4: 45661 | B4: Salário | C4: Salário Marido | D4: 8500 | E4: Salário mensal | F4: Realizado
A5: 45666 | B5: Salário | C5: Salário Esposa | D5: 6500 | E5: Salário mensal | F5: Realizado
A6: 45657 | B6: Benefício | C6: Auxílio Alimentação | D6: 500 | E6: Vale alimentação | F6: Realizado
A7: 45681 | B7: Prestação Serviço Extra | C7: Serviço Freelance | D7: 500 | E7: Trabalho extra | F7: Realizado
A8: 45671 | B8: Extra | C8: Outros | D8: 200 | E8: Receita extra | F8: Realizado
A9: 45692 | B9: Salário | C9: Salário Marido | D9: 8500 | E9: Salário mensal | F9: Realizado
A10: 45697 | B10: Salário | C10: Salário Esposa | D10: 6500 | E10: Salário mensal | F10: Realizado
A11: 45688 | B11: Benefício | C11: Auxílio Alimentação | D11: 500 | E11: Vale alimentação | F11: Realizado
A12: 45712 | B12: Prestação Serviço Extra | C12: Serviço Freelance | D12: 400 | E12: Trabalho extra | F12: Realizado
A13: 45720 | B13: Salário | C13: Salário Marido | D13: 8500 | E13: Salário mensal | F13: Realizado
A14: 45725 | B14: Salário | C14: Salário Esposa | D14: 6500 | E14: Salário mensal | F14: Realizado
A15: 45716 | B15: Benefício | C15: Auxílio Alimentação | D15: 500 | E15: Vale alimentação | F15: Realizado
... A57: 46005 | B57: Extra | C57: Outros | D57: 1000 | E57: Receita extra | F57: Realizado

Sheet LAN_DESPESAS
A1: 📤 LANÇAMENTOS DE DESPESAS
A2: Controle de Saídas Financeiras - Pagamentos à Vista (Débito/PIX)
A3: 📅 Data | B3: 📂 Categoria | C3: 📋 Subcategoria | D3: 💰 Valor | E3: 📝 Observação | F3: Categoria_Aux | G3: 📊 Status
A4: 45666 | B4: Habitação | C4: Aluguel/Financiamento | D4: 2375 | E4: Financiamento casa | F4: Habitacao | G4: Realizado
A5: 45671 | B5: Habitação | C5: Energia Elétrica | D5: 712.5 | E5: Conta de luz | F5: Habitacao | G5: Realizado
A6: 45676 | B6: Habitação | C6: Água | D6: 380 | E6: Conta de água | F6: Habitacao | G6: Realizado
A7: 45681 | B7: Habitação | C7: Internet / TV | D7: 570 | E7: Internet e TV | F7: Habitacao | G7: Realizado
A8: 45684 | B8: Habitação | C8: Condomínio | D8: 712.5 | E8: Taxa condomínio | F8: Habitacao | G8: Realizado
A9: 45661 | B9: Alimentação | C9: Supermercado | D9: 1365 | E9: Compras do mês | F9: Alimentacao | G9: Realizado
A10: 45674 | B10: Alimentação | C10: Padaria | D10: 292.5 | E10: Padaria | F10: Alimentacao | G10: Realizado
A11: 45678 | B11: Alimentação | C11: Restaurante | D11: 292.5 | E11: Almoço fora | F11: Alimentacao | G11: Realizado
A12: 45664 | B12: Transporte | C12: Gasolina | D12: 690 | E12: Combustível | F12: Transporte | G12: Realizado
A13: 45671 | B13: Transporte | C13: Estacionamento | D13: 230 | E13: Estacionamento | F13: Transporte | G13: Realizado
A14: 45681 | B14: Transporte | C14: Uber / Táxi | D14: 230 | E14: Transporte app | F14: Transporte | G14: Realizado
A15: 45666 | B15: Saúde | C15: Plano de Saúde | D15: 525 | E15: Mensalidade plano | F15: Saude | G15: Realizado
... A243: 46015 | B243: Outros | C243: Diversos | D243: 1200 | E243: Gastos diversos | F243: Outros | G243: Realizado

Sheet LAN_CARTOES
A1: 💳 LANÇAMENTOS DE CARTÕES DE CRÉDITO | J1: ⚠️ PARCELAS PENDENTES: | K1: =COUNTIF(I:I,"⚠️ Pendente") -> 0 | L1: =IF(K1=0,"✅ Tudo OK!","⚠️ Gerar parcelas!") -> ✅ Tudo OK!
A2: Compras Parceladas e à Vista no Crédito - Parcelas Geradas Automaticamente
A3: 📅 Data Compra | B3: 📂 Categoria | C3: 📋 Subcategoria | D3: 📝 Descrição | E3: 💳 Valor Total | F3: 🔢 Parcelas | G3: 💳 Cartão | H3: Categoria_Aux | I3: 📊 Status_Parcelas
A4: 45662 | B4: Alimentação | C4: Restaurante | D4: Jantar aniversário família | E4: 450 | F4: 1 | G4: Crédito Banco A - Maria | H4: =IF(tbCartoes[[#This Row],[📂 Categoria]]="","",SUBSTITUTE(tbCartoes[[#This Row],[📂 Categoria]]," ","_")) -> Alimentação | I4: =IF(A4="","",IF(COUNTIFS(tbParcelas6[Data_Compra],A4,tbParcelas6[Descrição],D4)>0,"✅ Gerada","⚠️ Pendente")) -> ✅ Gerada
A5: 45667 | B5: Vestuário | C5: Roupas | D5: Roupas de verão | E5: 890 | F5: 3 | G5: Crédito Banco A - Carlos | H5: =IF(tbCartoes[[#This Row],[📂 Categoria]]="","",SUBSTITUTE(tbCartoes[[#This Row],[📂 Categoria]]," ","_")) -> Vestuário | I5: =IF(A5="","",IF(COUNTIFS(tbParcelas6[Data_Compra],A5,tbParcelas6[Descrição],D5)>0,"✅ Gerada","⚠️ Pendente")) -> ✅ Gerada
A6: 45672 | B6: Lazer | C6: Viagem | D6: Passagens férias julho | E6: 3600 | F6: 6 | G6: Crédito Banco B - Maria | H6: =IF(tbCartoes[[#This Row],[📂 Categoria]]="","",SUBSTITUTE(tbCartoes[[#This Row],[📂 Categoria]]," ","_")) -> Lazer | I6: =IF(A6="","",IF(COUNTIFS(tbParcelas6[Data_Compra],A6,tbParcelas6[Descrição],D6)>0,"✅ Gerada","⚠️ Pendente")) -> ✅ Gerada
A7: 45677 | B7: Habitação | C7: Móveis / Decoração | D7: Sofá novo sala | E7: 4500 | F7: 10 | G7: Crédito Banco A - Maria | H7: =IF(tbCartoes[[#This Row],[📂 Categoria]]="","",SUBSTITUTE(tbCartoes[[#This Row],[📂 Categoria]]," ","_")) -> Habitação | I7: =IF(A7="","",IF(COUNTIFS(tbParcelas6[Data_Compra],A7,tbParcelas6[Descrição],D7)>0,"✅ Gerada","⚠️ Pendente")) -> ✅ Gerada
A8: 45691 | B8: Educação | C8: Cursos | D8: Curso online Excel | E8: 297 | F8: 1 | G8: Crédito Banco A - Carlos | H8: =IF(tbCartoes[[#This Row],[📂 Categoria]]="","",SUBSTITUTE(tbCartoes[[#This Row],[📂 Categoria]]," ","_")) -> Educação | I8: =IF(A8="","",IF(COUNTIFS(tbParcelas6[Data_Compra],A8,tbParcelas6[Descrição],D8)>0,"✅ Gerada","⚠️ Pendente")) -> ✅ Gerada
A9: 45702 | B9: Lazer | C9: Saídas | D9: Jantar Dia dos Namorados | E9: 380 | F9: 1 | G9: Crédito Banco B - Maria | H9: =IF(tbCartoes[[#This Row],[📂 Categoria]]="","",SUBSTITUTE(tbCartoes[[#This Row],[📂 Categoria]]," ","_")) -> Lazer | I9: =IF(A9="","",IF(COUNTIFS(tbParcelas6[Data_Compra],A9,tbParcelas6[Descrição],D9)>0,"✅ Gerada","⚠️ Pendente")) -> ✅ Gerada
A10: 45708 | B10: Saúde | C10: Consultas / Exames | D10: Óculos novos | E10: 1200 | F10: 4 | G10: Crédito Banco A - Maria | H10: =IF(tbCartoes[[#This Row],[📂 Categoria]]="","",SUBSTITUTE(tbCartoes[[#This Row],[📂 Categoria]]," ","_")) -> Saúde | I10: =IF(A10="","",IF(COUNTIFS(tbParcelas6[Data_Compra],A10,tbParcelas6[Descrição],D10)>0,"✅ Gerada","⚠️ Pendente")) -> ✅ Gerada
A11: 45721 | B11: Transporte | C11: Manutenção Veículo | D11: Revisão carro | E11: 1850 | F11: 3 | G11: Crédito Banco A - Carlos | H11: =IF(tbCartoes[[#This Row],[📂 Categoria]]="","",SUBSTITUTE(tbCartoes[[#This Row],[📂 Categoria]]," ","_")) -> Transporte | I11: =IF(A11="","",IF(COUNTIFS(tbParcelas6[Data_Compra],A11,tbParcelas6[Descrição],D11)>0,"✅ Gerada","⚠️ Pendente")) -> ✅ Gerada
A12: 45728 | B12: Alimentação | C12: Supermercado | D12: Compra grande mensal | E12: 650 | F12: 1 | G12: Crédito Banco B - Maria | H12: =IF(tbCartoes[[#This Row],[📂 Categoria]]="","",SUBSTITUTE(tbCartoes[[#This Row],[📂 Categoria]]," ","_")) -> Alimentação | I12: =IF(A12="","",IF(COUNTIFS(tbParcelas6[Data_Compra],A12,tbParcelas6[Descrição],D12)>0,"✅ Gerada","⚠️ Pendente")) -> ✅ Gerada
A13: 45741 | B13: Habitação | C13: Eletrodomésticos | D13: Geladeira nova | E13: 3200 | F13: 10 | G13: Crédito Banco A - Maria | H13: =IF(tbCartoes[[#This Row],[📂 Categoria]]="","",SUBSTITUTE(tbCartoes[[#This Row],[📂 Categoria]]," ","_")) -> Habitação | I13: =IF(A13="","",IF(COUNTIFS(tbParcelas6[Data_Compra],A13,tbParcelas6[Descrição],D13)>0,"✅ Gerada","⚠️ Pendente")) -> ✅ Gerada
A14: 45755 | B14: Vestuário | C14: Calçados | D14: Tênis corrida | E14: 590 | F14: 2 | G14: Crédito Banco A - Carlos | H14: =IF(tbCartoes[[#This Row],[📂 Categoria]]="","",SUBSTITUTE(tbCartoes[[#This Row],[📂 Categoria]]," ","_")) -> Vestuário | I14: =IF(A14="","",IF(COUNTIFS(tbParcelas6[Data_Compra],A14,tbParcelas6[Descrição],D14)>0,"✅ Gerada","⚠️ Pendente")) -> ✅ Gerada
A15: 45762 | B15: Lazer | C15: Streaming (Netflix/Spotify/Prime) | D15: Assinatura anual Disney+ | E15: 360 | F15: 1 | G15: Crédito Banco B - Maria | H15: =IF(tbCartoes[[#This Row],[📂 Categoria]]="","",SUBSTITUTE(tbCartoes[[#This Row],[📂 Categoria]]," ","_")) -> Lazer | I15: =IF(A15="","",IF(COUNTIFS(tbParcelas6[Data_Compra],A15,tbParcelas6[Descrição],D15)>0,"✅ Gerada","⚠️ Pendente")) -> ✅ Gerada
... A40: 46011 | B40: Lazer | C40: Saídas | D40: Festa Réveillon | E40: 450 | F40: 2 | G40: Crédito Banco A - Maria | H40: =IF(tbCartoes[[#This Row],[📂 Categoria]]="","",SUBSTITUTE(tbCartoes[[#This Row],[📂 Categoria]]," ","_")) -> Lazer | I40: =IF(A40="","",IF(COUNTIFS(tbParcelas6[Data_Compra],A40,tbParcelas6[Descrição],D40)>0,"✅ Gerada","⚠️ Pendente")) -> ✅ Gerada
H41: =IF(tbCartoes[[#This Row],[📂 Categoria]]="","",SUBSTITUTE(tbCartoes[[#This Row],[📂 Categoria]]," ","_"))
H42: =IF(tbCartoes[[#This Row],[📂 Categoria]]="","",SUBSTITUTE(tbCartoes[[#This Row],[📂 Categoria]]," ","_"))
H43: =IF(tbCartoes[[#This Row],[📂 Categoria]]="","",SUBSTITUTE(tbCartoes[[#This Row],[📂 Categoria]]," ","_"))
H44: =IF(tbCartoes[[#This Row],[📂 Categoria]]="","",SUBSTITUTE(tbCartoes[[#This Row],[📂 Categoria]]," ","_"))
H45: =IF(tbCartoes[[#This Row],[📂 Categoria]]="","",SUBSTITUTE(tbCartoes[[#This Row],[📂 Categoria]]," ","_"))
H46: =IF(tbCartoes[[#This Row],[📂 Categoria]]="","",SUBSTITUTE(tbCartoes[[#This Row],[📂 Categoria]]," ","_"))
H47: =IF(tbCartoes[[#This Row],[📂 Categoria]]="","",SUBSTITUTE(tbCartoes[[#This Row],[📂 Categoria]]," ","_"))
H48: =IF(tbCartoes[[#This Row],[📂 Categoria]]="","",SUBSTITUTE(tbCartoes[[#This Row],[📂 Categoria]]," ","_"))
H49: =IF(tbCartoes[[#This Row],[📂 Categoria]]="","",SUBSTITUTE(tbCartoes[[#This Row],[📂 Categoria]]," ","_"))
H50: =IF(tbCartoes[[#This Row],[📂 Categoria]]="","",SUBSTITUTE(tbCartoes[[#This Row],[📂 Categoria]]," ","_"))
H51: =IF(tbCartoes[[#This Row],[📂 Categoria]]="","",SUBSTITUTE(tbCartoes[[#This Row],[📂 Categoria]]," ","_"))
H52: =IF(tbCartoes[[#This Row],[📂 Categoria]]="","",SUBSTITUTE(tbCartoes[[#This Row],[📂 Categoria]]," ","_"))
... H1004: =IF(tbCartoes[[#This Row],[📂 Categoria]]="","",SUBSTITUTE(tbCartoes[[#This Row],[📂 Categoria]]," ","_"))

Sheet FLUXO_CAIXA
A1: 📊 FLUXO DE CAIXA: REALIZADO + PREVISTO | K1: {=INDEX($G$7:$G$18,MONTH(TODAY())-1)} -> 17146.333
K2: {=SUMPRODUCT((tb_receitas[📅 Data]>=DATE(YEAR(TODAY()),MONTH(TODAY()),1))*(tb_receitas[📅 Data]<TODAY())*(tb_receitas[📊 Status]="Realizado")*(tb_receitas[💵 Valor]))} -> 0
A3: 📅 ANO: | B3: 2025 | D3: 📆 MÊS: | E3: 0 | G3: (0 = Todos | 1-12 = Mês específico) | I3: 📅 Data Ref: | J3: =DATE($B$3,5,18) -> 45795 | K3: {=SUMPRODUCT((tbDespesas[📅 Data]>=DATE(YEAR(TODAY()),MONTH(TODAY()),1))*(tbDespesas[📅 Data]<TODAY())*(tbDespesas[📊 Status]="Realizado")*(tbDespesas[💰 Valor]))} -> 0
A4: 💰 SALDO EM 01/01: | B4: 10000 | C4: (Saldo bancário em 1º de janeiro do ano selecionado) | K4: {=SUMPRODUCT((tbParcelas6[Data_Vencimento]>=DATE(YEAR(TODAY()),MONTH(TODAY()),1))*(tbParcelas6[Data_Vencimento]<TODAY())*(tbParcelas6[Valor_Parcela]))} -> 0
K5: =K1+K2-K3-K4 -> 17146.333
A6: Mês | B6: Entradas Reais | C6: Entradas Previstas | D6: Saídas Reais | E6: Saídas Previstas | F6: Saldo Mês | G6: Saldo Acum. | H6: Status | K6: {=SUMPRODUCT((tb_investimentos[Data]>=DATE(YEAR(TODAY()),MONTH(TODAY()),1))*(tb_investimentos[Data]<TODAY())*(tb_investimentos[Movimento]="Aporte")*(tb_investimentos[Valor]))} -> 0
A7: ="jan/"&$B$3 -> jan/2025 | B7: =SUMIFS(tb_receitas[💵 Valor],tb_receitas[📅 Data],">="&DATE($B$3,1,1),tb_receitas[📅 Data],"<"&DATE($B$3,1+1,1),tb_receitas[📊 Status],"Realizado")+SUMIFS(tb_investimentos[Valor],tb_investimentos[Data],">="&DATE($B$3,1,1),tb_investimentos[Data],"<"&DATE($B$3,1+1,1),tb_investimentos[Movimento],"Resgate") -> 16200 | C7: {=SUMPRODUCT((tbPrevisoes[📂 TIPO]="Receita")*(tbPrevisoes[✅ STATUS]="Ativa")*(YEAR(tbPrevisoes[📅 DATA])=$B$3)*(MONTH(tbPrevisoes[📅 DATA])=1)*tbPrevisoes[💰 VALOR])} -> 0 | D7: =SUMIFS(tbDespesas[💰 Valor],tbDespesas[📅 Data],">="&DATE($B$3,1,1),tbDespesas[📅 Data],"<"&DATE($B$3,1+1,1),tbDespesas[📊 Status],"Realizado")+SUMIFS(tbParcelas6[Valor_Parcela],tbParcelas6[Data_Vencimento],">="&DATE($B$3,1,1),tbParcelas6[Data_Vencimento],"<"&DATE($B$3,1+1,1)) -> 12580 | E7: {=SUMPRODUCT((tbPrevisoes[📂 TIPO]="Despesa")*(tbPrevisoes[✅ STATUS]="Ativa")*(YEAR(tbPrevisoes[📅 DATA])=$B$3)*(MONTH(tbPrevisoes[📅 DATA])=1)*tbPrevisoes[💰 VALOR])} -> 0 | F7: =(B7+C7)-(D7+E7) -> 3620 | G7: =$B$4+F7 -> 13620 | H7: =IF(G7<0,"🔴 Negativo",IF(G7<5000,"🟡 Alerta","🟢 OK")) -> 🟢 OK
A8: ="fev/"&$B$3 -> fev/2025 | B8: =SUMIFS(tb_receitas[💵 Valor],tb_receitas[📅 Data],">="&DATE($B$3,2,1),tb_receitas[📅 Data],"<"&DATE($B$3,2+1,1),tb_receitas[📊 Status],"Realizado")+SUMIFS(tb_investimentos[Valor],tb_investimentos[Data],">="&DATE($B$3,2,1),tb_investimentos[Data],"<"&DATE($B$3,2+1,1),tb_investimentos[Movimento],"Resgate") -> 15900 | C8: {=SUMPRODUCT((tbPrevisoes[📂 TIPO]="Receita")*(tbPrevisoes[✅ STATUS]="Ativa")*(YEAR(tbPrevisoes[📅 DATA])=$B$3)*(MONTH(tbPrevisoes[📅 DATA])=2)*tbPrevisoes[💰 VALOR])} -> 0 | D8: =SUMIFS(tbDespesas[💰 Valor],tbDespesas[📅 Data],">="&DATE($B$3,2,1),tbDespesas[📅 Data],"<"&DATE($B$3,2+1,1),tbDespesas[📊 Status],"Realizado")+SUMIFS(tbParcelas6[Valor_Parcela],tbParcelas6[Data_Vencimento],">="&DATE($B$3,2,1),tbParcelas6[Data_Vencimento],"<"&DATE($B$3,2+1,1)) -> 14366.667 | E8: {=SUMPRODUCT((tbPrevisoes[📂 TIPO]="Despesa")*(tbPrevisoes[✅ STATUS]="Ativa")*(YEAR(tbPrevisoes[📅 DATA])=$B$3)*(MONTH(tbPrevisoes[📅 DATA])=2)*tbPrevisoes[💰 VALOR])} -> 0 | F8: =(B8+C8)-(D8+E8) -> 1533.3333 | G8: =G7+F8 -> 15153.333 | H8: =IF(G8<0,"🔴 Negativo",IF(G8<5000,"🟡 Alerta","🟢 OK")) -> 🟢 OK
A9: ="mar/"&$B$3 -> mar/2025 | B9: =SUMIFS(tb_receitas[💵 Valor],tb_receitas[📅 Data],">="&DATE($B$3,3,1),tb_receitas[📅 Data],"<"&DATE($B$3,3+1,1),tb_receitas[📊 Status],"Realizado")+SUMIFS(tb_investimentos[Valor],tb_investimentos[Data],">="&DATE($B$3,3,1),tb_investimentos[Data],"<"&DATE($B$3,3+1,1),tb_investimentos[Movimento],"Resgate") -> 16400 | C9: {=SUMPRODUCT((tbPrevisoes[📂 TIPO]="Receita")*(tbPrevisoes[✅ STATUS]="Ativa")*(YEAR(tbPrevisoes[📅 DATA])=$B$3)*(MONTH(tbPrevisoes[📅 DATA])=3)*tbPrevisoes[💰 VALOR])} -> 0 | D9: =SUMIFS(tbDespesas[💰 Valor],tbDespesas[📅 Data],">="&DATE($B$3,3,1),tbDespesas[📅 Data],"<"&DATE($B$3,3+1,1),tbDespesas[📊 Status],"Realizado")+SUMIFS(tbParcelas6[Valor_Parcela],tbParcelas6[Data_Vencimento],">="&DATE($B$3,3,1),tbParcelas6[Data_Vencimento],"<"&DATE($B$3,3+1,1)) -> 14073.667 | E9: {=SUMPRODUCT((tbPrevisoes[📂 TIPO]="Despesa")*(tbPrevisoes[✅ STATUS]="Ativa")*(YEAR(tbPrevisoes[📅 DATA])=$B$3)*(MONTH(tbPrevisoes[📅 DATA])=3)*tbPrevisoes[💰 VALOR])} -> 0 | F9: =(B9+C9)-(D9+E9) -> 2326.3333 | G9: =G8+F9 -> 17479.667 | H9: =IF(G9<0,"🔴 Negativo",IF(G9<5000,"🟡 Alerta","🟢 OK")) -> 🟢 OK
A10: ="abr/"&$B$3 -> abr/2025 | B10: =SUMIFS(tb_receitas[💵 Valor],tb_receitas[📅 Data],">="&DATE($B$3,4,1),tb_receitas[📅 Data],"<"&DATE($B$3,4+1,1),tb_receitas[📊 Status],"Realizado")+SUMIFS(tb_investimentos[Valor],tb_investimentos[Data],">="&DATE($B$3,4,1),tb_investimentos[Data],"<"&DATE($B$3,4+1,1),tb_investimentos[Movimento],"Resgate") -> 16000 | C10: {=SUMPRODUCT((tbPrevisoes[📂 TIPO]="Receita")*(tbPrevisoes[✅ STATUS]="Ativa")*(YEAR(tbPrevisoes[📅 DATA])=$B$3)*(MONTH(tbPrevisoes[📅 DATA])=4)*tbPrevisoes[💰 VALOR])} -> 0 | D10: =SUMIFS(tbDespesas[💰 Valor],tbDespesas[📅 Data],">="&DATE($B$3,4,1),tbDespesas[📅 Data],"<"&DATE($B$3,4+1,1),tbDespesas[📊 Status],"Realizado")+SUMIFS(tbParcelas6[Valor_Parcela],tbParcelas6[Data_Vencimento],">="&DATE($B$3,4,1),tbParcelas6[Data_Vencimento],"<"&DATE($B$3,4+1,1)) -> 16333.333 | E10: {=SUMPRODUCT((tbPrevisoes[📂 TIPO]="Despesa")*(tbPrevisoes[✅ STATUS]="Ativa")*(YEAR(tbPrevisoes[📅 DATA])=$B$3)*(MONTH(tbPrevisoes[📅 DATA])=4)*tbPrevisoes[💰 VALOR])} -> 0 | F10: =(B10+C10)-(D10+E10) -> -333.33333 | G10: =G9+F10 -> 17146.333 | H10: =IF(G10<0,"🔴 Negativo",IF(G10<5000,"🟡 Alerta","🟢 OK")) -> 🟢 OK
A11: ="mai/"&$B$3 -> mai/2025 | B11: =SUMIFS(tb_receitas[💵 Valor],tb_receitas[📅 Data],">="&DATE($B$3,5,1),tb_receitas[📅 Data],"<"&DATE($B$3,5+1,1),tb_receitas[📊 Status],"Realizado")+SUMIFS(tb_investimentos[Valor],tb_investimentos[Data],">="&DATE($B$3,5,1),tb_investimentos[Data],"<"&DATE($B$3,5+1,1),tb_investimentos[Movimento],"Resgate") -> 16150 | C11: {=SUMPRODUCT((tbPrevisoes[📂 TIPO]="Receita")*(tbPrevisoes[✅ STATUS]="Ativa")*(YEAR(tbPrevisoes[📅 DATA])=$B$3)*(MONTH(tbPrevisoes[📅 DATA])=5)*tbPrevisoes[💰 VALOR])} -> 0 | D11: =SUMIFS(tbDespesas[💰 Valor],tbDespesas[📅 Data],">="&DATE($B$3,5,1),tbDespesas[📅 Data],"<"&DATE($B$3,5+1,1),tbDespesas[📊 Status],"Realizado")+SUMIFS(tbParcelas6[Valor_Parcela],tbParcelas6[Data_Vencimento],">="&DATE($B$3,5,1),tbParcelas6[Data_Vencimento],"<"&DATE($B$3,5+1,1)) -> 15681.667 | E11: {=SUMPRODUCT((tbPrevisoes[📂 TIPO]="Despesa")*(tbPrevisoes[✅ STATUS]="Ativa")*(YEAR(tbPrevisoes[📅 DATA])=$B$3)*(MONTH(tbPrevisoes[📅 DATA])=5)*tbPrevisoes[💰 VALOR])} -> 0 | F11: =(B11+C11)-(D11+E11) -> 468.33333 | G11: =G10+F11 -> 17614.667 | H11: =IF(G11<0,"🔴 Negativo",IF(G11<5000,"🟡 Alerta","🟢 OK")) -> 🟢 OK
A12: ="jun/"&$B$3 -> jun/2025 | B12: =SUMIFS(tb_receitas[💵 Valor],tb_receitas[📅 Data],">="&DATE($B$3,6,1),tb_receitas[📅 Data],"<"&DATE($B$3,6+1,1),tb_receitas[📊 Status],"Realizado")+SUMIFS(tb_investimentos[Valor],tb_investimentos[Data],">="&DATE($B$3,6,1),tb_investimentos[Data],"<"&DATE($B$3,6+1,1),tb_investimentos[Movimento],"Resgate") -> 15950 | C12: {=SUMPRODUCT((tbPrevisoes[📂 TIPO]="Receita")*(tbPrevisoes[✅ STATUS]="Ativa")*(YEAR(tbPrevisoes[📅 DATA])=$B$3)*(MONTH(tbPrevisoes[📅 DATA])=6)*tbPrevisoes[💰 VALOR])} -> 0 | D12: =SUMIFS(tbDespesas[💰 Valor],tbDespesas[📅 Data],">="&DATE($B$3,6,1),tbDespesas[📅 Data],"<"&DATE($B$3,6+1,1),tbDespesas[📊 Status],"Realizado")+SUMIFS(tbParcelas6[Valor_Parcela],tbParcelas6[Data_Vencimento],">="&DATE($B$3,6,1),tbParcelas6[Data_Vencimento],"<"&DATE($B$3,6+1,1)) -> 16428.333 | E12: {=SUMPRODUCT((tbPrevisoes[📂 TIPO]="Despesa")*(tbPrevisoes[✅ STATUS]="Ativa")*(YEAR(tbPrevisoes[📅 DATA])=$B$3)*(MONTH(tbPrevisoes[📅 DATA])=6)*tbPrevisoes[💰 VALOR])} -> 0 | F12: =(B12+C12)-(D12+E12) -> -478.33333 | G12: =G11+F12 -> 17136.333 | H12: =IF(G12<0,"🔴 Negativo",IF(G12<5000,"🟡 Alerta","🟢 OK")) -> 🟢 OK
A13: ="jul/"&$B$3 -> jul/2025 | B13: =SUMIFS(tb_receitas[💵 Valor],tb_receitas[📅 Data],">="&DATE($B$3,7,1),tb_receitas[📅 Data],"<"&DATE($B$3,7+1,1),tb_receitas[📊 Status],"Realizado")+SUMIFS(tb_investimentos[Valor],tb_investimentos[Data],">="&DATE($B$3,7,1),tb_investimentos[Data],"<"&DATE($B$3,7+1,1),tb_investimentos[Movimento],"Resgate") -> 16000 | C13: {=SUMPRODUCT((tbPrevisoes[📂 TIPO]="Receita")*(tbPrevisoes[✅ STATUS]="Ativa")*(YEAR(tbPrevisoes[📅 DATA])=$B$3)*(MONTH(tbPrevisoes[📅 DATA])=7)*tbPrevisoes[💰 VALOR])} -> 0 | D13: =SUMIFS(tbDespesas[💰 Valor],tbDespesas[📅 Data],">="&DATE($B$3,7,1),tbDespesas[📅 Data],"<"&DATE($B$3,7+1,1),tbDespesas[📊 Status],"Realizado")+SUMIFS(tbParcelas6[Valor_Parcela],tbParcelas6[Data_Vencimento],">="&DATE($B$3,7,1),tbParcelas6[Data_Vencimento],"<"&DATE($B$3,7+1,1)) -> 16341.667 | E13: {=SUMPRODUCT((tbPrevisoes[📂 TIPO]="Despesa")*(tbPrevisoes[✅ STATUS]="Ativa")*(YEAR(tbPrevisoes[📅 DATA])=$B$3)*(MONTH(tbPrevisoes[📅 DATA])=7)*tbPrevisoes[💰 VALOR])} -> 0 | F13: =(B13+C13)-(D13+E13) -> -341.66667 | G13: =G12+F13 -> 16794.667 | H13: =IF(G13<0,"🔴 Negativo",IF(G13<5000,"🟡 Alerta","🟢 OK")) -> 🟢 OK | K13: {=SUMPRODUCT((tbDespesas[📅 Data]>=DATE(2026,5,1))*(tbDespesas[📅 Data]<TODAY())*(tbDespesas[📊 Status]="Realizado")*(tbDespesas[💰 Valor]))} -> 0
A14: ="ago/"&$B$3 -> ago/2025 | B14: =SUMIFS(tb_receitas[💵 Valor],tb_receitas[📅 Data],">="&DATE($B$3,8,1),tb_receitas[📅 Data],"<"&DATE($B$3,8+1,1),tb_receitas[📊 Status],"Realizado")+SUMIFS(tb_investimentos[Valor],tb_investimentos[Data],">="&DATE($B$3,8,1),tb_investimentos[Data],"<"&DATE($B$3,8+1,1),tb_investimentos[Movimento],"Resgate") -> 16250 | C14: {=SUMPRODUCT((tbPrevisoes[📂 TIPO]="Receita")*(tbPrevisoes[✅ STATUS]="Ativa")*(YEAR(tbPrevisoes[📅 DATA])=$B$3)*(MONTH(tbPrevisoes[📅 DATA])=8)*tbPrevisoes[💰 VALOR])} -> 0 | D14: =SUMIFS(tbDespesas[💰 Valor],tbDespesas[📅 Data],">="&DATE($B$3,8,1),tbDespesas[📅 Data],"<"&DATE($B$3,8+1,1),tbDespesas[📊 Status],"Realizado")+SUMIFS(tbParcelas6[Valor_Parcela],tbParcelas6[Data_Vencimento],">="&DATE($B$3,8,1),tbParcelas6[Data_Vencimento],"<"&DATE($B$3,8+1,1)) -> 14511.667 | E14: {=SUMPRODUCT((tbPrevisoes[📂 TIPO]="Despesa")*(tbPrevisoes[✅ STATUS]="Ativa")*(YEAR(tbPrevisoes[📅 DATA])=$B$3)*(MONTH(tbPrevisoes[📅 DATA])=8)*tbPrevisoes[💰 VALOR])} -> 0 | F14: =(B14+C14)-(D14+E14) -> 1738.3333 | G14: =G13+F14 -> 18533 | H14: =IF(G14<0,"🔴 Negativo",IF(G14<5000,"🟡 Alerta","🟢 OK")) -> 🟢 OK | K14: {=SUMPRODUCT((tbParcelas6[Data_Vencimento]>=DATE(2026,5,1))*(tbParcelas6[Data_Vencimento]<TODAY())*(tbParcelas6[Valor_Parcela]))} -> 0
A15: ="set/"&$B$3 -> set/2025 | B15: =SUMIFS(tb_receitas[💵 Valor],tb_receitas[📅 Data],">="&DATE($B$3,9,1),tb_receitas[📅 Data],"<"&DATE($B$3,9+1,1),tb_receitas[📊 Status],"Realizado")+SUMIFS(tb_investimentos[Valor],tb_investimentos[Data],">="&DATE($B$3,9,1),tb_investimentos[Data],"<"&DATE($B$3,9+1,1),tb_investimentos[Movimento],"Resgate") -> 16050 | C15: {=SUMPRODUCT((tbPrevisoes[📂 TIPO]="Receita")*(tbPrevisoes[✅ STATUS]="Ativa")*(YEAR(tbPrevisoes[📅 DATA])=$B$3)*(MONTH(tbPrevisoes[📅 DATA])=9)*tbPrevisoes[💰 VALOR])} -> 0 | D15: =SUMIFS(tbDespesas[💰 Valor],tbDespesas[📅 Data],">="&DATE($B$3,9,1),tbDespesas[📅 Data],"<"&DATE($B$3,9+1,1),tbDespesas[📊 Status],"Realizado")+SUMIFS(tbParcelas6[Valor_Parcela],tbParcelas6[Data_Vencimento],">="&DATE($B$3,9,1),tbParcelas6[Data_Vencimento],"<"&DATE($B$3,9+1,1)) -> 15540 | E15: {=SUMPRODUCT((tbPrevisoes[📂 TIPO]="Despesa")*(tbPrevisoes[✅ STATUS]="Ativa")*(YEAR(tbPrevisoes[📅 DATA])=$B$3)*(MONTH(tbPrevisoes[📅 DATA])=9)*tbPrevisoes[💰 VALOR])} -> 0 | F15: =(B15+C15)-(D15+E15) -> 510 | G15: =G14+F15 -> 19043 | H15: =IF(G15<0,"🔴 Negativo",IF(G15<5000,"🟡 Alerta","🟢 OK")) -> 🟢 OK | K15: {=SUMPRODUCT((tb_investimentos[Data]>=DATE(2026,5,1))*(tb_investimentos[Data]<TODAY())*(tb_investimentos[Movimento]="Aporte")*(tb_investimentos[Valor]))-SUMPRODUCT((tb_investimentos[Data]>=DATE(2026,5,1))*(tb_investimentos[Data]<TODAY())*(tb_investimentos[Movimento]="Resgate")*(tb_investimentos[Valor]))} -> 0
A16: ="out/"&$B$3 -> out/2025 | B16: =SUMIFS(tb_receitas[💵 Valor],tb_receitas[📅 Data],">="&DATE($B$3,10,1),tb_receitas[📅 Data],"<"&DATE($B$3,10+1,1),tb_receitas[📊 Status],"Realizado")+SUMIFS(tb_investimentos[Valor],tb_investimentos[Data],">="&DATE($B$3,10,1),tb_investimentos[Data],"<"&DATE($B$3,10+1,1),tb_investimentos[Movimento],"Resgate") -> 16000 | C16: {=SUMPRODUCT((tbPrevisoes[📂 TIPO]="Receita")*(tbPrevisoes[✅ STATUS]="Ativa")*(YEAR(tbPrevisoes[📅 DATA])=$B$3)*(MONTH(tbPrevisoes[📅 DATA])=10)*tbPrevisoes[💰 VALOR])} -> 0 | D16: =SUMIFS(tbDespesas[💰 Valor],tbDespesas[📅 Data],">="&DATE($B$3,10,1),tbDespesas[📅 Data],"<"&DATE($B$3,10+1,1),tbDespesas[📊 Status],"Realizado")+SUMIFS(tbParcelas6[Valor_Parcela],tbParcelas6[Data_Vencimento],">="&DATE($B$3,10,1),tbParcelas6[Data_Vencimento],"<"&DATE($B$3,10+1,1)) -> 15770 | E16: {=SUMPRODUCT((tbPrevisoes[📂 TIPO]="Despesa")*(tbPrevisoes[✅ STATUS]="Ativa")*(YEAR(tbPrevisoes[📅 DATA])=$B$3)*(MONTH(tbPrevisoes[📅 DATA])=10)*tbPrevisoes[💰 VALOR])} -> 0 | F16: =(B16+C16)-(D16+E16) -> 230 | G16: =G15+F16 -> 19273 | H16: =IF(G16<0,"🔴 Negativo",IF(G16<5000,"🟡 Alerta","🟢 OK")) -> 🟢 OK
A17: ="nov/"&$B$3 -> nov/2025 | B17: =SUMIFS(tb_receitas[💵 Valor],tb_receitas[📅 Data],">="&DATE($B$3,11,1),tb_receitas[📅 Data],"<"&DATE($B$3,11+1,1),tb_receitas[📊 Status],"Realizado")+SUMIFS(tb_investimentos[Valor],tb_investimentos[Data],">="&DATE($B$3,11,1),tb_investimentos[Data],"<"&DATE($B$3,11+1,1),tb_investimentos[Movimento],"Resgate") -> 16500 | C17: {=SUMPRODUCT((tbPrevisoes[📂 TIPO]="Receita")*(tbPrevisoes[✅ STATUS]="Ativa")*(YEAR(tbPrevisoes[📅 DATA])=$B$3)*(MONTH(tbPrevisoes[📅 DATA])=11)*tbPrevisoes[💰 VALOR])} -> 0 | D17: =SUMIFS(tbDespesas[💰 Valor],tbDespesas[📅 Data],">="&DATE($B$3,11,1),tbDespesas[📅 Data],"<"&DATE($B$3,11+1,1),tbDespesas[📊 Status],"Realizado")+SUMIFS(tbParcelas6[Valor_Parcela],tbParcelas6[Data_Vencimento],">="&DATE($B$3,11,1),tbParcelas6[Data_Vencimento],"<"&DATE($B$3,11+1,1)) -> 14956.667 | E17: {=SUMPRODUCT((tbPrevisoes[📂 TIPO]="Despesa")*(tbPrevisoes[✅ STATUS]="Ativa")*(YEAR(tbPrevisoes[📅 DATA])=$B$3)*(MONTH(tbPrevisoes[📅 DATA])=11)*tbPrevisoes[💰 VALOR])} -> 0 | F17: =(B17+C17)-(D17+E17) -> 1543.3333 | G17: =G16+F17 -> 20816.333 | H17: =IF(G17<0,"🔴 Negativo",IF(G17<5000,"🟡 Alerta","🟢 OK")) -> 🟢 OK
A18: ="dez/"&$B$3 -> dez/2025 | B18: =SUMIFS(tb_receitas[💵 Valor],tb_receitas[📅 Data],">="&DATE($B$3,12,1),tb_receitas[📅 Data],"<"&DATE($B$3,12+1,1),tb_receitas[📊 Status],"Realizado")+SUMIFS(tb_investimentos[Valor],tb_investimentos[Data],">="&DATE($B$3,12,1),tb_investimentos[Data],"<"&DATE($B$3,12+1,1),tb_investimentos[Movimento],"Resgate") -> 16600 | C18: {=SUMPRODUCT((tbPrevisoes[📂 TIPO]="Receita")*(tbPrevisoes[✅ STATUS]="Ativa")*(YEAR(tbPrevisoes[📅 DATA])=$B$3)*(MONTH(tbPrevisoes[📅 DATA])=12)*tbPrevisoes[💰 VALOR])} -> 0 | D18: =SUMIFS(tbDespesas[💰 Valor],tbDespesas[📅 Data],">="&DATE($B$3,12,1),tbDespesas[📅 Data],"<"&DATE($B$3,12+1,1),tbDespesas[📊 Status],"Realizado")+SUMIFS(tbParcelas6[Valor_Parcela],tbParcelas6[Data_Vencimento],">="&DATE($B$3,12,1),tbParcelas6[Data_Vencimento],"<"&DATE($B$3,12+1,1)) -> 16706.667 | E18: {=SUMPRODUCT((tbPrevisoes[📂 TIPO]="Despesa")*(tbPrevisoes[✅ STATUS]="Ativa")*(YEAR(tbPrevisoes[📅 DATA])=$B$3)*(MONTH(tbPrevisoes[📅 DATA])=12)*tbPrevisoes[💰 VALOR])} -> 0 | F18: =(B18+C18)-(D18+E18) -> -106.66667 | G18: =G17+F18 -> 20709.667 | H18: =IF(G18<0,"🔴 Negativo",IF(G18<5000,"🟡 Alerta","🟢 OK")) -> 🟢 OK
A19: TOTAL ANUAL | B19: =SUM(B7:B18) -> 194000 | C19: =SUM(C7:C18) -> 0 | D19: =SUM(D7:D18) -> 183290.33 | E19: =SUM(E7:E18) -> 0 | F19: =(B19+C19)-(D19+E19) -> 10709.667 | G19: =G18 -> 20709.667
A21: 📊 FLUXO DE CAIXA - PRÓXIMOS 30 DIAS
B22: 💰 SALDO INICIAL: R$ | C22: {=IFERROR(INDEX(G$7:G$18,MATCH(EOMONTH($J$3,-1),A$7:A$18,0)),$B$4)+SUMPRODUCT((tb_receitas[📅 Data]>=DATE(YEAR($J$3),MONTH($J$3),1))*(tb_receitas[📅 Data]<$J$3)*(tb_receitas[📊 Status]="Realizado")*(tb_receitas[💵 Valor]))-SUMPRODUCT((tbDespesas[📅 Data]>=DATE(YEAR($J$3),MONTH($J$3),1))*(tbDespesas[📅 Data]<$J$3)*(tbDespesas[📊 Status]="Realizado")*(tbDespesas[💰 Valor]))-SUMPRODUCT((tbParcelas6[Data_Vencimento]>=DATE(YEAR($J$3),MONTH($J$3),1))*(tbParcelas6[Data_Vencimento]<$J$3)*(tbParcelas6[Valor_Parcela]))} -> 14468.333
A23: # | B23: 📅 Data | C23: 📆 Dia | D23: 💰 Entradas | E23: 📉 Saídas | F23: 💵 Saldo Dia | G23: 📊 Saldo Acum. | I23: 🎨 LEGENDA
A24: 1 | B24: =$J$3+0 -> 45795 | C24: =TEXT(B24,"ddd") -> dom | D24: {=SUMPRODUCT((tb_receitas[📅 Data]=$B24)*(tb_receitas[📊 Status]="Realizado")*tb_receitas[💵 Valor])+SUMPRODUCT((tb_receitas[📅 Data]=$B24)*(tb_receitas[📊 Status]="Previsto")*tb_receitas[💵 Valor])+SUMPRODUCT((tbPrevisoes[📅 DATA]=$B24)*(tbPrevisoes[📂 TIPO]="Receita")*(tbPrevisoes[✅ STATUS]="Ativa")*tbPrevisoes[💰 VALOR])} -> 0 | E24: {=SUMPRODUCT((tbDespesas[📅 Data]=$B24)*(tbDespesas[📊 Status]="Realizado")*tbDespesas[💰 Valor])+SUMPRODUCT((tbDespesas[📅 Data]=$B24)*(tbDespesas[📊 Status]="Previsto")*tbDespesas[💰 Valor])+SUMPRODUCT((tbParcelas6[Data_Vencimento]=$B24)*tbParcelas6[Valor_Parcela])+SUMPRODUCT((tbPrevisoes[📅 DATA]=$B24)*(tbPrevisoes[📂 TIPO]="Despesa")*(tbPrevisoes[✅ STATUS]="Ativa")*tbPrevisoes[💰 VALOR])} -> 0 | F24: =D24-E24 -> 0 | G24: =$C$22+F24 -> 14468.333 | H24: =IF(B24=TODAY(),"📅","")
A25: 2 | B25: =$J$3+1 -> 45796 | C25: =TEXT(B25,"ddd") -> seg | D25: {=SUMPRODUCT((tb_receitas[📅 Data]=$B25)*(tb_receitas[📊 Status]="Realizado")*tb_receitas[💵 Valor])+SUMPRODUCT((tb_receitas[📅 Data]=$B25)*(tb_receitas[📊 Status]="Previsto")*tb_receitas[💵 Valor])+SUMPRODUCT((tbPrevisoes[📅 DATA]=$B25)*(tbPrevisoes[📂 TIPO]="Receita")*(tbPrevisoes[✅ STATUS]="Ativa")*tbPrevisoes[💰 VALOR])} -> 0 | E25: {=SUMPRODUCT((tbDespesas[📅 Data]=$B25)*(tbDespesas[📊 Status]="Realizado")*tbDespesas[💰 Valor])+SUMPRODUCT((tbDespesas[📅 Data]=$B25)*(tbDespesas[📊 Status]="Previsto")*tbDespesas[💰 Valor])+SUMPRODUCT((tbParcelas6[Data_Vencimento]=$B25)*tbParcelas6[Valor_Parcela])+SUMPRODUCT((tbPrevisoes[📅 DATA]=$B25)*(tbPrevisoes[📂 TIPO]="Despesa")*(tbPrevisoes[✅ STATUS]="Ativa")*tbPrevisoes[💰 VALOR])} -> 1104 | F25: =D25-E25 -> -1104 | G25: =G24+F25 -> 13364.333 | H25: =IF(B25=TODAY(),"📅","")
A26: 3 | B26: =$J$3+2 -> 45797 | C26: =TEXT(B26,"ddd") -> ter | D26: {=SUMPRODUCT((tb_receitas[📅 Data]=$B26)*(tb_receitas[📊 Status]="Realizado")*tb_receitas[💵 Valor])+SUMPRODUCT((tb_receitas[📅 Data]=$B26)*(tb_receitas[📊 Status]="Previsto")*tb_receitas[💵 Valor])+SUMPRODUCT((tbPrevisoes[📅 DATA]=$B26)*(tbPrevisoes[📂 TIPO]="Receita")*(tbPrevisoes[✅ STATUS]="Ativa")*tbPrevisoes[💰 VALOR])} -> 0 | E26: {=SUMPRODUCT((tbDespesas[📅 Data]=$B26)*(tbDespesas[📊 Status]="Realizado")*tbDespesas[💰 Valor])+SUMPRODUCT((tbDespesas[📅 Data]=$B26)*(tbDespesas[📊 Status]="Previsto")*tbDespesas[💰 Valor])+SUMPRODUCT((tbParcelas6[Data_Vencimento]=$B26)*tbParcelas6[Valor_Parcela])+SUMPRODUCT((tbPrevisoes[📅 DATA]=$B26)*(tbPrevisoes[📂 TIPO]="Despesa")*(tbPrevisoes[✅ STATUS]="Ativa")*tbPrevisoes[💰 VALOR])} -> 0 | F26: =D26-E26 -> 0 | G26: =G25+F26 -> 13364.333 | H26: =IF(B26=TODAY(),"📅","")
A27: 4 | B27: =$J$3+3 -> 45798 | C27: =TEXT(B27,"ddd") -> qua | D27: {=SUMPRODUCT((tb_receitas[📅 Data]=$B27)*(tb_receitas[📊 Status]="Realizado")*tb_receitas[💵 Valor])+SUMPRODUCT((tb_receitas[📅 Data]=$B27)*(tb_receitas[📊 Status]="Previsto")*tb_receitas[💵 Valor])+SUMPRODUCT((tbPrevisoes[📅 DATA]=$B27)*(tbPrevisoes[📂 TIPO]="Receita")*(tbPrevisoes[✅ STATUS]="Ativa")*tbPrevisoes[💰 VALOR])} -> 0 | E27: {=SUMPRODUCT((tbDespesas[📅 Data]=$B27)*(tbDespesas[📊 Status]="Realizado")*tbDespesas[💰 Valor])+SUMPRODUCT((tbDespesas[📅 Data]=$B27)*(tbDespesas[📊 Status]="Previsto")*tbDespesas[💰 Valor])+SUMPRODUCT((tbParcelas6[Data_Vencimento]=$B27)*tbParcelas6[Valor_Parcela])+SUMPRODUCT((tbPrevisoes[📅 DATA]=$B27)*(tbPrevisoes[📂 TIPO]="Despesa")*(tbPrevisoes[✅ STATUS]="Ativa")*tbPrevisoes[💰 VALOR])} -> 300 | F27: =D27-E27 -> -300 | G27: =G26+F27 -> 13064.333 | H27: =IF(B27=TODAY(),"📅","")
A28: 5 | B28: =$J$3+4 -> 45799 | C28: =TEXT(B28,"ddd") -> qui | D28: {=SUMPRODUCT((tb_receitas[📅 Data]=$B28)*(tb_receitas[📊 Status]="Realizado")*tb_receitas[💵 Valor])+SUMPRODUCT((tb_receitas[📅 Data]=$B28)*(tb_receitas[📊 Status]="Previsto")*tb_receitas[💵 Valor])+SUMPRODUCT((tbPrevisoes[📅 DATA]=$B28)*(tbPrevisoes[📂 TIPO]="Receita")*(tbPrevisoes[✅ STATUS]="Ativa")*tbPrevisoes[💰 VALOR])} -> 0 | E28: {=SUMPRODUCT((tbDespesas[📅 Data]=$B28)*(tbDespesas[📊 Status]="Realizado")*tbDespesas[💰 Valor])+SUMPRODUCT((tbDespesas[📅 Data]=$B28)*(tbDespesas[📊 Status]="Previsto")*tbDespesas[💰 Valor])+SUMPRODUCT((tbParcelas6[Data_Vencimento]=$B28)*tbParcelas6[Valor_Parcela])+SUMPRODUCT((tbPrevisoes[📅 DATA]=$B28)*(tbPrevisoes[📂 TIPO]="Despesa")*(tbPrevisoes[✅ STATUS]="Ativa")*tbPrevisoes[💰 VALOR])} -> 0 | F28: =D28-E28 -> 0 | G28: =G27+F28 -> 13064.333 | H28: =IF(B28=TODAY(),"📅","")
A29: 6 | B29: =$J$3+5 -> 45800 | C29: =TEXT(B29,"ddd") -> sex | D29: {=SUMPRODUCT((tb_receitas[📅 Data]=$B29)*(tb_receitas[📊 Status]="Realizado")*tb_receitas[💵 Valor])+SUMPRODUCT((tb_receitas[📅 Data]=$B29)*(tb_receitas[📊 Status]="Previsto")*tb_receitas[💵 Valor])+SUMPRODUCT((tbPrevisoes[📅 DATA]=$B29)*(tbPrevisoes[📂 TIPO]="Receita")*(tbPrevisoes[✅ STATUS]="Ativa")*tbPrevisoes[💰 VALOR])} -> 0 | E29: {=SUMPRODUCT((tbDespesas[📅 Data]=$B29)*(tbDespesas[📊 Status]="Realizado")*tbDespesas[💰 Valor])+SUMPRODUCT((tbDespesas[📅 Data]=$B29)*(tbDespesas[📊 Status]="Previsto")*tbDespesas[💰 Valor])+SUMPRODUCT((tbParcelas6[Data_Vencimento]=$B29)*tbParcelas6[Valor_Parcela])+SUMPRODUCT((tbPrevisoes[📅 DATA]=$B29)*(tbPrevisoes[📂 TIPO]="Despesa")*(tbPrevisoes[✅ STATUS]="Ativa")*tbPrevisoes[💰 VALOR])} -> 0 | F29: =D29-E29 -> 0 | G29: =G28+F29 -> 13064.333 | H29: =IF(B29=TODAY(),"📅","")
A30: 7 | B30: =$J$3+6 -> 45801 | C30: =TEXT(B30,"ddd") -> sáb | D30: {=SUMPRODUCT((tb_receitas[📅 Data]=$B30)*(tb_receitas[📊 Status]="Realizado")*tb_receitas[💵 Valor])+SUMPRODUCT((tb_receitas[📅 Data]=$B30)*(tb_receitas[📊 Status]="Previsto")*tb_receitas[💵 Valor])+SUMPRODUCT((tbPrevisoes[📅 DATA]=$B30)*(tbPrevisoes[📂 TIPO]="Receita")*(tbPrevisoes[✅ STATUS]="Ativa")*tbPrevisoes[💰 VALOR])} -> 500 | E30: {=SUMPRODUCT((tbDespesas[📅 Data]=$B30)*(tbDespesas[📊 Status]="Realizado")*tbDespesas[💰 Valor])+SUMPRODUCT((tbDespesas[📅 Data]=$B30)*(tbDespesas[📊 Status]="Previsto")*tbDespesas[💰 Valor])+SUMPRODUCT((tbParcelas6[Data_Vencimento]=$B30)*tbParcelas6[Valor_Parcela])+SUMPRODUCT((tbPrevisoes[📅 DATA]=$B30)*(tbPrevisoes[📂 TIPO]="Despesa")*(tbPrevisoes[✅ STATUS]="Ativa")*tbPrevisoes[💰 VALOR])} -> 1816 | F30: =D30-E30 -> -1316 | G30: =G29+F30 -> 11748.333 | H30: =IF(B30=TODAY(),"📅","")
A31: 8 | B31: =$J$3+7 -> 45802 | C31: =TEXT(B31,"ddd") -> dom | D31: {=SUMPRODUCT((tb_receitas[📅 Data]=$B31)*(tb_receitas[📊 Status]="Realizado")*tb_receitas[💵 Valor])+SUMPRODUCT((tb_receitas[📅 Data]=$B31)*(tb_receitas[📊 Status]="Previsto")*tb_receitas[💵 Valor])+SUMPRODUCT((tbPrevisoes[📅 DATA]=$B31)*(tbPrevisoes[📂 TIPO]="Receita")*(tbPrevisoes[✅ STATUS]="Ativa")*tbPrevisoes[💰 VALOR])} -> 0 | E31: {=SUMPRODUCT((tbDespesas[📅 Data]=$B31)*(tbDespesas[📊 Status]="Realizado")*tbDespesas[💰 Valor])+SUMPRODUCT((tbDespesas[📅 Data]=$B31)*(tbDespesas[📊 Status]="Previsto")*tbDespesas[💰 Valor])+SUMPRODUCT((tbParcelas6[Data_Vencimento]=$B31)*tbParcelas6[Valor_Parcela])+SUMPRODUCT((tbPrevisoes[📅 DATA]=$B31)*(tbPrevisoes[📂 TIPO]="Despesa")*(tbPrevisoes[✅ STATUS]="Ativa")*tbPrevisoes[💰 VALOR])} -> 0 | F31: =D31-E31 -> 0 | G31: =G30+F31 -> 11748.333 | H31: =IF(B31=TODAY(),"📅","")
A32: 9 | B32: =$J$3+8 -> 45803 | C32: =TEXT(B32,"ddd") -> seg | D32: {=SUMPRODUCT((tb_receitas[📅 Data]=$B32)*(tb_receitas[📊 Status]="Realizado")*tb_receitas[💵 Valor])+SUMPRODUCT((tb_receitas[📅 Data]=$B32)*(tb_receitas[📊 Status]="Previsto")*tb_receitas[💵 Valor])+SUMPRODUCT((tbPrevisoes[📅 DATA]=$B32)*(tbPrevisoes[📂 TIPO]="Receita")*(tbPrevisoes[✅ STATUS]="Ativa")*tbPrevisoes[💰 VALOR])} -> 0 | E32: {=SUMPRODUCT((tbDespesas[📅 Data]=$B32)*(tbDespesas[📊 Status]="Realizado")*tbDespesas[💰 Valor])+SUMPRODUCT((tbDespesas[📅 Data]=$B32)*(tbDespesas[📊 Status]="Previsto")*tbDespesas[💰 Valor])+SUMPRODUCT((tbParcelas6[Data_Vencimento]=$B32)*tbParcelas6[Valor_Parcela])+SUMPRODUCT((tbPrevisoes[📅 DATA]=$B32)*(tbPrevisoes[📂 TIPO]="Despesa")*(tbPrevisoes[✅ STATUS]="Ativa")*tbPrevisoes[💰 VALOR])} -> 0 | F32: =D32-E32 -> 0 | G32: =G31+F32 -> 11748.333 | H32: =IF(B32=TODAY(),"📅","")
A33: 10 | B33: =$J$3+9 -> 45804 | C33: =TEXT(B33,"ddd") -> ter | D33: {=SUMPRODUCT((tb_receitas[📅 Data]=$B33)*(tb_receitas[📊 Status]="Realizado")*tb_receitas[💵 Valor])+SUMPRODUCT((tb_receitas[📅 Data]=$B33)*(tb_receitas[📊 Status]="Previsto")*tb_receitas[💵 Valor])+SUMPRODUCT((tbPrevisoes[📅 DATA]=$B33)*(tbPrevisoes[📂 TIPO]="Receita")*(tbPrevisoes[✅ STATUS]="Ativa")*tbPrevisoes[💰 VALOR])} -> 0 | E33: {=SUMPRODUCT((tbDespesas[📅 Data]=$B33)*(tbDespesas[📊 Status]="Realizado")*tbDespesas[💰 Valor])+SUMPRODUCT((tbDespesas[📅 Data]=$B33)*(tbDespesas[📊 Status]="Previsto")*tbDespesas[💰 Valor])+SUMPRODUCT((tbParcelas6[Data_Vencimento]=$B33)*tbParcelas6[Valor_Parcela])+SUMPRODUCT((tbPrevisoes[📅 DATA]=$B33)*(tbPrevisoes[📂 TIPO]="Despesa")*(tbPrevisoes[✅ STATUS]="Ativa")*tbPrevisoes[💰 VALOR])} -> 720 | F33: =D33-E33 -> -720 | G33: =G32+F33 -> 11028.333 | H33: =IF(B33=TODAY(),"📅","")
A34: 11 | B34: =$J$3+10 -> 45805 | C34: =TEXT(B34,"ddd") -> qua | D34: {=SUMPRODUCT((tb_receitas[📅 Data]=$B34)*(tb_receitas[📊 Status]="Realizado")*tb_receitas[💵 Valor])+SUMPRODUCT((tb_receitas[📅 Data]=$B34)*(tb_receitas[📊 Status]="Previsto")*tb_receitas[💵 Valor])+SUMPRODUCT((tbPrevisoes[📅 DATA]=$B34)*(tbPrevisoes[📂 TIPO]="Receita")*(tbPrevisoes[✅ STATUS]="Ativa")*tbPrevisoes[💰 VALOR])} -> 0 | E34: {=SUMPRODUCT((tbDespesas[📅 Data]=$B34)*(tbDespesas[📊 Status]="Realizado")*tbDespesas[💰 Valor])+SUMPRODUCT((tbDespesas[📅 Data]=$B34)*(tbDespesas[📊 Status]="Previsto")*tbDespesas[💰 Valor])+SUMPRODUCT((tbParcelas6[Data_Vencimento]=$B34)*tbParcelas6[Valor_Parcela])+SUMPRODUCT((tbPrevisoes[📅 DATA]=$B34)*(tbPrevisoes[📂 TIPO]="Despesa")*(tbPrevisoes[✅ STATUS]="Ativa")*tbPrevisoes[💰 VALOR])} -> 0 | F34: =D34-E34 -> 0 | G34: =G33+F34 -> 11028.333 | H34: =IF(B34=TODAY(),"📅","")
A35: 12 | B35: =$J$3+11 -> 45806 | C35: =TEXT(B35,"ddd") -> qui | D35: {=SUMPRODUCT((tb_receitas[📅 Data]=$B35)*(tb_receitas[📊 Status]="Realizado")*tb_receitas[💵 Valor])+SUMPRODUCT((tb_receitas[📅 Data]=$B35)*(tb_receitas[📊 Status]="Previsto")*tb_receitas[💵 Valor])+SUMPRODUCT((tbPrevisoes[📅 DATA]=$B35)*(tbPrevisoes[📂 TIPO]="Receita")*(tbPrevisoes[✅ STATUS]="Ativa")*tbPrevisoes[💰 VALOR])} -> 0 | E35: {=SUMPRODUCT((tbDespesas[📅 Data]=$B35)*(tbDespesas[📊 Status]="Realizado")*tbDespesas[💰 Valor])+SUMPRODUCT((tbDespesas[📅 Data]=$B35)*(tbDespesas[📊 Status]="Previsto")*tbDespesas[💰 Valor])+SUMPRODUCT((tbParcelas6[Data_Vencimento]=$B35)*tbParcelas6[Valor_Parcela])+SUMPRODUCT((tbPrevisoes[📅 DATA]=$B35)*(tbPrevisoes[📂 TIPO]="Despesa")*(tbPrevisoes[✅ STATUS]="Ativa")*tbPrevisoes[💰 VALOR])} -> 0 | F35: =D35-E35 -> 0 | G35: =G34+F35 -> 11028.333 | H35: =IF(B35=TODAY(),"📅","")
A36: 13 | B36: =$J$3+12 -> 45807 | C36: =TEXT(B36,"ddd") -> sex | D36: {=SUMPRODUCT((tb_receitas[📅 Data]=$B36)*(tb_receitas[📊 Status]="Realizado")*tb_receitas[💵 Valor])+SUMPRODUCT((tb_receitas[📅 Data]=$B36)*(tb_receitas[📊 Status]="Previsto")*tb_receitas[💵 Valor])+SUMPRODUCT((tbPrevisoes[📅 DATA]=$B36)*(tbPrevisoes[📂 TIPO]="Receita")*(tbPrevisoes[✅ STATUS]="Ativa")*tbPrevisoes[💰 VALOR])} -> 0 | E36: {=SUMPRODUCT((tbDespesas[📅 Data]=$B36)*(tbDespesas[📊 Status]="Realizado")*tbDespesas[💰 Valor])+SUMPRODUCT((tbDespesas[📅 Data]=$B36)*(tbDespesas[📊 Status]="Previsto")*tbDespesas[💰 Valor])+SUMPRODUCT((tbParcelas6[Data_Vencimento]=$B36)*tbParcelas6[Valor_Parcela])+SUMPRODUCT((tbPrevisoes[📅 DATA]=$B36)*(tbPrevisoes[📂 TIPO]="Despesa")*(tbPrevisoes[✅ STATUS]="Ativa")*tbPrevisoes[💰 VALOR])} -> 0 | F36: =D36-E36 -> 0 | G36: =G35+F36 -> 11028.333 | H36: =IF(B36=TODAY(),"📅","")
A37: 14 | B37: =$J$3+13 -> 45808 | C37: =TEXT(B37,"ddd") -> sáb | D37: {=SUMPRODUCT((tb_receitas[📅 Data]=$B37)*(tb_receitas[📊 Status]="Realizado")*tb_receitas[💵 Valor])+SUMPRODUCT((tb_receitas[📅 Data]=$B37)*(tb_receitas[📊 Status]="Previsto")*tb_receitas[💵 Valor])+SUMPRODUCT((tbPrevisoes[📅 DATA]=$B37)*(tbPrevisoes[📂 TIPO]="Receita")*(tbPrevisoes[✅ STATUS]="Ativa")*tbPrevisoes[💰 VALOR])} -> 500 | E37: {=SUMPRODUCT((tbDespesas[📅 Data]=$B37)*(tbDespesas[📊 Status]="Realizado")*tbDespesas[💰 Valor])+SUMPRODUCT((tbDespesas[📅 Data]=$B37)*(tbDespesas[📊 Status]="Previsto")*tbDespesas[💰 Valor])+SUMPRODUCT((tbParcelas6[Data_Vencimento]=$B37)*tbParcelas6[Valor_Parcela])+SUMPRODUCT((tbPrevisoes[📅 DATA]=$B37)*(tbPrevisoes[📂 TIPO]="Despesa")*(tbPrevisoes[✅ STATUS]="Ativa")*tbPrevisoes[💰 VALOR])} -> 100 | F37: =D37-E37 -> 400 | G37: =G36+F37 -> 11428.333 | H37: =IF(B37=TODAY(),"📅","")
A38: 15 | B38: =$J$3+14 -> 45809 | C38: =TEXT(B38,"ddd") -> dom | D38: {=SUMPRODUCT((tb_receitas[📅 Data]=$B38)*(tb_receitas[📊 Status]="Realizado")*tb_receitas[💵 Valor])+SUMPRODUCT((tb_receitas[📅 Data]=$B38)*(tb_receitas[📊 Status]="Previsto")*tb_receitas[💵 Valor])+SUMPRODUCT((tbPrevisoes[📅 DATA]=$B38)*(tbPrevisoes[📂 TIPO]="Receita")*(tbPrevisoes[✅ STATUS]="Ativa")*tbPrevisoes[💰 VALOR])} -> 0 | E38: {=SUMPRODUCT((tbDespesas[📅 Data]=$B38)*(tbDespesas[📊 Status]="Realizado")*tbDespesas[💰 Valor])+SUMPRODUCT((tbDespesas[📅 Data]=$B38)*(tbDespesas[📊 Status]="Previsto")*tbDespesas[💰 Valor])+SUMPRODUCT((tbParcelas6[Data_Vencimento]=$B38)*tbParcelas6[Valor_Parcela])+SUMPRODUCT((tbPrevisoes[📅 DATA]=$B38)*(tbPrevisoes[📂 TIPO]="Despesa")*(tbPrevisoes[✅ STATUS]="Ativa")*tbPrevisoes[💰 VALOR])} -> 0 | F38: =D38-E38 -> 0 | G38: =G37+F38 -> 11428.333 | H38: =IF(B38=TODAY(),"📅","")
A39: 16 | B39: =$J$3+15 -> 45810 | C39: =TEXT(B39,"ddd") -> seg | D39: {=SUMPRODUCT((tb_receitas[📅 Data]=$B39)*(tb_receitas[📊 Status]="Realizado")*tb_receitas[💵 Valor])+SUMPRODUCT((tb_receitas[📅 Data]=$B39)*(tb_receitas[📊 Status]="Previsto")*tb_receitas[💵 Valor])+SUMPRODUCT((tbPrevisoes[📅 DATA]=$B39)*(tbPrevisoes[📂 TIPO]="Receita")*(tbPrevisoes[✅ STATUS]="Ativa")*tbPrevisoes[💰 VALOR])} -> 0 | E39: {=SUMPRODUCT((tbDespesas[📅 Data]=$B39)*(tbDespesas[📊 Status]="Realizado")*tbDespesas[💰 Valor])+SUMPRODUCT((tbDespesas[📅 Data]=$B39)*(tbDespesas[📊 Status]="Previsto")*tbDespesas[💰 Valor])+SUMPRODUCT((tbParcelas6[Data_Vencimento]=$B39)*tbParcelas6[Valor_Parcela])+SUMPRODUCT((tbPrevisoes[📅 DATA]=$B39)*(tbPrevisoes[📂 TIPO]="Despesa")*(tbPrevisoes[✅ STATUS]="Ativa")*tbPrevisoes[💰 VALOR])} -> 0 | F39: =D39-E39 -> 0 | G39: =G38+F39 -> 11428.333 | H39: =IF(B39=TODAY(),"📅","")
A40: 17 | B40: =$J$3+16 -> 45811 | C40: =TEXT(B40,"ddd") -> ter | D40: {=SUMPRODUCT((tb_receitas[📅 Data]=$B40)*(tb_receitas[📊 Status]="Realizado")*tb_receitas[💵 Valor])+SUMPRODUCT((tb_receitas[📅 Data]=$B40)*(tb_receitas[📊 Status]="Previsto")*tb_receitas[💵 Valor])+SUMPRODUCT((tbPrevisoes[📅 DATA]=$B40)*(tbPrevisoes[📂 TIPO]="Receita")*(tbPrevisoes[✅ STATUS]="Ativa")*tbPrevisoes[💰 VALOR])} -> 0 | E40: {=SUMPRODUCT((tbDespesas[📅 Data]=$B40)*(tbDespesas[📊 Status]="Realizado")*tbDespesas[💰 Valor])+SUMPRODUCT((tbDespesas[📅 Data]=$B40)*(tbDespesas[📊 Status]="Previsto")*tbDespesas[💰 Valor])+SUMPRODUCT((tbParcelas6[Data_Vencimento]=$B40)*tbParcelas6[Valor_Parcela])+SUMPRODUCT((tbPrevisoes[📅 DATA]=$B40)*(tbPrevisoes[📂 TIPO]="Despesa")*(tbPrevisoes[✅ STATUS]="Ativa")*tbPrevisoes[💰 VALOR])} -> 0 | F40: =D40-E40 -> 0 | G40: =G39+F40 -> 11428.333 | H40: =IF(B40=TODAY(),"📅","")
A41: 18 | B41: =$J$3+17 -> 45812 | C41: =TEXT(B41,"ddd") -> qua | D41: {=SUMPRODUCT((tb_receitas[📅 Data]=$B41)*(tb_receitas[📊 Status]="Realizado")*tb_receitas[💵 Valor])+SUMPRODUCT((tb_receitas[📅 Data]=$B41)*(tb_receitas[📊 Status]="Previsto")*tb_receitas[💵 Valor])+SUMPRODUCT((tbPrevisoes[📅 DATA]=$B41)*(tbPrevisoes[📂 TIPO]="Receita")*(tbPrevisoes[✅ STATUS]="Ativa")*tbPrevisoes[💰 VALOR])} -> 8500 | E41: {=SUMPRODUCT((tbDespesas[📅 Data]=$B41)*(tbDespesas[📊 Status]="Realizado")*tbDespesas[💰 Valor])+SUMPRODUCT((tbDespesas[📅 Data]=$B41)*(tbDespesas[📊 Status]="Previsto")*tbDespesas[💰 Valor])+SUMPRODUCT((tbParcelas6[Data_Vencimento]=$B41)*tbParcelas6[Valor_Parcela])+SUMPRODUCT((tbPrevisoes[📅 DATA]=$B41)*(tbPrevisoes[📂 TIPO]="Despesa")*(tbPrevisoes[✅ STATUS]="Ativa")*tbPrevisoes[💰 VALOR])} -> 2886 | F41: =D41-E41 -> 5614 | G41: =G40+F41 -> 17042.333 | H41: =IF(B41=TODAY(),"📅","")
A42: 19 | B42: =$J$3+18 -> 45813 | C42: =TEXT(B42,"ddd") -> qui | D42: {=SUMPRODUCT((tb_receitas[📅 Data]=$B42)*(tb_receitas[📊 Status]="Realizado")*tb_receitas[💵 Valor])+SUMPRODUCT((tb_receitas[📅 Data]=$B42)*(tb_receitas[📊 Status]="Previsto")*tb_receitas[💵 Valor])+SUMPRODUCT((tbPrevisoes[📅 DATA]=$B42)*(tbPrevisoes[📂 TIPO]="Receita")*(tbPrevisoes[✅ STATUS]="Ativa")*tbPrevisoes[💰 VALOR])} -> 0 | E42: {=SUMPRODUCT((tbDespesas[📅 Data]=$B42)*(tbDespesas[📊 Status]="Realizado")*tbDespesas[💰 Valor])+SUMPRODUCT((tbDespesas[📅 Data]=$B42)*(tbDespesas[📊 Status]="Previsto")*tbDespesas[💰 Valor])+SUMPRODUCT((tbParcelas6[Data_Vencimento]=$B42)*tbParcelas6[Valor_Parcela])+SUMPRODUCT((tbPrevisoes[📅 DATA]=$B42)*(tbPrevisoes[📂 TIPO]="Despesa")*(tbPrevisoes[✅ STATUS]="Ativa")*tbPrevisoes[💰 VALOR])} -> 0 | F42: =D42-E42 -> 0 | G42: =G41+F42 -> 17042.333 | H42: =IF(B42=TODAY(),"📅","")
A43: 20 | B43: =$J$3+19 -> 45814 | C43: =TEXT(B43,"ddd") -> sex | D43: {=SUMPRODUCT((tb_receitas[📅 Data]=$B43)*(tb_receitas[📊 Status]="Realizado")*tb_receitas[💵 Valor])+SUMPRODUCT((tb_receitas[📅 Data]=$B43)*(tb_receitas[📊 Status]="Previsto")*tb_receitas[💵 Valor])+SUMPRODUCT((tbPrevisoes[📅 DATA]=$B43)*(tbPrevisoes[📂 TIPO]="Receita")*(tbPrevisoes[✅ STATUS]="Ativa")*tbPrevisoes[💰 VALOR])} -> 0 | E43: {=SUMPRODUCT((tbDespesas[📅 Data]=$B43)*(tbDespesas[📊 Status]="Realizado")*tbDespesas[💰 Valor])+SUMPRODUCT((tbDespesas[📅 Data]=$B43)*(tbDespesas[📊 Status]="Previsto")*tbDespesas[💰 Valor])+SUMPRODUCT((tbParcelas6[Data_Vencimento]=$B43)*tbParcelas6[Valor_Parcela])+SUMPRODUCT((tbPrevisoes[📅 DATA]=$B43)*(tbPrevisoes[📂 TIPO]="Despesa")*(tbPrevisoes[✅ STATUS]="Ativa")*tbPrevisoes[💰 VALOR])} -> 0 | F43: =D43-E43 -> 0 | G43: =G42+F43 -> 17042.333 | H43: =IF(B43=TODAY(),"📅","")
A44: 21 | B44: =$J$3+20 -> 45815 | C44: =TEXT(B44,"ddd") -> sáb | D44: {=SUMPRODUCT((tb_receitas[📅 Data]=$B44)*(tb_receitas[📊 Status]="Realizado")*tb_receitas[💵 Valor])+SUMPRODUCT((tb_receitas[📅 Data]=$B44)*(tb_receitas[📊 Status]="Previsto")*tb_receitas[💵 Valor])+SUMPRODUCT((tbPrevisoes[📅 DATA]=$B44)*(tbPrevisoes[📂 TIPO]="Receita")*(tbPrevisoes[✅ STATUS]="Ativa")*tbPrevisoes[💰 VALOR])} -> 0 | E44: {=SUMPRODUCT((tbDespesas[📅 Data]=$B44)*(tbDespesas[📊 Status]="Realizado")*tbDespesas[💰 Valor])+SUMPRODUCT((tbDespesas[📅 Data]=$B44)*(tbDespesas[📊 Status]="Previsto")*tbDespesas[💰 Valor])+SUMPRODUCT((tbParcelas6[Data_Vencimento]=$B44)*tbParcelas6[Valor_Parcela])+SUMPRODUCT((tbPrevisoes[📅 DATA]=$B44)*(tbPrevisoes[📂 TIPO]="Despesa")*(tbPrevisoes[✅ STATUS]="Ativa")*tbPrevisoes[💰 VALOR])} -> 708 | F44: =D44-E44 -> -708 | G44: =G43+F44 -> 16334.333 | H44: =IF(B44=TODAY(),"📅","")
A45: 22 | B45: =$J$3+21 -> 45816 | C45: =TEXT(B45,"ddd") -> dom | D45: {=SUMPRODUCT((tb_receitas[📅 Data]=$B45)*(tb_receitas[📊 Status]="Realizado")*tb_receitas[💵 Valor])+SUMPRODUCT((tb_receitas[📅 Data]=$B45)*(tb_receitas[📊 Status]="Previsto")*tb_receitas[💵 Valor])+SUMPRODUCT((tbPrevisoes[📅 DATA]=$B45)*(tbPrevisoes[📂 TIPO]="Receita")*(tbPrevisoes[✅ STATUS]="Ativa")*tbPrevisoes[💰 VALOR])} -> 0 | E45: {=SUMPRODUCT((tbDespesas[📅 Data]=$B45)*(tbDespesas[📊 Status]="Realizado")*tbDespesas[💰 Valor])+SUMPRODUCT((tbDespesas[📅 Data]=$B45)*(tbDespesas[📊 Status]="Previsto")*tbDespesas[💰 Valor])+SUMPRODUCT((tbParcelas6[Data_Vencimento]=$B45)*tbParcelas6[Valor_Parcela])+SUMPRODUCT((tbPrevisoes[📅 DATA]=$B45)*(tbPrevisoes[📂 TIPO]="Despesa")*(tbPrevisoes[✅ STATUS]="Ativa")*tbPrevisoes[💰 VALOR])} -> 0 | F45: =D45-E45 -> 0 | G45: =G44+F45 -> 16334.333 | H45: =IF(B45=TODAY(),"📅","")
A46: 23 | B46: =$J$3+22 -> 45817 | C46: =TEXT(B46,"ddd") -> seg | D46: {=SUMPRODUCT((tb_receitas[📅 Data]=$B46)*(tb_receitas[📊 Status]="Realizado")*tb_receitas[💵 Valor])+SUMPRODUCT((tb_receitas[📅 Data]=$B46)*(tb_receitas[📊 Status]="Previsto")*tb_receitas[💵 Valor])+SUMPRODUCT((tbPrevisoes[📅 DATA]=$B46)*(tbPrevisoes[📂 TIPO]="Receita")*(tbPrevisoes[✅ STATUS]="Ativa")*tbPrevisoes[💰 VALOR])} -> 6500 | E46: {=SUMPRODUCT((tbDespesas[📅 Data]=$B46)*(tbDespesas[📊 Status]="Realizado")*tbDespesas[💰 Valor])+SUMPRODUCT((tbDespesas[📅 Data]=$B46)*(tbDespesas[📊 Status]="Previsto")*tbDespesas[💰 Valor])+SUMPRODUCT((tbParcelas6[Data_Vencimento]=$B46)*tbParcelas6[Valor_Parcela])+SUMPRODUCT((tbPrevisoes[📅 DATA]=$B46)*(tbPrevisoes[📂 TIPO]="Despesa")*(tbPrevisoes[✅ STATUS]="Ativa")*tbPrevisoes[💰 VALOR])} -> 2921 | F46: =D46-E46 -> 3579 | G46: =G45+F46 -> 19913.333 | H46: =IF(B46=TODAY(),"📅","")
A47: 24 | B47: =$J$3+23 -> 45818 | C47: =TEXT(B47,"ddd") -> ter | D47: {=SUMPRODUCT((tb_receitas[📅 Data]=$B47)*(tb_receitas[📊 Status]="Realizado")*tb_receitas[💵 Valor])+SUMPRODUCT((tb_receitas[📅 Data]=$B47)*(tb_receitas[📊 Status]="Previsto")*tb_receitas[💵 Valor])+SUMPRODUCT((tbPrevisoes[📅 DATA]=$B47)*(tbPrevisoes[📂 TIPO]="Receita")*(tbPrevisoes[✅ STATUS]="Ativa")*tbPrevisoes[💰 VALOR])} -> 0 | E47: {=SUMPRODUCT((tbDespesas[📅 Data]=$B47)*(tbDespesas[📊 Status]="Realizado")*tbDespesas[💰 Valor])+SUMPRODUCT((tbDespesas[📅 Data]=$B47)*(tbDespesas[📊 Status]="Previsto")*tbDespesas[💰 Valor])+SUMPRODUCT((tbParcelas6[Data_Vencimento]=$B47)*tbParcelas6[Valor_Parcela])+SUMPRODUCT((tbPrevisoes[📅 DATA]=$B47)*(tbPrevisoes[📂 TIPO]="Despesa")*(tbPrevisoes[✅ STATUS]="Ativa")*tbPrevisoes[💰 VALOR])} -> 0 | F47: =D47-E47 -> 0 | G47: =G46+F47 -> 19913.333 | H47: =IF(B47=TODAY(),"📅","")
A48: 25 | B48: =$J$3+24 -> 45819 | C48: =TEXT(B48,"ddd") -> qua | D48: {=SUMPRODUCT((tb_receitas[📅 Data]=$B48)*(tb_receitas[📊 Status]="Realizado")*tb_receitas[💵 Valor])+SUMPRODUCT((tb_receitas[📅 Data]=$B48)*(tb_receitas[📊 Status]="Previsto")*tb_receitas[💵 Valor])+SUMPRODUCT((tbPrevisoes[📅 DATA]=$B48)*(tbPrevisoes[📂 TIPO]="Receita")*(tbPrevisoes[✅ STATUS]="Ativa")*tbPrevisoes[💰 VALOR])} -> 0 | E48: {=SUMPRODUCT((tbDespesas[📅 Data]=$B48)*(tbDespesas[📊 Status]="Realizado")*tbDespesas[💰 Valor])+SUMPRODUCT((tbDespesas[📅 Data]=$B48)*(tbDespesas[📊 Status]="Previsto")*tbDespesas[💰 Valor])+SUMPRODUCT((tbParcelas6[Data_Vencimento]=$B48)*tbParcelas6[Valor_Parcela])+SUMPRODUCT((tbPrevisoes[📅 DATA]=$B48)*(tbPrevisoes[📂 TIPO]="Despesa")*(tbPrevisoes[✅ STATUS]="Ativa")*tbPrevisoes[💰 VALOR])} -> 280 | F48: =D48-E48 -> -280 | G48: =G47+F48 -> 19633.333 | H48: =IF(B48=TODAY(),"📅","")
A49: 26 | B49: =$J$3+25 -> 45820 | C49: =TEXT(B49,"ddd") -> qui | D49: {=SUMPRODUCT((tb_receitas[📅 Data]=$B49)*(tb_receitas[📊 Status]="Realizado")*tb_receitas[💵 Valor])+SUMPRODUCT((tb_receitas[📅 Data]=$B49)*(tb_receitas[📊 Status]="Previsto")*tb_receitas[💵 Valor])+SUMPRODUCT((tbPrevisoes[📅 DATA]=$B49)*(tbPrevisoes[📂 TIPO]="Receita")*(tbPrevisoes[✅ STATUS]="Ativa")*tbPrevisoes[💰 VALOR])} -> 0 | E49: {=SUMPRODUCT((tbDespesas[📅 Data]=$B49)*(tbDespesas[📊 Status]="Realizado")*tbDespesas[💰 Valor])+SUMPRODUCT((tbDespesas[📅 Data]=$B49)*(tbDespesas[📊 Status]="Previsto")*tbDespesas[💰 Valor])+SUMPRODUCT((tbParcelas6[Data_Vencimento]=$B49)*tbParcelas6[Valor_Parcela])+SUMPRODUCT((tbPrevisoes[📅 DATA]=$B49)*(tbPrevisoes[📂 TIPO]="Despesa")*(tbPrevisoes[✅ STATUS]="Ativa")*tbPrevisoes[💰 VALOR])} -> 0 | F49: =D49-E49 -> 0 | G49: =G48+F49 -> 19633.333 | H49: =IF(B49=TODAY(),"📅","")
A50: 27 | B50: =$J$3+26 -> 45821 | C50: =TEXT(B50,"ddd") -> sex | D50: {=SUMPRODUCT((tb_receitas[📅 Data]=$B50)*(tb_receitas[📊 Status]="Realizado")*tb_receitas[💵 Valor])+SUMPRODUCT((tb_receitas[📅 Data]=$B50)*(tb_receitas[📊 Status]="Previsto")*tb_receitas[💵 Valor])+SUMPRODUCT((tbPrevisoes[📅 DATA]=$B50)*(tbPrevisoes[📂 TIPO]="Receita")*(tbPrevisoes[✅ STATUS]="Ativa")*tbPrevisoes[💰 VALOR])} -> 0 | E50: {=SUMPRODUCT((tbDespesas[📅 Data]=$B50)*(tbDespesas[📊 Status]="Realizado")*tbDespesas[💰 Valor])+SUMPRODUCT((tbDespesas[📅 Data]=$B50)*(tbDespesas[📊 Status]="Previsto")*tbDespesas[💰 Valor])+SUMPRODUCT((tbParcelas6[Data_Vencimento]=$B50)*tbParcelas6[Valor_Parcela])+SUMPRODUCT((tbPrevisoes[📅 DATA]=$B50)*(tbPrevisoes[📂 TIPO]="Despesa")*(tbPrevisoes[✅ STATUS]="Ativa")*tbPrevisoes[💰 VALOR])} -> 0 | F50: =D50-E50 -> 0 | G50: =G49+F50 -> 19633.333 | H50: =IF(B50=TODAY(),"📅","")
A51: 28 | B51: =$J$3+27 -> 45822 | C51: =TEXT(B51,"ddd") -> sáb | D51: {=SUMPRODUCT((tb_receitas[📅 Data]=$B51)*(tb_receitas[📊 Status]="Realizado")*tb_receitas[💵 Valor])+SUMPRODUCT((tb_receitas[📅 Data]=$B51)*(tb_receitas[📊 Status]="Previsto")*tb_receitas[💵 Valor])+SUMPRODUCT((tbPrevisoes[📅 DATA]=$B51)*(tbPrevisoes[📂 TIPO]="Receita")*(tbPrevisoes[✅ STATUS]="Ativa")*tbPrevisoes[💰 VALOR])} -> 0 | E51: {=SUMPRODUCT((tbDespesas[📅 Data]=$B51)*(tbDespesas[📊 Status]="Realizado")*tbDespesas[💰 Valor])+SUMPRODUCT((tbDespesas[📅 Data]=$B51)*(tbDespesas[📊 Status]="Previsto")*tbDespesas[💰 Valor])+SUMPRODUCT((tbParcelas6[Data_Vencimento]=$B51)*tbParcelas6[Valor_Parcela])+SUMPRODUCT((tbPrevisoes[📅 DATA]=$B51)*(tbPrevisoes[📂 TIPO]="Despesa")*(tbPrevisoes[✅ STATUS]="Ativa")*tbPrevisoes[💰 VALOR])} -> 1064.5 | F51: =D51-E51 -> -1064.5 | G51: =G50+F51 -> 18568.833 | H51: =IF(B51=TODAY(),"📅","")
A52: 29 | B52: =$J$3+28 -> 45823 | C52: =TEXT(B52,"ddd") -> dom | D52: {=SUMPRODUCT((tb_receitas[📅 Data]=$B52)*(tb_receitas[📊 Status]="Realizado")*tb_receitas[💵 Valor])+SUMPRODUCT((tb_receitas[📅 Data]=$B52)*(tb_receitas[📊 Status]="Previsto")*tb_receitas[💵 Valor])+SUMPRODUCT((tbPrevisoes[📅 DATA]=$B52)*(tbPrevisoes[📂 TIPO]="Receita")*(tbPrevisoes[✅ STATUS]="Ativa")*tbPrevisoes[💰 VALOR])} -> 0 | E52: {=SUMPRODUCT((tbDespesas[📅 Data]=$B52)*(tbDespesas[📊 Status]="Realizado")*tbDespesas[💰 Valor])+SUMPRODUCT((tbDespesas[📅 Data]=$B52)*(tbDespesas[📊 Status]="Previsto")*tbDespesas[💰 Valor])+SUMPRODUCT((tbParcelas6[Data_Vencimento]=$B52)*tbParcelas6[Valor_Parcela])+SUMPRODUCT((tbPrevisoes[📅 DATA]=$B52)*(tbPrevisoes[📂 TIPO]="Despesa")*(tbPrevisoes[✅ STATUS]="Ativa")*tbPrevisoes[💰 VALOR])} -> 0 | F52: =D52-E52 -> 0 | G52: =G51+F52 -> 18568.833 | H52: =IF(B52=TODAY(),"📅","")
A53: 30 | B53: =$J$3+29 -> 45824 | C53: =TEXT(B53,"ddd") -> seg | D53: {=SUMPRODUCT((tb_receitas[📅 Data]=$B53)*(tb_receitas[📊 Status]="Realizado")*tb_receitas[💵 Valor])+SUMPRODUCT((tb_receitas[📅 Data]=$B53)*(tb_receitas[📊 Status]="Previsto")*tb_receitas[💵 Valor])+SUMPRODUCT((tbPrevisoes[📅 DATA]=$B53)*(tbPrevisoes[📂 TIPO]="Receita")*(tbPrevisoes[✅ STATUS]="Ativa")*tbPrevisoes[💰 VALOR])} -> 0 | E53: {=SUMPRODUCT((tbDespesas[📅 Data]=$B53)*(tbDespesas[📊 Status]="Realizado")*tbDespesas[💰 Valor])+SUMPRODUCT((tbDespesas[📅 Data]=$B53)*(tbDespesas[📊 Status]="Previsto")*tbDespesas[💰 Valor])+SUMPRODUCT((tbParcelas6[Data_Vencimento]=$B53)*tbParcelas6[Valor_Parcela])+SUMPRODUCT((tbPrevisoes[📅 DATA]=$B53)*(tbPrevisoes[📂 TIPO]="Despesa")*(tbPrevisoes[✅ STATUS]="Ativa")*tbPrevisoes[💰 VALOR])} -> 190 | F53: =D53-E53 -> -190 | G53: =G52+F53 -> 18378.833 | H53: =IF(B53=TODAY(),"📅","")
A54: TOTAL 30 DIAS | D54: =SUM(D24:D53) -> 16000 | E54: =SUM(E24:E53) -> 12089.5 | F54: =SUM(F24:F53) -> 3910.5 | G54: =G53 -> 18378.833
A56: 📋 LEGENDA
A57: 📅 Amarelo = Hoje
A58: 🔶 Laranja = Último dia do mês
A59: 🔵 Azul = Mês atual
A60: 🟢 Verde = Próximo mês
A62: 💡 COMO USAR:
A63: • O fluxo mostra automaticamente os próximos 30 dias a partir de HOJE
A64: • Inclui: Receitas, Despesas, Parcelas de Cartão e Previsões Ativas
A65: • Saldo Inicial = Saldo fim do mês anterior + movimentações do mês atual até ontem
A66: • B4 deve conter o saldo bancário REAL em 1º de janeiro do ano selecionado
A67: • Investimentos NÃO são incluídos nas saídas (são transferências de patrimônio)

Sheet DASHBOARD
A1: 📊 DASHBOARD - ORÇAMENTO DOMÉSTICO | P1: 📋 DADOS AUXILIARES (não ocultar - usados pelos gráficos)
A2: Controle Financeiro Pessoal
A4: 📅 ANO: | B4: 2025 | D4: 📆 MÊS: | E4: 0 | G4: (0 = Ano completo | 1-12 = Mês específico)
A6: 💰 RECEITAS | D6: 📉 DESPESAS | G6: 💵 SALDO | J6: 📈 INVESTIMENTOS | M6: 📊 % ECONOMIA
A7: {=SUMPRODUCT((YEAR(tb_receitas[📅 Data])=$B$4)*(IF($E$4=0,1,MONTH(tb_receitas[📅 Data])=$E$4))*tb_receitas[💵 Valor])+SUMPRODUCT((YEAR(tbPrevisoes[📅 DATA])=$B$4)*(IF($E$4=0,1,MONTH(tbPrevisoes[📅 DATA])=$E$4))*(tbPrevisoes[📂 TIPO]="Receita")*(tbPrevisoes[✅ STATUS]="Ativa")*tbPrevisoes[💰 VALOR])} -> 194000 | D7: {=SUMPRODUCT((YEAR(tbDespesas[📅 Data])=$B$4)*(IF($E$4=0,1,MONTH(tbDespesas[📅 Data])=$E$4))*(tbDespesas[📊 Status]="Realizado")*tbDespesas[💰 Valor])+SUMPRODUCT((YEAR(tbParcelas6[Data_Vencimento])=$B$4)*(IF($E$4=0,1,MONTH(tbParcelas6[Data_Vencimento])=$E$4))*tbParcelas6[Valor_Parcela])+SUMPRODUCT((YEAR(tbPrevisoes[📅 DATA])=$B$4)*(IF($E$4=0,1,MONTH(tbPrevisoes[📅 DATA])=$E$4))*(tbPrevisoes[📂 TIPO]="Despesa")*(tbPrevisoes[✅ STATUS]="Ativa")*tbPrevisoes[💰 VALOR])} -> 183290.33 | G7: =A7-D7 -> 10709.667 | J7: {=SUMPRODUCT((YEAR(tb_investimentos[Data])=$B$4)*(IF($E$4=0,1,MONTH(tb_investimentos[Data])=$E$4))*(tb_investimentos[Movimento]="Aporte")*tb_investimentos[Valor])-SUMPRODUCT((YEAR(tb_investimentos[Data])=$B$4)*(IF($E$4=0,1,MONTH(tb_investimentos[Data])=$E$4))*(tb_investimentos[Movimento]="Resgate")*tb_investimentos[Valor])} -> 6200 | M7: =IF(A7=0,0,(A7-D7)/A7) -> 0.055204467
A22: 📋 ORÇADO vs REALIZADO
A23: Categoria | B23: Orçado | C23: Realizado | D23: Variação | E23: % Variação | F23: Status | P23: Categoria | Q23: Valor
A24: RECEITAS | B24: =IF($E$4=0,ORCAMENTO!$B$3*12,ORCAMENTO!$B$3) -> 192000 | C24: {=SUMPRODUCT((YEAR(tb_receitas[📅 Data])=$B$4)*(IF($E$4=0,1,MONTH(tb_receitas[📅 Data])=$E$4))*tb_receitas[💵 Valor])} -> 194000 | D24: =C24-B24 -> 2000 | E24: =IFERROR(D24/B24,0) -> 0.010416667 | F24: =IF(D24>=0,"✅ OK","⚠️ Abaixo") -> ✅ OK | P24: Habitação | Q24: =C32 -> 59508.333
A25: Salário | B25: =IF($E$4=0,ORCAMENTO!$B$4*12,ORCAMENTO!$B$4) -> 180000 | C25: {=SUMPRODUCT((tb_receitas[📂 Categoria]="Salário")*(YEAR(tb_receitas[📅 Data])=$B$4)*(IF($E$4=0,1,MONTH(tb_receitas[📅 Data])=$E$4))*tb_receitas[💵 Valor])} -> 180000 | D25: =C25-B25 -> 0 | E25: =IFERROR(D25/B25,0) -> 0 | F25: =IF(D25>=0,"✅","⚠️") -> ✅ | P25: Alimentação | Q25: =C33 -> 27450
A26: Benefício | B26: =IF($E$4=0,ORCAMENTO!$B$11*12,ORCAMENTO!$B$11) -> 6000 | C26: {=SUMPRODUCT((tb_receitas[📂 Categoria]="Benefício")*(YEAR(tb_receitas[📅 Data])=$B$4)*(IF($E$4=0,1,MONTH(tb_receitas[📅 Data])=$E$4))*tb_receitas[💵 Valor])} -> 5500 | D26: =C26-B26 -> -500 | E26: =IFERROR(D26/B26,0) -> -0.083333333 | F26: =IF(D26>=0,"✅","⚠️") -> ⚠️ | P26: Transporte | Q26: =C34 -> 15866.667
A27: Prestação Serviço Extra | B27: =IF($E$4=0,ORCAMENTO!$B$14*12,ORCAMENTO!$B$14) -> 6000 | C27: {=SUMPRODUCT((tb_receitas[📂 Categoria]="Prestação Serviço Extra")*(YEAR(tb_receitas[📅 Data])=$B$4)*(IF($E$4=0,1,MONTH(tb_receitas[📅 Data])=$E$4))*tb_receitas[💵 Valor])} -> 6100 | D27: =C27-B27 -> 100 | E27: =IFERROR(D27/B27,0) -> 0.016666667 | F27: =IF(D27>=0,"✅","⚠️") -> ✅ | P27: Saúde | Q27: =C35 -> 10765
A28: Convênios | B28: =IF($E$4=0,ORCAMENTO!$B$12*12,ORCAMENTO!$B$12) -> 0 | C28: {=SUMPRODUCT((tb_receitas[📂 Categoria]="Convênios")*(YEAR(tb_receitas[📅 Data])=$B$4)*(IF($E$4=0,1,MONTH(tb_receitas[📅 Data])=$E$4))*tb_receitas[💵 Valor])} -> 0 | D28: =C28-B28 -> 0 | E28: =IFERROR(D28/B28,0) -> 0 | F28: =IF(D28>=0,"✅","⚠️") -> ✅ | P28: Educação | Q28: =C36 -> 18917
A29: Extra | B29: =IF($E$4=0,ORCAMENTO!$B$13*12,ORCAMENTO!$B$13) -> 0 | C29: {=SUMPRODUCT((tb_receitas[📂 Categoria]="Extra")*(YEAR(tb_receitas[📅 Data])=$B$4)*(IF($E$4=0,1,MONTH(tb_receitas[📅 Data])=$E$4))*tb_receitas[💵 Valor])} -> 2400 | D29: =C29-B29 -> 2400 | E29: =IFERROR(D29/B29,0) -> 0 | F29: =IF(D29>=0,"✅","⚠️") -> ✅ | P29: Vestuário | Q29: =C37 -> 4971.6667
P30: Lazer | Q30: =C38 -> 10765
A31: DESPESAS | B31: =IF($E$4=0,ORCAMENTO!$B$20*12,ORCAMENTO!$B$20) -> 150000 | C31: {=SUMPRODUCT((YEAR(tbDespesas[📅 Data])=$B$4)*(IF($E$4=0,1,MONTH(tbDespesas[📅 Data])=$E$4))*tbDespesas[💰 Valor])+SUMPRODUCT((YEAR(tbParcelas6[Data_Vencimento])=$B$4)*(IF($E$4=0,1,MONTH(tbParcelas6[Data_Vencimento])=$E$4))*tbParcelas6[Valor_Parcela])} -> 183290.33 | D31: =B31-C31 -> -33290.333 | E31: =IF(B31=0,0,(B31-C31)/B31) -> -0.22193556 | F31: =IF(D31>=0,"✅ OK","🔴 Estouro") -> 🔴 Estouro | P31: Trabalho | Q31: =C39 -> 1150
A32: Habitação | B32: =IF($E$4=0,ORCAMENTO!$B$21*12,ORCAMENTO!$B$21) -> 57600 | C32: {=SUMPRODUCT((tbDespesas[📂 Categoria]="Habitação")*(YEAR(tbDespesas[📅 Data])=$B$4)*(IF($E$4=0,1,MONTH(tbDespesas[📅 Data])=$E$4))*(tbDespesas[📊 Status]="Realizado")*tbDespesas[💰 Valor])+SUMPRODUCT((tbCartoes[📂 Categoria]="Habitação")*(YEAR(tbCartoes[📅 Data Compra])=$B$4)*(IF($E$4=0,1,MONTH(tbCartoes[📅 Data Compra])=$E$4))*tbCartoes[💳 Valor Total]*IF(tbCartoes[🔢 Parcelas]=0,0,1/tbCartoes[🔢 Parcelas]))} -> 59508.333 | D32: =B32-C32 -> -1908.3333 | E32: =IFERROR(D32/B32,0) -> -0.033130787 | F32: =IF(D32>=0,"✅","🔴") -> 🔴 | P32: Caridade | Q32: =C40 -> 2450
A33: Alimentação | B33: =IF($E$4=0,ORCAMENTO!$B$22*12,ORCAMENTO!$B$22) -> 24000 | C33: {=SUMPRODUCT((tbDespesas[📂 Categoria]="Alimentação")*(YEAR(tbDespesas[📅 Data])=$B$4)*(IF($E$4=0,1,MONTH(tbDespesas[📅 Data])=$E$4))*(tbDespesas[📊 Status]="Realizado")*tbDespesas[💰 Valor])+SUMPRODUCT((tbCartoes[📂 Categoria]="Alimentação")*(YEAR(tbCartoes[📅 Data Compra])=$B$4)*(IF($E$4=0,1,MONTH(tbCartoes[📅 Data Compra])=$E$4))*tbCartoes[💳 Valor Total]*IF(tbCartoes[🔢 Parcelas]=0,0,1/tbCartoes[🔢 Parcelas]))} -> 27450 | D33: =B33-C33 -> -3450 | E33: =IFERROR(D33/B33,0) -> -0.14375 | F33: =IF(D33>=0,"✅","🔴") -> 🔴 | P33: Outros | Q33: =C42 -> 12300
A34: Transporte | B34: =IF($E$4=0,ORCAMENTO!$B$23*12,ORCAMENTO!$B$23) -> 14400 | C34: {=SUMPRODUCT((tbDespesas[📂 Categoria]="Transporte")*(YEAR(tbDespesas[📅 Data])=$B$4)*(IF($E$4=0,1,MONTH(tbDespesas[📅 Data])=$E$4))*(tbDespesas[📊 Status]="Realizado")*tbDespesas[💰 Valor])+SUMPRODUCT((tbCartoes[📂 Categoria]="Transporte")*(YEAR(tbCartoes[📅 Data Compra])=$B$4)*(IF($E$4=0,1,MONTH(tbCartoes[📅 Data Compra])=$E$4))*tbCartoes[💳 Valor Total]*IF(tbCartoes[🔢 Parcelas]=0,0,1/tbCartoes[🔢 Parcelas]))} -> 15866.667 | D34: =B34-C34 -> -1466.6667 | E34: =IFERROR(D34/B34,0) -> -0.10185185 | F34: =IF(D34>=0,"✅","🔴") -> 🔴
A35: Saúde | B35: =IF($E$4=0,ORCAMENTO!$B$24*12,ORCAMENTO!$B$24) -> 9600 | C35: {=SUMPRODUCT((tbDespesas[📂 Categoria]="Saúde")*(YEAR(tbDespesas[📅 Data])=$B$4)*(IF($E$4=0,1,MONTH(tbDespesas[📅 Data])=$E$4))*(tbDespesas[📊 Status]="Realizado")*tbDespesas[💰 Valor])+SUMPRODUCT((tbCartoes[📂 Categoria]="Saúde")*(YEAR(tbCartoes[📅 Data Compra])=$B$4)*(IF($E$4=0,1,MONTH(tbCartoes[📅 Data Compra])=$E$4))*tbCartoes[💳 Valor Total]*IF(tbCartoes[🔢 Parcelas]=0,0,1/tbCartoes[🔢 Parcelas]))} -> 10765 | D35: =B35-C35 -> -1165 | E35: =IFERROR(D35/B35,0) -> -0.12135417 | F35: =IF(D35>=0,"✅","🔴") -> 🔴
A36: Educação | B36: =IF($E$4=0,ORCAMENTO!$B$25*12,ORCAMENTO!$B$25) -> 18000 | C36: {=SUMPRODUCT((tbDespesas[📂 Categoria]="Educação")*(YEAR(tbDespesas[📅 Data])=$B$4)*(IF($E$4=0,1,MONTH(tbDespesas[📅 Data])=$E$4))*(tbDespesas[📊 Status]="Realizado")*tbDespesas[💰 Valor])+SUMPRODUCT((tbCartoes[📂 Categoria]="Educação")*(YEAR(tbCartoes[📅 Data Compra])=$B$4)*(IF($E$4=0,1,MONTH(tbCartoes[📅 Data Compra])=$E$4))*tbCartoes[💳 Valor Total]*IF(tbCartoes[🔢 Parcelas]=0,0,1/tbCartoes[🔢 Parcelas]))} -> 18917 | D36: =B36-C36 -> -917 | E36: =IFERROR(D36/B36,0) -> -0.050944444 | F36: =IF(D36>=0,"✅","🔴") -> 🔴
A37: Vestuário | B37: =IF($E$4=0,ORCAMENTO!$B$26*12,ORCAMENTO!$B$26) -> 3600 | C37: {=SUMPRODUCT((tbDespesas[📂 Categoria]="Vestuário")*(YEAR(tbDespesas[📅 Data])=$B$4)*(IF($E$4=0,1,MONTH(tbDespesas[📅 Data])=$E$4))*(tbDespesas[📊 Status]="Realizado")*tbDespesas[💰 Valor])+SUMPRODUCT((tbCartoes[📂 Categoria]="Vestuário")*(YEAR(tbCartoes[📅 Data Compra])=$B$4)*(IF($E$4=0,1,MONTH(tbCartoes[📅 Data Compra])=$E$4))*tbCartoes[💳 Valor Total]*IF(tbCartoes[🔢 Parcelas]=0,0,1/tbCartoes[🔢 Parcelas]))} -> 4971.6667 | D37: =B37-C37 -> -1371.6667 | E37: =IFERROR(D37/B37,0) -> -0.38101852 | F37: =IF(D37>=0,"✅","🔴") -> 🔴
A38: Lazer | B38: =IF($E$4=0,ORCAMENTO!$B$27*12,ORCAMENTO!$B$27) -> 7200 | C38: {=SUMPRODUCT((tbDespesas[📂 Categoria]="Lazer")*(YEAR(tbDespesas[📅 Data])=$B$4)*(IF($E$4=0,1,MONTH(tbDespesas[📅 Data])=$E$4))*(tbDespesas[📊 Status]="Realizado")*tbDespesas[💰 Valor])+SUMPRODUCT((tbCartoes[📂 Categoria]="Lazer")*(YEAR(tbCartoes[📅 Data Compra])=$B$4)*(IF($E$4=0,1,MONTH(tbCartoes[📅 Data Compra])=$E$4))*tbCartoes[💳 Valor Total]*IF(tbCartoes[🔢 Parcelas]=0,0,1/tbCartoes[🔢 Parcelas]))} -> 10765 | D38: =B38-C38 -> -3565 | E38: =IFERROR(D38/B38,0) -> -0.49513889 | F38: =IF(D38>=0,"✅","🔴") -> 🔴
A39: Trabalho | B39: =IF($E$4=0,ORCAMENTO!$B$29*12,ORCAMENTO!$B$29) -> 2400 | C39: {=SUMPRODUCT((tbDespesas[📂 Categoria]="Caridade")*(YEAR(tbDespesas[📅 Data])=$B$4)*(IF($E$4=0,1,MONTH(tbDespesas[📅 Data])=$E$4))*(tbDespesas[📊 Status]="Realizado")*tbDespesas[💰 Valor])+SUMPRODUCT((tbCartoes[📂 Categoria]="Caridade")*(YEAR(tbCartoes[📅 Data Compra])=$B$4)*(IF($E$4=0,1,MONTH(tbCartoes[📅 Data Compra])=$E$4))*tbCartoes[💳 Valor Total]*IF(tbCartoes[🔢 Parcelas]=0,0,1/tbCartoes[🔢 Parcelas]))} -> 1150 | D39: =B39-C39 -> 1250 | E39: =IFERROR(D39/B39,0) -> 0.52083333 | F39: =IF(D39>=0,"✅","🔴") -> ✅
A40: Caridade | B40: =IF($E$4=0,ORCAMENTO!$B$28*12,ORCAMENTO!$B$28) -> 1200 | C40: {=SUMPRODUCT((tbDespesas[📂 Categoria]="Trabalho")*(YEAR(tbDespesas[📅 Data])=$B$4)*(IF($E$4=0,1,MONTH(tbDespesas[📅 Data])=$E$4))*(tbDespesas[📊 Status]="Realizado")*tbDespesas[💰 Valor])+SUMPRODUCT((tbCartoes[📂 Categoria]="Trabalho")*(YEAR(tbCartoes[📅 Data Compra])=$B$4)*(IF($E$4=0,1,MONTH(tbCartoes[📅 Data Compra])=$E$4))*tbCartoes[💳 Valor Total]*IF(tbCartoes[🔢 Parcelas]=0,0,1/tbCartoes[🔢 Parcelas]))} -> 2450 | D40: =B40-C40 -> -1250 | E40: =IFERROR(D40/B40,0) -> -1.0416667 | F40: =IF(D40>=0,"✅","🔴") -> 🔴
A41: Dívidas | B41: =IF($E$4=0,ORCAMENTO!$B$30*12,ORCAMENTO!$B$30) -> 0 | C41: {=SUMPRODUCT((tbDespesas[📂 Categoria]="Dívidas")*(YEAR(tbDespesas[📅 Data])=$B$4)*(IF($E$4=0,1,MONTH(tbDespesas[📅 Data])=$E$4))*(tbDespesas[📊 Status]="Realizado")*tbDespesas[💰 Valor])+SUMPRODUCT((tbCartoes[📂 Categoria]="Dívidas")*(YEAR(tbCartoes[📅 Data Compra])=$B$4)*(IF($E$4=0,1,MONTH(tbCartoes[📅 Data Compra])=$E$4))*tbCartoes[💳 Valor Total]*IF(tbCartoes[🔢 Parcelas]=0,0,1/tbCartoes[🔢 Parcelas]))} -> 0 | D41: =B41-C41 -> 0 | E41: =IFERROR(D41/B41,0) -> 0 | F41: =IF(D41>=0,"✅","🔴") -> ✅
A42: Outros | B42: =IF($E$4=0,ORCAMENTO!$B$31*12,ORCAMENTO!$B$31) -> 12000 | C42: {=SUMPRODUCT((tbDespesas[📂 Categoria]="Outros")*(YEAR(tbDespesas[📅 Data])=$B$4)*(IF($E$4=0,1,MONTH(tbDespesas[📅 Data])=$E$4))*(tbDespesas[📊 Status]="Realizado")*tbDespesas[💰 Valor])+SUMPRODUCT((tbCartoes[📂 Categoria]="Outros")*(YEAR(tbCartoes[📅 Data Compra])=$B$4)*(IF($E$4=0,1,MONTH(tbCartoes[📅 Data Compra])=$E$4))*tbCartoes[💳 Valor Total]*IF(tbCartoes[🔢 Parcelas]=0,0,1/tbCartoes[🔢 Parcelas]))} -> 12300 | D42: =B42-C42 -> -300 | E42: =IFERROR(D42/B42,0) -> -0.025 | F42: =IF(D42>=0,"✅","🔴") -> 🔴
R53: Mês | S53: Receitas | T53: Despesas | U53: Saldo Mês | V53: Saldo Acumulado | X53: Mês | Y53: Saldo Acumulado
R54: Jan | S54: =FLUXO_CAIXA!B7 -> 16200 | T54: =FLUXO_CAIXA!D7 -> 12580 | U54: 24925.62 | V54: 24925.62 | X54: Mês | Y54: Saldo
R55: Fev | S55: =FLUXO_CAIXA!B8 -> 15900 | T55: =FLUXO_CAIXA!D8 -> 14366.667 | U55: 3176.09 | V55: 28101.71 | X55: Jan | Y55: =FLUXO_CAIXA!G7 -> 13620
R56: Mar | S56: =FLUXO_CAIXA!B9 -> 16400 | T56: =FLUXO_CAIXA!D9 -> 14073.667 | U56: 5131.19 | V56: 33232.9 | X56: Fev | Y56: =FLUXO_CAIXA!G8 -> 15153.333
R57: Abr | S57: =FLUXO_CAIXA!B10 -> 16000 | T57: =FLUXO_CAIXA!D10 -> 16333.333 | U57: 11810.41 | V57: 45043.31 | X57: Mar | Y57: =FLUXO_CAIXA!G9 -> 17479.667
R58: Mai | S58: =FLUXO_CAIXA!B11 -> 16150 | T58: =FLUXO_CAIXA!D11 -> 15681.667 | U58: -14200.77 | V58: 30842.54 | X58: Abr | Y58: =FLUXO_CAIXA!G10 -> 17146.333
R59: Jun | S59: =FLUXO_CAIXA!B12 -> 15950 | T59: =FLUXO_CAIXA!D12 -> 16428.333 | U59: -3901.76 | V59: 26940.78 | X59: Mai | Y59: =FLUXO_CAIXA!G11 -> 17614.667
R60: Jul | S60: =FLUXO_CAIXA!B13 -> 16000 | T60: =FLUXO_CAIXA!D13 -> 16341.667 | U60: 901.06 | V60: 27841.84 | X60: Jun | Y60: =FLUXO_CAIXA!G12 -> 17136.333
R61: Ago | S61: =FLUXO_CAIXA!B14 -> 16250 | T61: =FLUXO_CAIXA!D14 -> 14511.667 | U61: -1012.96 | V61: 26828.88 | X61: Jul | Y61: =FLUXO_CAIXA!G13 -> 16794.667
R62: Set | S62: =FLUXO_CAIXA!B15 -> 16050 | T62: =FLUXO_CAIXA!D15 -> 15540 | U62: -356.33 | V62: 26472.55 | X62: Ago | Y62: =FLUXO_CAIXA!G14 -> 18533
R63: Out | S63: =FLUXO_CAIXA!B16 -> 16000 | T63: =FLUXO_CAIXA!D16 -> 15770 | U63: 1668.2 | V63: 28140.75 | X63: Set | Y63: =FLUXO_CAIXA!G15 -> 19043
R64: Nov | S64: =FLUXO_CAIXA!B17 -> 16500 | T64: =FLUXO_CAIXA!D17 -> 14956.667 | U64: 6617.39 | V64: 34758.14 | X64: Out | Y64: =FLUXO_CAIXA!G16 -> 19273
R65: Dez | S65: =FLUXO_CAIXA!B18 -> 16600 | T65: =FLUXO_CAIXA!D18 -> 16706.667 | X65: Nov | Y65: =FLUXO_CAIXA!G17 -> 20816.333
X66: Dez | Y66: =FLUXO_CAIXA!G18 -> 20709.667
R67: Dez | S67: 41009.45 | T67: 34168.56 | U67: 6840.89 | V67: 41599.03 | X67: Dez | Y67: 41599.03
R68: TOTAL | S68: 594300.8 | T68: 552701.77 | U68: 41599.03 | V68: 41599.03
A74: 💡 INSIGHTS E ALERTAS
A76: 📊 Taxa de Economia: | B76: =IF(A7=0,0,(A7-D7)/A7) -> 0.055204467 | C76: =IF(B76<0.1,"🔴 Abaixo de 10% - Atenção!",IF(B76<0.2,"🟡 Entre 10-20% - Razoável","🟢 Acima de 20% - Ótimo!")) -> 🔴 Abaixo de 10% - Atenção!
A77: 💰 Maior Despesa: | B77: =INDEX(P24:P33,MATCH(MAX(Q24:Q33),Q24:Q33,0)) -> Habitação | C77: =MAX(Q24:Q33) -> 59508.333
A78: 📈 Melhor Mês (Saldo): | B78: =INDEX(R54:R67,MATCH(MAX(U54:U67),U54:U67,0)) -> Jan | C78: =MAX(U54:U67) -> 24925.62
A79: 📉 Pior Mês (Saldo): | B79: =INDEX(R54:R67,MATCH(MIN(U54:U67),U54:U67,0)) -> Mai | C79: =MIN(U54:U67) -> -14200.77
A81: 📌 Dica: Altere o ANO (B4) e o MÊS (E4) para filtrar os dados. Mês=0 mostra o ano completo.
A82: Última atualização: 18/05/2026, 11:38:54
A85: 📊 EVOLUÇÃO MENSAL DOS INVESTIMENTOS
A87: Mês | B87: Aportes | C87: Resgates | D87: Saldo Mês | E87: Acumulado
A88: Jan | B88: {=SUMPRODUCT((tb_investimentos[Movimento]="Aporte")*(YEAR(tb_investimentos[Data])=$B$4)*(MONTH(tb_investimentos[Data])=1)*tb_investimentos[Valor])} -> 500 | C88: {=SUMPRODUCT((tb_investimentos[Movimento]="Resgate")*(YEAR(tb_investimentos[Data])=$B$4)*(MONTH(tb_investimentos[Data])=1)*tb_investimentos[Valor])} -> 0 | D88: =B88-C88 -> 500 | E88: =D88 -> 500
A89: Fev | B89: {=SUMPRODUCT((tb_investimentos[Movimento]="Aporte")*(YEAR(tb_investimentos[Data])=$B$4)*(MONTH(tb_investimentos[Data])=2)*tb_investimentos[Valor])} -> 500 | C89: {=SUMPRODUCT((tb_investimentos[Movimento]="Resgate")*(YEAR(tb_investimentos[Data])=$B$4)*(MONTH(tb_investimentos[Data])=2)*tb_investimentos[Valor])} -> 0 | D89: =B89-C89 -> 500 | E89: =E88+D89 -> 1000
A90: Mar | B90: {=SUMPRODUCT((tb_investimentos[Movimento]="Aporte")*(YEAR(tb_investimentos[Data])=$B$4)*(MONTH(tb_investimentos[Data])=3)*tb_investimentos[Valor])} -> 500 | C90: {=SUMPRODUCT((tb_investimentos[Movimento]="Resgate")*(YEAR(tb_investimentos[Data])=$B$4)*(MONTH(tb_investimentos[Data])=3)*tb_investimentos[Valor])} -> 0 | D90: =B90-C90 -> 500 | E90: =E89+D90 -> 1500
A91: Abr | B91: {=SUMPRODUCT((tb_investimentos[Movimento]="Aporte")*(YEAR(tb_investimentos[Data])=$B$4)*(MONTH(tb_investimentos[Data])=4)*tb_investimentos[Valor])} -> 500 | C91: {=SUMPRODUCT((tb_investimentos[Movimento]="Resgate")*(YEAR(tb_investimentos[Data])=$B$4)*(MONTH(tb_investimentos[Data])=4)*tb_investimentos[Valor])} -> 0 | D91: =B91-C91 -> 500 | E91: =E90+D91 -> 2000
A92: Mai | B92: {=SUMPRODUCT((tb_investimentos[Movimento]="Aporte")*(YEAR(tb_investimentos[Data])=$B$4)*(MONTH(tb_investimentos[Data])=5)*tb_investimentos[Valor])} -> 500 | C92: {=SUMPRODUCT((tb_investimentos[Movimento]="Resgate")*(YEAR(tb_investimentos[Data])=$B$4)*(MONTH(tb_investimentos[Data])=5)*tb_investimentos[Valor])} -> 0 | D92: =B92-C92 -> 500 | E92: =E91+D92 -> 2500
A93: Jun | B93: {=SUMPRODUCT((tb_investimentos[Movimento]="Aporte")*(YEAR(tb_investimentos[Data])=$B$4)*(MONTH(tb_investimentos[Data])=6)*tb_investimentos[Valor])} -> 500 | C93: {=SUMPRODUCT((tb_investimentos[Movimento]="Resgate")*(YEAR(tb_investimentos[Data])=$B$4)*(MONTH(tb_investimentos[Data])=6)*tb_investimentos[Valor])} -> 0 | D93: =B93-C93 -> 500 | E93: =E92+D93 -> 3000
A94: Jul | B94: {=SUMPRODUCT((tb_investimentos[Movimento]="Aporte")*(YEAR(tb_investimentos[Data])=$B$4)*(MONTH(tb_investimentos[Data])=7)*tb_investimentos[Valor])} -> 500 | C94: {=SUMPRODUCT((tb_investimentos[Movimento]="Resgate")*(YEAR(tb_investimentos[Data])=$B$4)*(MONTH(tb_investimentos[Data])=7)*tb_investimentos[Valor])} -> 0 | D94: =B94-C94 -> 500 | E94: =E93+D94 -> 3500
A95: Ago | B95: {=SUMPRODUCT((tb_investimentos[Movimento]="Aporte")*(YEAR(tb_investimentos[Data])=$B$4)*(MONTH(tb_investimentos[Data])=8)*tb_investimentos[Valor])} -> 500 | C95: {=SUMPRODUCT((tb_investimentos[Movimento]="Resgate")*(YEAR(tb_investimentos[Data])=$B$4)*(MONTH(tb_investimentos[Data])=8)*tb_investimentos[Valor])} -> 0 | D95: =B95-C95 -> 500 | E95: =E94+D95 -> 4000
A96: Set | B96: {=SUMPRODUCT((tb_investimentos[Movimento]="Aporte")*(YEAR(tb_investimentos[Data])=$B$4)*(MONTH(tb_investimentos[Data])=9)*tb_investimentos[Valor])} -> 500 | C96: {=SUMPRODUCT((tb_investimentos[Movimento]="Resgate")*(YEAR(tb_investimentos[Data])=$B$4)*(MONTH(tb_investimentos[Data])=9)*tb_investimentos[Valor])} -> 0 | D96: =B96-C96 -> 500 | E96: =E95+D96 -> 4500
A97: Out | B97: {=SUMPRODUCT((tb_investimentos[Movimento]="Aporte")*(YEAR(tb_investimentos[Data])=$B$4)*(MONTH(tb_investimentos[Data])=10)*tb_investimentos[Valor])} -> 500 | C97: {=SUMPRODUCT((tb_investimentos[Movimento]="Resgate")*(YEAR(tb_investimentos[Data])=$B$4)*(MONTH(tb_investimentos[Data])=10)*tb_investimentos[Valor])} -> 0 | D97: =B97-C97 -> 500 | E97: =E96+D97 -> 5000
A98: Nov | B98: {=SUMPRODUCT((tb_investimentos[Movimento]="Aporte")*(YEAR(tb_investimentos[Data])=$B$4)*(MONTH(tb_investimentos[Data])=11)*tb_investimentos[Valor])} -> 500 | C98: {=SUMPRODUCT((tb_investimentos[Movimento]="Resgate")*(YEAR(tb_investimentos[Data])=$B$4)*(MONTH(tb_investimentos[Data])=11)*tb_investimentos[Valor])} -> 0 | D98: =B98-C98 -> 500 | E98: =E97+D98 -> 5500
A99: Dez | B99: {=SUMPRODUCT((tb_investimentos[Movimento]="Aporte")*(YEAR(tb_investimentos[Data])=$B$4)*(MONTH(tb_investimentos[Data])=12)*tb_investimentos[Valor])} -> 700 | C99: {=SUMPRODUCT((tb_investimentos[Movimento]="Resgate")*(YEAR(tb_investimentos[Data])=$B$4)*(MONTH(tb_investimentos[Data])=12)*tb_investimentos[Valor])} -> 0 | D99: =B99-C99 -> 700 | E99: =E98+D99 -> 6200
A100: TOTAL | B100: =SUM(B88:B99) -> 6200 | C100: =SUM(C88:C99) -> 0 | D100: =SUM(D88:D99) -> 6200 | E100: =E99 -> 6200

Sheet FATURAS_CARTAO
A1: ⚙️ CONFIGURAÇÃO DOS CARTÕES DE CRÉDITO
A3: Cartão | B3: Nome_Sistema | C3: Dia_Corte | D3: Dia_Vencimento
A4: Crédito Banco A - Maria | B4: BancoA_Maria | C4: 7 | D4: 15
A5: Crédito Banco B - Maria | B5: BancoB_Maria | C5: 9 | D5: 19
A6: Crédito Banco A - Carlos | B6: BancoA_Carlos | C6: 29 | D6: 5
A8: 📋 COMO FUNCIONA O CÁLCULO DA FATURA:
A10: 1. DIA_CORTE: Último dia para compras entrarem na fatura do mês
A11: 2. DIA_VENCIMENTO: Dia do pagamento da fatura
A13: Exemplo - Cartão Banco A Maria (Corte dia 7, Vencimento dia 15):
A14: • Compra em 05/01 → Entra na fatura de JAN → Vence 15/01
A15: • Compra em 10/01 → Entra na fatura de FEV → Vence 15/02
A17: ⚠️ IMPORTANTE: Os nomes em 'Cartão' devem ser EXATAMENTE iguais
A18: aos da tabela de configuração para o sistema funcionar.
A20: 📋 FATURAS VINCENDAS POR CARTÃO
A21: Mostra as próximas faturas com lançamentos para cada cartão (baseado em parcelas geradas)
A22: 📅 Data de Referência: | B22: =TODAY() -> 46160
A24: 💳 CRÉDITO BANCO A - CARLOS | K24: Datas Carlos | L24: Datas Maria A | M24: Datas Maria B
A25: Corte: dia 29 | Vencimento: dia 5 do mês seguinte | K25: =IFERROR(_xlfn.LET(_xlpm.minData,_xlfn.MINIFS(tbParcelas6[Data_Vencimento],tbParcelas6[Cartão],"Crédito INTER - João",tbParcelas6[Data_Vencimento],">="&$B$22),_xlpm.mesRef,EOMONTH(_xlpm.minData,-1)+1,DATE(YEAR(_xlpm.mesRef),MONTH(_xlpm.mesRef),VLOOKUP("Crédito INTER - João",tbConfigCartoes[],4,FALSE))),"-") -> - | L25: =IFERROR(_xlfn.LET(_xlpm.minData,_xlfn.MINIFS(tbParcelas6[Data_Vencimento],tbParcelas6[Cartão],"Crédito INTER - Ana",tbParcelas6[Data_Vencimento],">="&$B$22),_xlpm.mesRef,EOMONTH(_xlpm.minData,-1)+1,DATE(YEAR(_xlpm.mesRef),MONTH(_xlpm.mesRef),VLOOKUP("Crédito INTER - Ana",tbConfigCartoes[],4,FALSE))),"-") -> - | M25: =IFERROR(_xlfn.LET(_xlpm.minData,_xlfn.MINIFS(tbParcelas6[Data_Vencimento],tbParcelas6[Cartão],"Crédito Credicom Ana",tbParcelas6[Data_Vencimento],">="&$B$22),_xlpm.mesRef,EOMONTH(_xlpm.minData,-1)+1,DATE(YEAR(_xlpm.mesRef),MONTH(_xlpm.mesRef),VLOOKUP("Crédito Credicom Ana",tbConfigCartoes[],4,FALSE))),"-") -> -
A26: Vencimento | B26: Fatura | C26: Qtd Lançamentos | D26: Valor Total | E26: Status | F26: Dias p/ Vencer | K26: =IFERROR(_xlfn.LET(_xlpm.minData,_xlfn.MINIFS(tbParcelas6[Data_Vencimento],tbParcelas6[Cartão],"Crédito INTER - João",tbParcelas6[Data_Vencimento],">"&EOMONTH(K25,0)),_xlpm.mesRef,EOMONTH(_xlpm.minData,-1)+1,DATE(YEAR(_xlpm.mesRef),MONTH(_xlpm.mesRef),VLOOKUP("Crédito INTER - João",tbConfigCartoes[],4,FALSE))),"-") -> - | L26: =IFERROR(_xlfn.LET(_xlpm.minData,_xlfn.MINIFS(tbParcelas6[Data_Vencimento],tbParcelas6[Cartão],"Crédito INTER - Ana",tbParcelas6[Data_Vencimento],">"&EOMONTH(L25,0)),_xlpm.mesRef,EOMONTH(_xlpm.minData,-1)+1,DATE(YEAR(_xlpm.mesRef),MONTH(_xlpm.mesRef),VLOOKUP("Crédito INTER - Ana",tbConfigCartoes[],4,FALSE))),"-") -> - | M26: =IFERROR(_xlfn.LET(_xlpm.minData,_xlfn.MINIFS(tbParcelas6[Data_Vencimento],tbParcelas6[Cartão],"Crédito Credicom Ana",tbParcelas6[Data_Vencimento],">"&EOMONTH(M25,0)),_xlpm.mesRef,EOMONTH(_xlpm.minData,-1)+1,DATE(YEAR(_xlpm.mesRef),MONTH(_xlpm.mesRef),VLOOKUP("Crédito Credicom Ana",tbConfigCartoes[],4,FALSE))),"-") -> -
A27: =IF(K25="-","-",K25) -> - | B27: =IF(A27="-","-",TEXT(A27,"mmm")&"/"&YEAR(A27)) -> - | C27: =IF(A27="-","-",COUNTIFS(tbParcelas6[Cartão],"Crédito INTER - João",tbParcelas6[Data_Vencimento],">="&DATE(YEAR(A27),MONTH(A27),1),tbParcelas6[Data_Vencimento],"<="&EOMONTH(A27,0))) -> - | D27: =IF(A27="-","-",SUMIFS(tbParcelas6[Valor_Parcela],tbParcelas6[Cartão],"Crédito INTER - João",tbParcelas6[Data_Vencimento],">="&DATE(YEAR(A27),MONTH(A27),1),tbParcelas6[Data_Vencimento],"<="&EOMONTH(A27,0))) -> - | E27: =IF(A27="-","-",IF(A27<$B$22,"⚠️ Vencida",IF(A27-$B$22<=7,"🔴 Urgente",IF(A27-$B$22<=15,"🟡 Próxima","🟢 OK")))) -> - | F27: =IF(A27="-","-",A27-$B$22) -> - | K27: =IFERROR(_xlfn.LET(_xlpm.minData,_xlfn.MINIFS(tbParcelas6[Data_Vencimento],tbParcelas6[Cartão],"Crédito INTER - João",tbParcelas6[Data_Vencimento],">"&EOMONTH(K26,0)),_xlpm.mesRef,EOMONTH(_xlpm.minData,-1)+1,DATE(YEAR(_xlpm.mesRef),MONTH(_xlpm.mesRef),VLOOKUP("Crédito INTER - João",tbConfigCartoes[],4,FALSE))),"-") -> - | L27: =IFERROR(_xlfn.LET(_xlpm.minData,_xlfn.MINIFS(tbParcelas6[Data_Vencimento],tbParcelas6[Cartão],"Crédito INTER - Ana",tbParcelas6[Data_Vencimento],">"&EOMONTH(L26,0)),_xlpm.mesRef,EOMONTH(_xlpm.minData,-1)+1,DATE(YEAR(_xlpm.mesRef),MONTH(_xlpm.mesRef),VLOOKUP("Crédito INTER - Ana",tbConfigCartoes[],4,FALSE))),"-") -> - | M27: =IFERROR(_xlfn.LET(_xlpm.minData,_xlfn.MINIFS(tbParcelas6[Data_Vencimento],tbParcelas6[Cartão],"Crédito Credicom Ana",tbParcelas6[Data_Vencimento],">"&EOMONTH(M26,0)),_xlpm.mesRef,EOMONTH(_xlpm.minData,-1)+1,DATE(YEAR(_xlpm.mesRef),MONTH(_xlpm.mesRef),VLOOKUP("Crédito Credicom Ana",tbConfigCartoes[],4,FALSE))),"-") -> -
A28: =IF(K26="-","-",K26) -> - | B28: =IF(A28="-","-",TEXT(A28,"mmm")&"/"&YEAR(A28)) -> - | C28: =IF(A28="-","-",COUNTIFS(tbParcelas6[Cartão],"Crédito INTER - João",tbParcelas6[Data_Vencimento],">="&DATE(YEAR(A28),MONTH(A28),1),tbParcelas6[Data_Vencimento],"<="&EOMONTH(A28,0))) -> - | D28: =IF(A28="-","-",SUMIFS(tbParcelas6[Valor_Parcela],tbParcelas6[Cartão],"Crédito INTER - João",tbParcelas6[Data_Vencimento],">="&DATE(YEAR(A28),MONTH(A28),1),tbParcelas6[Data_Vencimento],"<="&EOMONTH(A28,0))) -> - | E28: =IF(A28="-","-",IF(A28<$B$22,"⚠️ Vencida",IF(A28-$B$22<=7,"🔴 Urgente",IF(A28-$B$22<=15,"🟡 Próxima","🟢 OK")))) -> - | F28: =IF(A28="-","-",A28-$B$22) -> - | K28: =IFERROR(_xlfn.LET(_xlpm.minData,_xlfn.MINIFS(tbParcelas6[Data_Vencimento],tbParcelas6[Cartão],"Crédito INTER - João",tbParcelas6[Data_Vencimento],">"&EOMONTH(K27,0)),_xlpm.mesRef,EOMONTH(_xlpm.minData,-1)+1,DATE(YEAR(_xlpm.mesRef),MONTH(_xlpm.mesRef),VLOOKUP("Crédito INTER - João",tbConfigCartoes[],4,FALSE))),"-") -> - | L28: =IFERROR(_xlfn.LET(_xlpm.minData,_xlfn.MINIFS(tbParcelas6[Data_Vencimento],tbParcelas6[Cartão],"Crédito INTER - Ana",tbParcelas6[Data_Vencimento],">"&EOMONTH(L27,0)),_xlpm.mesRef,EOMONTH(_xlpm.minData,-1)+1,DATE(YEAR(_xlpm.mesRef),MONTH(_xlpm.mesRef),VLOOKUP("Crédito INTER - Ana",tbConfigCartoes[],4,FALSE))),"-") -> - | M28: =IFERROR(_xlfn.LET(_xlpm.minData,_xlfn.MINIFS(tbParcelas6[Data_Vencimento],tbParcelas6[Cartão],"Crédito Credicom Ana",tbParcelas6[Data_Vencimento],">"&EOMONTH(M27,0)),_xlpm.mesRef,EOMONTH(_xlpm.minData,-1)+1,DATE(YEAR(_xlpm.mesRef),MONTH(_xlpm.mesRef),VLOOKUP("Crédito Credicom Ana",tbConfigCartoes[],4,FALSE))),"-") -> -
A29: =IF(K27="-","-",K27) -> - | B29: =IF(A29="-","-",TEXT(A29,"mmm")&"/"&YEAR(A29)) -> - | C29: =IF(A29="-","-",COUNTIFS(tbParcelas6[Cartão],"Crédito INTER - João",tbParcelas6[Data_Vencimento],">="&DATE(YEAR(A29),MONTH(A29),1),tbParcelas6[Data_Vencimento],"<="&EOMONTH(A29,0))) -> - | D29: =IF(A29="-","-",SUMIFS(tbParcelas6[Valor_Parcela],tbParcelas6[Cartão],"Crédito INTER - João",tbParcelas6[Data_Vencimento],">="&DATE(YEAR(A29),MONTH(A29),1),tbParcelas6[Data_Vencimento],"<="&EOMONTH(A29,0))) -> - | E29: =IF(A29="-","-",IF(A29<$B$22,"⚠️ Vencida",IF(A29-$B$22<=7,"🔴 Urgente",IF(A29-$B$22<=15,"🟡 Próxima","🟢 OK")))) -> - | F29: =IF(A29="-","-",A29-$B$22) -> - | K29: =IFERROR(_xlfn.LET(_xlpm.minData,_xlfn.MINIFS(tbParcelas6[Data_Vencimento],tbParcelas6[Cartão],"Crédito INTER - João",tbParcelas6[Data_Vencimento],">"&EOMONTH(K28,0)),_xlpm.mesRef,EOMONTH(_xlpm.minData,-1)+1,DATE(YEAR(_xlpm.mesRef),MONTH(_xlpm.mesRef),VLOOKUP("Crédito INTER - João",tbConfigCartoes[],4,FALSE))),"-") -> - | L29: =IFERROR(_xlfn.LET(_xlpm.minData,_xlfn.MINIFS(tbParcelas6[Data_Vencimento],tbParcelas6[Cartão],"Crédito INTER - Ana",tbParcelas6[Data_Vencimento],">"&EOMONTH(L28,0)),_xlpm.mesRef,EOMONTH(_xlpm.minData,-1)+1,DATE(YEAR(_xlpm.mesRef),MONTH(_xlpm.mesRef),VLOOKUP("Crédito INTER - Ana",tbConfigCartoes[],4,FALSE))),"-") -> - | M29: =IFERROR(_xlfn.LET(_xlpm.minData,_xlfn.MINIFS(tbParcelas6[Data_Vencimento],tbParcelas6[Cartão],"Crédito Credicom Ana",tbParcelas6[Data_Vencimento],">"&EOMONTH(M28,0)),_xlpm.mesRef,EOMONTH(_xlpm.minData,-1)+1,DATE(YEAR(_xlpm.mesRef),MONTH(_xlpm.mesRef),VLOOKUP("Crédito Credicom Ana",tbConfigCartoes[],4,FALSE))),"-") -> -
A30: =IF(K28="-","-",K28) -> - | B30: =IF(A30="-","-",TEXT(A30,"mmm")&"/"&YEAR(A30)) -> - | C30: =IF(A30="-","-",COUNTIFS(tbParcelas6[Cartão],"Crédito INTER - João",tbParcelas6[Data_Vencimento],">="&DATE(YEAR(A30),MONTH(A30),1),tbParcelas6[Data_Vencimento],"<="&EOMONTH(A30,0))) -> - | D30: =IF(A30="-","-",SUMIFS(tbParcelas6[Valor_Parcela],tbParcelas6[Cartão],"Crédito INTER - João",tbParcelas6[Data_Vencimento],">="&DATE(YEAR(A30),MONTH(A30),1),tbParcelas6[Data_Vencimento],"<="&EOMONTH(A30,0))) -> - | E30: =IF(A30="-","-",IF(A30<$B$22,"⚠️ Vencida",IF(A30-$B$22<=7,"🔴 Urgente",IF(A30-$B$22<=15,"🟡 Próxima","🟢 OK")))) -> - | F30: =IF(A30="-","-",A30-$B$22) -> - | K30: =IFERROR(_xlfn.LET(_xlpm.minData,_xlfn.MINIFS(tbParcelas6[Data_Vencimento],tbParcelas6[Cartão],"Crédito INTER - João",tbParcelas6[Data_Vencimento],">"&EOMONTH(K29,0)),_xlpm.mesRef,EOMONTH(_xlpm.minData,-1)+1,DATE(YEAR(_xlpm.mesRef),MONTH(_xlpm.mesRef),VLOOKUP("Crédito INTER - João",tbConfigCartoes[],4,FALSE))),"-") -> - | L30: =IFERROR(_xlfn.LET(_xlpm.minData,_xlfn.MINIFS(tbParcelas6[Data_Vencimento],tbParcelas6[Cartão],"Crédito INTER - Ana",tbParcelas6[Data_Vencimento],">"&EOMONTH(L29,0)),_xlpm.mesRef,EOMONTH(_xlpm.minData,-1)+1,DATE(YEAR(_xlpm.mesRef),MONTH(_xlpm.mesRef),VLOOKUP("Crédito INTER - Ana",tbConfigCartoes[],4,FALSE))),"-") -> - | M30: =IFERROR(_xlfn.LET(_xlpm.minData,_xlfn.MINIFS(tbParcelas6[Data_Vencimento],tbParcelas6[Cartão],"Crédito Credicom Ana",tbParcelas6[Data_Vencimento],">"&EOMONTH(M29,0)),_xlpm.mesRef,EOMONTH(_xlpm.minData,-1)+1,DATE(YEAR(_xlpm.mesRef),MONTH(_xlpm.mesRef),VLOOKUP("Crédito Credicom Ana",tbConfigCartoes[],4,FALSE))),"-") -> -
A31: =IF(K29="-","-",K29) -> - | B31: =IF(A31="-","-",TEXT(A31,"mmm")&"/"&YEAR(A31)) -> - | C31: =IF(A31="-","-",COUNTIFS(tbParcelas6[Cartão],"Crédito INTER - João",tbParcelas6[Data_Vencimento],">="&DATE(YEAR(A31),MONTH(A31),1),tbParcelas6[Data_Vencimento],"<="&EOMONTH(A31,0))) -> - | D31: =IF(A31="-","-",SUMIFS(tbParcelas6[Valor_Parcela],tbParcelas6[Cartão],"Crédito INTER - João",tbParcelas6[Data_Vencimento],">="&DATE(YEAR(A31),MONTH(A31),1),tbParcelas6[Data_Vencimento],"<="&EOMONTH(A31,0))) -> - | E31: =IF(A31="-","-",IF(A31<$B$22,"⚠️ Vencida",IF(A31-$B$22<=7,"🔴 Urgente",IF(A31-$B$22<=15,"🟡 Próxima","🟢 OK")))) -> - | F31: =IF(A31="-","-",A31-$B$22) -> - | K31: =IFERROR(_xlfn.LET(_xlpm.minData,_xlfn.MINIFS(tbParcelas6[Data_Vencimento],tbParcelas6[Cartão],"Crédito INTER - João",tbParcelas6[Data_Vencimento],">"&EOMONTH(K30,0)),_xlpm.mesRef,EOMONTH(_xlpm.minData,-1)+1,DATE(YEAR(_xlpm.mesRef),MONTH(_xlpm.mesRef),VLOOKUP("Crédito INTER - João",tbConfigCartoes[],4,FALSE))),"-") -> - | L31: =IFERROR(_xlfn.LET(_xlpm.minData,_xlfn.MINIFS(tbParcelas6[Data_Vencimento],tbParcelas6[Cartão],"Crédito INTER - Ana",tbParcelas6[Data_Vencimento],">"&EOMONTH(L30,0)),_xlpm.mesRef,EOMONTH(_xlpm.minData,-1)+1,DATE(YEAR(_xlpm.mesRef),MONTH(_xlpm.mesRef),VLOOKUP("Crédito INTER - Ana",tbConfigCartoes[],4,FALSE))),"-") -> - | M31: =IFERROR(_xlfn.LET(_xlpm.minData,_xlfn.MINIFS(tbParcelas6[Data_Vencimento],tbParcelas6[Cartão],"Crédito Credicom Ana",tbParcelas6[Data_Vencimento],">"&EOMONTH(M30,0)),_xlpm.mesRef,EOMONTH(_xlpm.minData,-1)+1,DATE(YEAR(_xlpm.mesRef),MONTH(_xlpm.mesRef),VLOOKUP("Crédito Credicom Ana",tbConfigCartoes[],4,FALSE))),"-") -> -
A32: =IF(K30="-","-",K30) -> - | B32: =IF(A32="-","-",TEXT(A32,"mmm")&"/"&YEAR(A32)) -> - | C32: =IF(A32="-","-",COUNTIFS(tbParcelas6[Cartão],"Crédito INTER - João",tbParcelas6[Data_Vencimento],">="&DATE(YEAR(A32),MONTH(A32),1),tbParcelas6[Data_Vencimento],"<="&EOMONTH(A32,0))) -> - | D32: =IF(A32="-","-",SUMIFS(tbParcelas6[Valor_Parcela],tbParcelas6[Cartão],"Crédito INTER - João",tbParcelas6[Data_Vencimento],">="&DATE(YEAR(A32),MONTH(A32),1),tbParcelas6[Data_Vencimento],"<="&EOMONTH(A32,0))) -> - | E32: =IF(A32="-","-",IF(A32<$B$22,"⚠️ Vencida",IF(A32-$B$22<=7,"🔴 Urgente",IF(A32-$B$22<=15,"🟡 Próxima","🟢 OK")))) -> - | F32: =IF(A32="-","-",A32-$B$22) -> - | K32: =IFERROR(_xlfn.LET(_xlpm.minData,_xlfn.MINIFS(tbParcelas6[Data_Vencimento],tbParcelas6[Cartão],"Crédito INTER - João",tbParcelas6[Data_Vencimento],">"&EOMONTH(K31,0)),_xlpm.mesRef,EOMONTH(_xlpm.minData,-1)+1,DATE(YEAR(_xlpm.mesRef),MONTH(_xlpm.mesRef),VLOOKUP("Crédito INTER - João",tbConfigCartoes[],4,FALSE))),"-") -> - | L32: =IFERROR(_xlfn.LET(_xlpm.minData,_xlfn.MINIFS(tbParcelas6[Data_Vencimento],tbParcelas6[Cartão],"Crédito INTER - Ana",tbParcelas6[Data_Vencimento],">"&EOMONTH(L31,0)),_xlpm.mesRef,EOMONTH(_xlpm.minData,-1)+1,DATE(YEAR(_xlpm.mesRef),MONTH(_xlpm.mesRef),VLOOKUP("Crédito INTER - Ana",tbConfigCartoes[],4,FALSE))),"-") -> - | M32: =IFERROR(_xlfn.LET(_xlpm.minData,_xlfn.MINIFS(tbParcelas6[Data_Vencimento],tbParcelas6[Cartão],"Crédito Credicom Ana",tbParcelas6[Data_Vencimento],">"&EOMONTH(M31,0)),_xlpm.mesRef,EOMONTH(_xlpm.minData,-1)+1,DATE(YEAR(_xlpm.mesRef),MONTH(_xlpm.mesRef),VLOOKUP("Crédito Credicom Ana",tbConfigCartoes[],4,FALSE))),"-") -> -
A33: =IF(K31="-","-",K31) -> - | B33: =IF(A33="-","-",TEXT(A33,"mmm")&"/"&YEAR(A33)) -> - | C33: =IF(A33="-","-",COUNTIFS(tbParcelas6[Cartão],"Crédito INTER - João",tbParcelas6[Data_Vencimento],">="&DATE(YEAR(A33),MONTH(A33),1),tbParcelas6[Data_Vencimento],"<="&EOMONTH(A33,0))) -> - | D33: =IF(A33="-","-",SUMIFS(tbParcelas6[Valor_Parcela],tbParcelas6[Cartão],"Crédito INTER - João",tbParcelas6[Data_Vencimento],">="&DATE(YEAR(A33),MONTH(A33),1),tbParcelas6[Data_Vencimento],"<="&EOMONTH(A33,0))) -> - | E33: =IF(A33="-","-",IF(A33<$B$22,"⚠️ Vencida",IF(A33-$B$22<=7,"🔴 Urgente",IF(A33-$B$22<=15,"🟡 Próxima","🟢 OK")))) -> - | F33: =IF(A33="-","-",A33-$B$22) -> - | K33: =IFERROR(EOMONTH(_xlfn.MINIFS(#REF!,#REF!,"Crédito INTER - João",#REF!,">"&EOMONTH(K32,0)),-1)+1,"-") -> - | L33: =IFERROR(EOMONTH(_xlfn.MINIFS(#REF!,#REF!,"Crédito INTER - Ana",#REF!,">"&EOMONTH(L32,0)),-1)+1,"-") -> - | M33: =IFERROR(EOMONTH(_xlfn.MINIFS(#REF!,#REF!,"Crédito Credicom Ana",#REF!,">"&EOMONTH(M32,0)),-1)+1,"-") -> -
A34: =IF(K32="-","-",K32) -> - | B34: =IF(A34="-","-",TEXT(A34,"mmm")&"/"&YEAR(A34)) -> - | C34: =IF(A34="-","-",COUNTIFS(tbParcelas6[Cartão],"Crédito INTER - João",tbParcelas6[Data_Vencimento],">="&DATE(YEAR(A34),MONTH(A34),1),tbParcelas6[Data_Vencimento],"<="&EOMONTH(A34,0))) -> - | D34: =IF(A34="-","-",SUMIFS(tbParcelas6[Valor_Parcela],tbParcelas6[Cartão],"Crédito INTER - João",tbParcelas6[Data_Vencimento],">="&DATE(YEAR(A34),MONTH(A34),1),tbParcelas6[Data_Vencimento],"<="&EOMONTH(A34,0))) -> - | E34: =IF(A34="-","-",IF(A34<$B$22,"⚠️ Vencida",IF(A34-$B$22<=7,"🔴 Urgente",IF(A34-$B$22<=15,"🟡 Próxima","🟢 OK")))) -> - | F34: =IF(A34="-","-",A34-$B$22) -> - | K34: =IFERROR(EOMONTH(_xlfn.MINIFS(#REF!,#REF!,"Crédito INTER - João",#REF!,">"&EOMONTH(K33,0)),-1)+1,"-") -> - | L34: =IFERROR(EOMONTH(_xlfn.MINIFS(#REF!,#REF!,"Crédito INTER - Ana",#REF!,">"&EOMONTH(L33,0)),-1)+1,"-") -> - | M34: =IFERROR(EOMONTH(_xlfn.MINIFS(#REF!,#REF!,"Crédito Credicom Ana",#REF!,">"&EOMONTH(M33,0)),-1)+1,"-") -> -
A35: =IF(K33="-","-",K33) -> - | B35: =IF(A35="-","-",TEXT(A35,"mmm")&"/"&YEAR(A35)) -> - | C35: =IF(A35="-","-",COUNTIFS(tbParcelas6[Cartão],"Crédito INTER - João",tbParcelas6[Data_Vencimento],">="&DATE(YEAR(A35),MONTH(A35),1),tbParcelas6[Data_Vencimento],"<="&EOMONTH(A35,0))) -> - | D35: =IF(A35="-","-",SUMIFS(tbParcelas6[Valor_Parcela],tbParcelas6[Cartão],"Crédito INTER - João",tbParcelas6[Data_Vencimento],">="&DATE(YEAR(A35),MONTH(A35),1),tbParcelas6[Data_Vencimento],"<="&EOMONTH(A35,0))) -> - | E35: =IF(A35="-","-",IF(A35<$B$22,"⚠️ Vencida",IF(A35-$B$22<=7,"🔴 Urgente",IF(A35-$B$22<=15,"🟡 Próxima","🟢 OK")))) -> - | F35: =IF(A35="-","-",A35-$B$22) -> -
A36: =IF(K34="-","-",K34) -> - | B36: =IF(A36="-","-",TEXT(A36,"mmm")&"/"&YEAR(A36)) -> - | C36: =IF(A36="-","-",COUNTIFS(tbParcelas6[Cartão],"Crédito INTER - João",tbParcelas6[Data_Vencimento],A36)) -> - | D36: =IF(A36="-","-",SUMIFS(tbParcelas6[Valor_Parcela],tbParcelas6[Cartão],"Crédito INTER - João",tbParcelas6[Data_Vencimento],A36)) -> - | E36: =IF(A36="-","-",IF(A36<$B$22,"⚠️ Vencida",IF(A36-$B$22<=7,"🔴 Urgente",IF(A36-$B$22<=15,"🟡 Próxima","🟢 OK")))) -> - | F36: =IF(A36="-","-",A36-$B$22) -> -
A39: 💳 CRÉDITO BANCO A - MARIA
A40: Corte: dia 7 | Vencimento: dia 15
A41: Vencimento | B41: Fatura | C41: Qtd Lançamentos | D41: Valor Total | E41: Status | F41: Dias p/ Vencer
A42: =IF(L25="-","-",L25) -> - | B42: =IF(A42="-","-",TEXT(A42,"mmm")&"/"&YEAR(A42)) -> - | C42: =IF(A42="-","-",COUNTIFS(tbParcelas6[Cartão],"Crédito INTER - Ana",tbParcelas6[Data_Vencimento],">="&DATE(YEAR(A42),MONTH(A42),1),tbParcelas6[Data_Vencimento],"<="&EOMONTH(A42,0))) -> - | D42: =IF(A42="-","-",SUMIFS(tbParcelas6[Valor_Parcela],tbParcelas6[Cartão],"Crédito INTER - Ana",tbParcelas6[Data_Vencimento],">="&DATE(YEAR(A42),MONTH(A42),1),tbParcelas6[Data_Vencimento],"<="&EOMONTH(A42,0))) -> - | E42: =IF(A42="-","-",IF(A42<$B$22,"⚠️ Vencida",IF(A42-$B$22<=7,"🔴 Urgente",IF(A42-$B$22<=15,"🟡 Próxima","🟢 OK")))) -> - | F42: =IF(A42="-","-",A42-$B$22) -> -
A43: =IF(L26="-","-",L26) -> - | B43: =IF(A43="-","-",TEXT(A43,"mmm")&"/"&YEAR(A43)) -> - | C43: =IF(A43="-","-",COUNTIFS(tbParcelas6[Cartão],"Crédito INTER - Ana",tbParcelas6[Data_Vencimento],">="&DATE(YEAR(A43),MONTH(A43),1),tbParcelas6[Data_Vencimento],"<="&EOMONTH(A43,0))) -> - | D43: =IF(A43="-","-",SUMIFS(tbParcelas6[Valor_Parcela],tbParcelas6[Cartão],"Crédito INTER - Ana",tbParcelas6[Data_Vencimento],">="&DATE(YEAR(A43),MONTH(A43),1),tbParcelas6[Data_Vencimento],"<="&EOMONTH(A43,0))) -> - | E43: =IF(A43="-","-",IF(A43<$B$22,"⚠️ Vencida",IF(A43-$B$22<=7,"🔴 Urgente",IF(A43-$B$22<=15,"🟡 Próxima","🟢 OK")))) -> - | F43: =IF(A43="-","-",A43-$B$22) -> -
A44: =IF(L27="-","-",L27) -> - | B44: =IF(A44="-","-",TEXT(A44,"mmm")&"/"&YEAR(A44)) -> - | C44: =IF(A44="-","-",COUNTIFS(tbParcelas6[Cartão],"Crédito INTER - Ana",tbParcelas6[Data_Vencimento],">="&DATE(YEAR(A44),MONTH(A44),1),tbParcelas6[Data_Vencimento],"<="&EOMONTH(A44,0))) -> - | D44: =IF(A44="-","-",SUMIFS(tbParcelas6[Valor_Parcela],tbParcelas6[Cartão],"Crédito INTER - Ana",tbParcelas6[Data_Vencimento],">="&DATE(YEAR(A44),MONTH(A44),1),tbParcelas6[Data_Vencimento],"<="&EOMONTH(A44,0))) -> - | E44: =IF(A44="-","-",IF(A44<$B$22,"⚠️ Vencida",IF(A44-$B$22<=7,"🔴 Urgente",IF(A44-$B$22<=15,"🟡 Próxima","🟢 OK")))) -> - | F44: =IF(A44="-","-",A44-$B$22) -> -
A45: =IF(L28="-","-",L28) -> - | B45: =IF(A45="-","-",TEXT(A45,"mmm")&"/"&YEAR(A45)) -> - | C45: =IF(A45="-","-",COUNTIFS(tbParcelas6[Cartão],"Crédito INTER - Ana",tbParcelas6[Data_Vencimento],">="&DATE(YEAR(A45),MONTH(A45),1),tbParcelas6[Data_Vencimento],"<="&EOMONTH(A45,0))) -> - | D45: =IF(A45="-","-",SUMIFS(tbParcelas6[Valor_Parcela],tbParcelas6[Cartão],"Crédito INTER - Ana",tbParcelas6[Data_Vencimento],">="&DATE(YEAR(A45),MONTH(A45),1),tbParcelas6[Data_Vencimento],"<="&EOMONTH(A45,0))) -> - | E45: =IF(A45="-","-",IF(A45<$B$22,"⚠️ Vencida",IF(A45-$B$22<=7,"🔴 Urgente",IF(A45-$B$22<=15,"🟡 Próxima","🟢 OK")))) -> - | F45: =IF(A45="-","-",A45-$B$22) -> -
A46: =IF(L29="-","-",L29) -> - | B46: =IF(A46="-","-",TEXT(A46,"mmm")&"/"&YEAR(A46)) -> - | C46: =IF(A46="-","-",COUNTIFS(tbParcelas6[Cartão],"Crédito INTER - Ana",tbParcelas6[Data_Vencimento],">="&DATE(YEAR(A46),MONTH(A46),1),tbParcelas6[Data_Vencimento],"<="&EOMONTH(A46,0))) -> - | D46: =IF(A46="-","-",SUMIFS(tbParcelas6[Valor_Parcela],tbParcelas6[Cartão],"Crédito INTER - Ana",tbParcelas6[Data_Vencimento],">="&DATE(YEAR(A46),MONTH(A46),1),tbParcelas6[Data_Vencimento],"<="&EOMONTH(A46,0))) -> - | E46: =IF(A46="-","-",IF(A46<$B$22,"⚠️ Vencida",IF(A46-$B$22<=7,"🔴 Urgente",IF(A46-$B$22<=15,"🟡 Próxima","🟢 OK")))) -> - | F46: =IF(A46="-","-",A46-$B$22) -> -
A47: =IF(L30="-","-",L30) -> - | B47: =IF(A47="-","-",TEXT(A47,"mmm")&"/"&YEAR(A47)) -> - | C47: =IF(A47="-","-",COUNTIFS(tbParcelas6[Cartão],"Crédito INTER - Ana",tbParcelas6[Data_Vencimento],">="&DATE(YEAR(A47),MONTH(A47),1),tbParcelas6[Data_Vencimento],"<="&EOMONTH(A47,0))) -> - | D47: =IF(A47="-","-",SUMIFS(tbParcelas6[Valor_Parcela],tbParcelas6[Cartão],"Crédito INTER - Ana",tbParcelas6[Data_Vencimento],">="&DATE(YEAR(A47),MONTH(A47),1),tbParcelas6[Data_Vencimento],"<="&EOMONTH(A47,0))) -> - | E47: =IF(A47="-","-",IF(A47<$B$22,"⚠️ Vencida",IF(A47-$B$22<=7,"🔴 Urgente",IF(A47-$B$22<=15,"🟡 Próxima","🟢 OK")))) -> - | F47: =IF(A47="-","-",A47-$B$22) -> -
A48: =IF(L31="-","-",L31) -> - | B48: =IF(A48="-","-",TEXT(A48,"mmm")&"/"&YEAR(A48)) -> - | C48: =IF(A48="-","-",COUNTIFS(tbParcelas6[Cartão],"Crédito INTER - Ana",tbParcelas6[Data_Vencimento],">="&DATE(YEAR(A48),MONTH(A48),1),tbParcelas6[Data_Vencimento],"<="&EOMONTH(A48,0))) -> - | D48: =IF(A48="-","-",SUMIFS(tbParcelas6[Valor_Parcela],tbParcelas6[Cartão],"Crédito INTER - Ana",tbParcelas6[Data_Vencimento],">="&DATE(YEAR(A48),MONTH(A48),1),tbParcelas6[Data_Vencimento],"<="&EOMONTH(A48,0))) -> - | E48: =IF(A48="-","-",IF(A48<$B$22,"⚠️ Vencida",IF(A48-$B$22<=7,"🔴 Urgente",IF(A48-$B$22<=15,"🟡 Próxima","🟢 OK")))) -> - | F48: =IF(A48="-","-",A48-$B$22) -> -
A49: 💳 CRÉDITO BANCO B - MARIA
A50: Corte: dia 9 | Vencimento: dia 19
A51: Vencimento | B51: Fatura | C51: Qtd Lançamentos | D51: Valor Total | E51: Status | F51: Dias p/ Vencer
A52: =IF(M25="-","-",M25) -> - | B52: =IF(A52="-","-",TEXT(A52,"mmm")&"/"&YEAR(A52)) -> - | C52: =IF(A52="-","-",COUNTIFS(tbParcelas6[Cartão],"Crédito Credicom Ana",tbParcelas6[Data_Vencimento],">="&DATE(YEAR(A52),MONTH(A52),1),tbParcelas6[Data_Vencimento],"<="&EOMONTH(A52,0))) -> - | D52: =IF(A52="-","-",SUMIFS(tbParcelas6[Valor_Parcela],tbParcelas6[Cartão],"Crédito Credicom Ana",tbParcelas6[Data_Vencimento],">="&DATE(YEAR(A52),MONTH(A52),1),tbParcelas6[Data_Vencimento],"<="&EOMONTH(A52,0))) -> - | E52: =IF(A52="-","-",IF(A52<$B$22,"⚠️ Vencida",IF(A52-$B$22<=7,"🔴 Urgente",IF(A52-$B$22<=15,"🟡 Próxima","🟢 OK")))) -> - | F52: =IF(A52="-","-",A52-$B$22) -> -
A53: =IF(M26="-","-",M26) -> - | B53: =IF(A53="-","-",TEXT(A53,"mmm")&"/"&YEAR(A53)) -> - | C53: =IF(A53="-","-",COUNTIFS(tbParcelas6[Cartão],"Crédito Credicom Ana",tbParcelas6[Data_Vencimento],">="&DATE(YEAR(A53),MONTH(A53),1),tbParcelas6[Data_Vencimento],"<="&EOMONTH(A53,0))) -> - | D53: =IF(A53="-","-",SUMIFS(tbParcelas6[Valor_Parcela],tbParcelas6[Cartão],"Crédito Credicom Ana",tbParcelas6[Data_Vencimento],">="&DATE(YEAR(A53),MONTH(A53),1),tbParcelas6[Data_Vencimento],"<="&EOMONTH(A53,0))) -> - | E53: =IF(A53="-","-",IF(A53<$B$22,"⚠️ Vencida",IF(A53-$B$22<=7,"🔴 Urgente",IF(A53-$B$22<=15,"🟡 Próxima","🟢 OK")))) -> - | F53: =IF(A53="-","-",A53-$B$22) -> -
A61: 📊 RESUMO DOS CARTÕES
A62: Cartão | B62: Próximo Vencimento | C62: Valor | D62: Status | E62: Dias
A63: Crédito Banco A - Carlos | B63: =A27 -> - | C63: =IF(A63="-","-",D27) -> - | D63: =E27 -> - | E63: =F27 -> -
A64: Crédito Banco A - Maria | B64: =IF(A42="-","-",A42) -> - | C64: =IF(D42="-",0,D42) -> 0 | D64: =E42 -> - | E64: =F42 -> -
A65: Crédito Banco B - Maria | B65: =IF(A52="-","-",A52) -> - | C65: =IF(D52="-",0,D52) -> 0 | D65: =E52 -> - | E65: =F52 -> -
A68: 💰 TOTAL PRÓXIMAS FATURAS: | C68: =SUM(C63:C65) -> 0
A71: 💡 LEGENDA DE STATUS:
A72: 🔴 Urgente = vence em até 7 dias | 🟡 Próxima = vence em até 15 dias | 🟢 OK = mais de 15 dias | ⚠️ Vencida
A74: ⚠️ NOTA: As parcelas são baseadas nos lançamentos da aba LAN_CARTOES. Se um cartão não aparecer,
A75: verifique se as parcelas foram geradas corretamente na aba PARCELAS.

Sheet PREVISOES
A1: 💰 CONTROLE DE PREVISÕES FINANCEIRAS
A2: Gestão de Receitas e Despesas Previstas | Fluxo de Caixa Projetado
A4: 📅 DATA | B4: 📂 TIPO | C4: 📁 CATEGORIA | D4: 📋 SUBCATEGORIA | E4: 💰 VALOR | F4: 📝 DESCRIÇÃO | G4: ✅ STATUS

Sheet LAN_INVESTIMENTOS
A1: 📈 LANÇAMENTO DE INVESTIMENTOS | H1: 📊 RESUMO DE INVESTIMENTOS
A2: Controle de Aportes e Resgates | H2: 🔍 Filtros: | I2: ANO: | J2: 2026 | K2: MÊS: | L2: 0
A3: Data | B3: Ativo | C3: Tipo_Ativo | D3: Movimento | E3: Valor | F3: Obs | H3: (Mês 0 = Ano completo)
A4: 45671 | B4: Tesouro Direto | C4: Renda Fixa | D4: Aporte | E4: 300 | F4: Aporte mensal RF
A5: 45671 | B5: ETF | C5: Renda Variável | D5: Aporte | E5: 100 | F5: Aporte mensal RV | H5: Tipo de Ativo | I5: Aportes | J5: Resgates | K5: Saldo Líquido | L5: % do Total
A6: 45671 | B6: Previdência Privada | C6: Previdência | D6: Aporte | E6: 100 | F6: Aporte mensal Prev | H6: Renda Fixa | I6: {=SUMPRODUCT((tb_investimentos[Tipo_Ativo]="Renda Fixa")*(tb_investimentos[Movimento]="Aporte")*(YEAR(tb_investimentos[Data])=$J$2)*(IF($L$2=0,1,MONTH(tb_investimentos[Data])=$L$2))*tb_investimentos[Valor])} -> 0 | J6: {=SUMPRODUCT((tb_investimentos[Tipo_Ativo]="Renda Fixa")*(tb_investimentos[Movimento]="Resgate")*(YEAR(tb_investimentos[Data])=$J$2)*(IF($L$2=0,1,MONTH(tb_investimentos[Data])=$L$2))*tb_investimentos[Valor])} -> 0 | K6: =I6-J6 -> 0 | L6: =IFERROR(K6/SUM($K$6:$K$9),0) -> 0
A7: 45702 | B7: Tesouro Direto | C7: Renda Fixa | D7: Aporte | E7: 300 | F7: Aporte mensal RF | H7: Renda Variável | I7: {=SUMPRODUCT((tb_investimentos[Tipo_Ativo]="Renda Variável")*(tb_investimentos[Movimento]="Aporte")*(YEAR(tb_investimentos[Data])=$J$2)*(IF($L$2=0,1,MONTH(tb_investimentos[Data])=$L$2))*tb_investimentos[Valor])} -> 0 | J7: {=SUMPRODUCT((tb_investimentos[Tipo_Ativo]="Renda Variável")*(tb_investimentos[Movimento]="Resgate")*(YEAR(tb_investimentos[Data])=$J$2)*(IF($L$2=0,1,MONTH(tb_investimentos[Data])=$L$2))*tb_investimentos[Valor])} -> 0 | K7: =I7-J7 -> 0 | L7: =IFERROR(K7/SUM($K$6:$K$9),0) -> 0
A8: 45702 | B8: ETF | C8: Renda Variável | D8: Aporte | E8: 100 | F8: Aporte mensal RV | H8: Previdência | I8: {=SUMPRODUCT((tb_investimentos[Tipo_Ativo]="Previdência")*(tb_investimentos[Movimento]="Aporte")*(YEAR(tb_investimentos[Data])=$J$2)*(IF($L$2=0,1,MONTH(tb_investimentos[Data])=$L$2))*tb_investimentos[Valor])} -> 0 | J8: {=SUMPRODUCT((tb_investimentos[Tipo_Ativo]="Previdência")*(tb_investimentos[Movimento]="Resgate")*(YEAR(tb_investimentos[Data])=$J$2)*(IF($L$2=0,1,MONTH(tb_investimentos[Data])=$L$2))*tb_investimentos[Valor])} -> 0 | K8: =I8-J8 -> 0 | L8: =IFERROR(K8/SUM($K$6:$K$9),0) -> 0
A9: 45702 | B9: Previdência Privada | C9: Previdência | D9: Aporte | E9: 100 | F9: Aporte mensal Prev | H9: Alternativos | I9: {=SUMPRODUCT((tb_investimentos[Tipo_Ativo]="Alternativos")*(tb_investimentos[Movimento]="Aporte")*(YEAR(tb_investimentos[Data])=$J$2)*(IF($L$2=0,1,MONTH(tb_investimentos[Data])=$L$2))*tb_investimentos[Valor])} -> 0 | J9: {=SUMPRODUCT((tb_investimentos[Tipo_Ativo]="Alternativos")*(tb_investimentos[Movimento]="Resgate")*(YEAR(tb_investimentos[Data])=$J$2)*(IF($L$2=0,1,MONTH(tb_investimentos[Data])=$L$2))*tb_investimentos[Valor])} -> 0 | K9: =I9-J9 -> 0 | L9: =IFERROR(K9/SUM($K$6:$K$9),0) -> 0
A10: 45730 | B10: Tesouro Direto | C10: Renda Fixa | D10: Aporte | E10: 300 | F10: Aporte mensal RF | H10: TOTAL | I10: =SUM(I6:I9) -> 0 | J10: =SUM(J6:J9) -> 0 | K10: =SUM(K6:K9) -> 0 | L10: =SUM(L6:L9) -> 0
A11: 45730 | B11: ETF | C11: Renda Variável | D11: Aporte | E11: 100 | F11: Aporte mensal RV
A12: 45730 | B12: Previdência Privada | C12: Previdência | D12: Aporte | E12: 100 | F12: Aporte mensal Prev | H12: 📈 EVOLUÇÃO MENSAL
A13: 45761 | B13: Tesouro Direto | C13: Renda Fixa | D13: Aporte | E13: 300 | F13: Aporte mensal RF | H13: Mês | I13: Aportes | J13: Resgates | K13: Saldo Mês | L13: Acumulado
A14: 45761 | B14: ETF | C14: Renda Variável | D14: Aporte | E14: 100 | F14: Aporte mensal RV | H14: Jan | I14: {=SUMPRODUCT((tb_investimentos[Movimento]="Aporte")*(YEAR(tb_investimentos[Data])=$J$2)*(MONTH(tb_investimentos[Data])=1)*tb_investimentos[Valor])} -> 0 | J14: {=SUMPRODUCT((tb_investimentos[Movimento]="Resgate")*(YEAR(tb_investimentos[Data])=$J$2)*(MONTH(tb_investimentos[Data])=1)*tb_investimentos[Valor])} -> 0 | K14: =I14-J14 -> 0 | L14: =K14 -> 0
A15: 45761 | B15: Previdência Privada | C15: Previdência | D15: Aporte | E15: 100 | F15: Aporte mensal Prev | H15: Fev | I15: {=SUMPRODUCT((tb_investimentos[Movimento]="Aporte")*(YEAR(tb_investimentos[Data])=$J$2)*(MONTH(tb_investimentos[Data])=2)*tb_investimentos[Valor])} -> 0 | J15: {=SUMPRODUCT((tb_investimentos[Movimento]="Resgate")*(YEAR(tb_investimentos[Data])=$J$2)*(MONTH(tb_investimentos[Data])=2)*tb_investimentos[Valor])} -> 0 | K15: =I15-J15 -> 0 | L15: =L14+K15 -> 0
A16: 45791 | B16: Tesouro Direto | C16: Renda Fixa | D16: Aporte | E16: 300 | F16: Aporte mensal RF | H16: Mar | I16: {=SUMPRODUCT((tb_investimentos[Movimento]="Aporte")*(YEAR(tb_investimentos[Data])=$J$2)*(MONTH(tb_investimentos[Data])=3)*tb_investimentos[Valor])} -> 0 | J16: {=SUMPRODUCT((tb_investimentos[Movimento]="Resgate")*(YEAR(tb_investimentos[Data])=$J$2)*(MONTH(tb_investimentos[Data])=3)*tb_investimentos[Valor])} -> 0 | K16: =I16-J16 -> 0 | L16: =L15+K16 -> 0
A17: 45791 | B17: ETF | C17: Renda Variável | D17: Aporte | E17: 100 | F17: Aporte mensal RV | H17: Abr | I17: {=SUMPRODUCT((tb_investimentos[Movimento]="Aporte")*(YEAR(tb_investimentos[Data])=$J$2)*(MONTH(tb_investimentos[Data])=4)*tb_investimentos[Valor])} -> 0 | J17: {=SUMPRODUCT((tb_investimentos[Movimento]="Resgate")*(YEAR(tb_investimentos[Data])=$J$2)*(MONTH(tb_investimentos[Data])=4)*tb_investimentos[Valor])} -> 0 | K17: =I17-J17 -> 0 | L17: =L16+K17 -> 0
A18: 45791 | B18: Previdência Privada | C18: Previdência | D18: Aporte | E18: 100 | F18: Aporte mensal Prev | H18: Mai | I18: {=SUMPRODUCT((tb_investimentos[Movimento]="Aporte")*(YEAR(tb_investimentos[Data])=$J$2)*(MONTH(tb_investimentos[Data])=5)*tb_investimentos[Valor])} -> 0 | J18: {=SUMPRODUCT((tb_investimentos[Movimento]="Resgate")*(YEAR(tb_investimentos[Data])=$J$2)*(MONTH(tb_investimentos[Data])=5)*tb_investimentos[Valor])} -> 0 | K18: =I18-J18 -> 0 | L18: =L17+K18 -> 0
A19: 45822 | B19: Tesouro Direto | C19: Renda Fixa | D19: Aporte | E19: 300 | F19: Aporte mensal RF | H19: Jun | I19: {=SUMPRODUCT((tb_investimentos[Movimento]="Aporte")*(YEAR(tb_investimentos[Data])=$J$2)*(MONTH(tb_investimentos[Data])=6)*tb_investimentos[Valor])} -> 0 | J19: {=SUMPRODUCT((tb_investimentos[Movimento]="Resgate")*(YEAR(tb_investimentos[Data])=$J$2)*(MONTH(tb_investimentos[Data])=6)*tb_investimentos[Valor])} -> 0 | K19: =I19-J19 -> 0 | L19: =L18+K19 -> 0
A20: 45822 | B20: ETF | C20: Renda Variável | D20: Aporte | E20: 100 | F20: Aporte mensal RV | H20: Jul | I20: {=SUMPRODUCT((tb_investimentos[Movimento]="Aporte")*(YEAR(tb_investimentos[Data])=$J$2)*(MONTH(tb_investimentos[Data])=7)*tb_investimentos[Valor])} -> 0 | J20: {=SUMPRODUCT((tb_investimentos[Movimento]="Resgate")*(YEAR(tb_investimentos[Data])=$J$2)*(MONTH(tb_investimentos[Data])=7)*tb_investimentos[Valor])} -> 0 | K20: =I20-J20 -> 0 | L20: =L19+K20 -> 0
A21: 45822 | B21: Previdência Privada | C21: Previdência | D21: Aporte | E21: 100 | F21: Aporte mensal Prev | H21: Ago | I21: {=SUMPRODUCT((tb_investimentos[Movimento]="Aporte")*(YEAR(tb_investimentos[Data])=$J$2)*(MONTH(tb_investimentos[Data])=8)*tb_investimentos[Valor])} -> 0 | J21: {=SUMPRODUCT((tb_investimentos[Movimento]="Resgate")*(YEAR(tb_investimentos[Data])=$J$2)*(MONTH(tb_investimentos[Data])=8)*tb_investimentos[Valor])} -> 0 | K21: =I21-J21 -> 0 | L21: =L20+K21 -> 0
A22: 45852 | B22: Tesouro Direto | C22: Renda Fixa | D22: Aporte | E22: 300 | F22: Aporte mensal RF | H22: Set | I22: {=SUMPRODUCT((tb_investimentos[Movimento]="Aporte")*(YEAR(tb_investimentos[Data])=$J$2)*(MONTH(tb_investimentos[Data])=9)*tb_investimentos[Valor])} -> 0 | J22: {=SUMPRODUCT((tb_investimentos[Movimento]="Resgate")*(YEAR(tb_investimentos[Data])=$J$2)*(MONTH(tb_investimentos[Data])=9)*tb_investimentos[Valor])} -> 0 | K22: =I22-J22 -> 0 | L22: =L21+K22 -> 0
A23: 45852 | B23: ETF | C23: Renda Variável | D23: Aporte | E23: 100 | F23: Aporte mensal RV | H23: Out | I23: {=SUMPRODUCT((tb_investimentos[Movimento]="Aporte")*(YEAR(tb_investimentos[Data])=$J$2)*(MONTH(tb_investimentos[Data])=10)*tb_investimentos[Valor])} -> 0 | J23: {=SUMPRODUCT((tb_investimentos[Movimento]="Resgate")*(YEAR(tb_investimentos[Data])=$J$2)*(MONTH(tb_investimentos[Data])=10)*tb_investimentos[Valor])} -> 0 | K23: =I23-J23 -> 0 | L23: =L22+K23 -> 0
A24: 45852 | B24: Previdência Privada | C24: Previdência | D24: Aporte | E24: 100 | F24: Aporte mensal Prev | H24: Nov | I24: {=SUMPRODUCT((tb_investimentos[Movimento]="Aporte")*(YEAR(tb_investimentos[Data])=$J$2)*(MONTH(tb_investimentos[Data])=11)*tb_investimentos[Valor])} -> 0 | J24: {=SUMPRODUCT((tb_investimentos[Movimento]="Resgate")*(YEAR(tb_investimentos[Data])=$J$2)*(MONTH(tb_investimentos[Data])=11)*tb_investimentos[Valor])} -> 0 | K24: =I24-J24 -> 0 | L24: =L23+K24 -> 0
A25: 45883 | B25: Tesouro Direto | C25: Renda Fixa | D25: Aporte | E25: 300 | F25: Aporte mensal RF | H25: Dez | I25: {=SUMPRODUCT((tb_investimentos[Movimento]="Aporte")*(YEAR(tb_investimentos[Data])=$J$2)*(MONTH(tb_investimentos[Data])=12)*tb_investimentos[Valor])} -> 0 | J25: {=SUMPRODUCT((tb_investimentos[Movimento]="Resgate")*(YEAR(tb_investimentos[Data])=$J$2)*(MONTH(tb_investimentos[Data])=12)*tb_investimentos[Valor])} -> 0 | K25: =I25-J25 -> 0 | L25: =L24+K25 -> 0
A26: 45883 | B26: ETF | C26: Renda Variável | D26: Aporte | E26: 100 | F26: Aporte mensal RV | H26: TOTAL | I26: =SUM(I14:I25) -> 0 | J26: =SUM(J14:J25) -> 0 | K26: =SUM(K14:K25) -> 0 | L26: =L25 -> 0
A27: 45883 | B27: Previdência Privada | C27: Previdência | D27: Aporte | E27: 100 | F27: Aporte mensal Prev | K27: CC ANA | L27: 4000
A28: 45914 | B28: Tesouro Direto | C28: Renda Fixa | D28: Aporte | E28: 300 | F28: Aporte mensal RF | H28: 💡 DICA: Altere ANO (J2) e MÊS (L2) para filtrar os dados.
A29: 45914 | B29: ETF | C29: Renda Variável | D29: Aporte | E29: 100 | F29: Aporte mensal RV
A30: 45914 | B30: Previdência Privada | C30: Previdência | D30: Aporte | E30: 100 | F30: Aporte mensal Prev | H30: TOTAL João e Ana | L30: =L26-C47+L27 -> 4000
A31: 45944 | B31: Tesouro Direto | C31: Renda Fixa | D31: Aporte | E31: 300 | F31: Aporte mensal RF
A32: 45944 | B32: ETF | C32: Renda Variável | D32: Aporte | E32: 100 | F32: Aporte mensal RV
A33: 45944 | B33: Previdência Privada | C33: Previdência | D33: Aporte | E33: 100 | F33: Aporte mensal Prev
A34: 45975 | B34: Tesouro Direto | C34: Renda Fixa | D34: Aporte | E34: 300 | F34: Aporte mensal RF
A35: 45975 | B35: ETF | C35: Renda Variável | D35: Aporte | E35: 100 | F35: Aporte mensal RV
A36: 45975 | B36: Previdência Privada | C36: Previdência | D36: Aporte | E36: 100 | F36: Aporte mensal Prev
A37: 46005 | B37: Tesouro Direto | C37: Renda Fixa | D37: Aporte | E37: 500 | F37: Aporte mensal RF
A38: 46005 | B38: ETF | C38: Renda Variável | D38: Aporte | E38: 100 | F38: Aporte mensal RV
A39: 46005 | B39: Previdência Privada | C39: Previdência | D39: Aporte | E39: 100 | F39: Aporte mensal Prev

Sheet CAD_Investimentos
A1: Tipo_Ativo | B1: Classe | C1: Categoria
A2: Conta Corrente | B2: Liquidez | C2: Caixa
A3: Tesouro Direto | B3: Renda Fixa | C3: Investimentos
A4: Renda Fixa | B4: Renda Fixa | C4: Investimentos
A5: Ações | B5: Renda Variável | C5: Investimentos
A6: FII | B6: Renda Variável | C6: Investimentos
A7: Previdência Privada | B7: Previdência | C7: Investimentos
A8: Consórcio | B8: Alternativos | C8: Investimentos
A9: Moeda Estrangeira | B9: Alternativos | C9: Investimentos

Sheet CAD_Categorias
A1: Tipo | B1: Categoria | C1: Subcategoria
A2: Receita | B2: Salário | C2: Maria – Hospital Central
A3: Receita | B3: Salário | C3: Maria – Hospital 13º/Férias
A4: Receita | B4: Salário | C4: Maria – Plano Saúde
A5: Receita | B5: Salário | C5: Maria – Plano Saúde Extras
A6: Receita | B6: Salário | C6: Maria – Bolsa Doutorado
A7: Receita | B7: Salário | C7: Carlos – Auxílio
A8: Receita | B8: Benefício | C8: Auxílio Alimentação
A9: Receita | B9: Serviço | C9: Consultas Particulares
A10: Receita | B10: Convênios | C10: Outros Convênios
A11: Receita | B11: Extra | C11: Restituição IR
A12: Receita | B12: Extra | C12: Outros
... A64: Investimento | B64: Alternativos | C64: Outros / Subscrição

Sheet Aux_Listas
A1: Salário | B1: Salário | C1: Benefício | D1: Serviço | E1: Convênios | F1: Extra | G1: Habitação | H1: Alimentação | I1: Transporte | J1: Saúde | K1: Educação | L1: Vestuário | M1: Lazer | N1: Trabalho | O1: Caridade | P1: Dívidas | Q1: Outras_Despesas | R1: Renda_Fixa | S1: Renda_Variável | T1: Previdência | U1: Invest_Alternativos
A2: Benefício | B2: Maria – Hospital Central | C2: Auxílio Alimentação | D2: Consultas Particulares | E2: Outros Convênios | F2: Restituição IR | G2: Faxineira | H2: Supermercado/Sacolão/Padaria | I2: IPVA Veículos | J2: Plano de Saúde | K2: Mensalidade Escolar | L2: Roupas | M2: Viagens | N2: Custo Trabalho | O2: Dízimo | P2: Pgto Dívidas | Q2: Presentes | R2: Tesouro Direto | S2: Ações | T2: Prev.Privada | U2: Poupança
A3: Serviço | B3: Maria – Hospital 13º/Férias | F3: Outros | G3: Empregada Doméstica | H3: Almoço Escola/Trabalho | I3: Seguro Veículos | J3: Farmácia | K3: Marterial Escolar | L3: Calçados | M3: Saídas | O3: Doação | Q3: Juros | R3: CDB | S3: FII
A4: Convênios | B4: Maria – Plano Saúde | G4: Imposto Doméstica | H4: Delivery | I4: Manutenção Veículos | J4: Dentista/Médico Extra | K4: Material Extra | L4: Acessórios | M4: Festas | O4: Contribuição Missas | Q4: Aquisições Bens
A5: Extra | B5: Maria – Plano Saúde Extras | G5: IPTU | I5: Gasolina | J5: Outros | K5: Uniforme | M5: Esportes / Música | Q5: Outros
A6: Habitação | B6: Maria – Bolsa Doutorado | G6: Energia Elétrica | I6: Estacionamento | K6: Outros | M6: Streaming
A7: Alimentação | B7: Carlos – Auxílio | G7: Água | I7: Uber
A8: Transporte | G8: Gás
A9: Saúde | G9: NET(Fone, TV, Internet)
A10: Educação | G10: Jardim_Área Externa
A11: Vestuário | G11: Limpeza Piscina
A12: Lazer | G12: Manutenção Casa
A13: Trabalho | G13: Seguro Casa
A14: Caridade | G14: Segurança APIBB
A15: Dívidas | G15: Aquisições para Casa
A16: Outros | G16: Animais PETs
A17: Renda Fixa
A18: Renda Variável
A19: Previdência
A20: Alternativos

Sheet CALENDARIO
A1: Data | B1: Ano | C1: Mês | D1: Ano_Mês | E1: Dia | F1: Semana | G1: Trimestre
A2: =DATE(2024,1,1) -> 45292 | B2: =YEAR(A2) -> 2024 | C2: =MONTH(A2) -> 1 | D2: =TEXT(A2,"mmmm") -> janeiro | E2: =DAY(A2) -> 1 | F2: =WEEKNUM(A2,2) -> 1 | G2: =INT((MONTH(A2)-1)/3)+1 -> 1
A3: =A2+1 -> 45293
A4: =A3+1 -> 45294
A5: =A4+1 -> 45295
A6: =A5+1 -> 45296
A7: =A6+1 -> 45297
A8: =A7+1 -> 45298
A9: =A8+1 -> 45299
A10: =A9+1 -> 45300
A11: =A10+1 -> 45301
A12: =A11+1 -> 45302
A13: =A12+1 -> 45303
A14: =A13+1 -> 45304
... A2959: =A2958+1 -> 48249

Sheet PARCELAS 
A1: ID_Compra | B1: Data_Compra | C1: Descrição | D1: Parcela | E1: Valor_Parcela | F1: Fatura_MesAno | G1: Data_Vencimento | H1: Cartão
A2: 1 | B2: 45662 | C2: Jantar aniversário família | D2: 1 | E2: 450 | F2: jan/2025 | G2: 45672.125 | H2: Crédito Banco A - Maria
A3: 2 | B3: 45667 | C3: Roupas de verão | D3: 1 | E3: 296.66667 | F3: jan/2025 | G3: 45693.125 | H3: Crédito Banco A - Carlos
A4: 2 | B4: 45667 | C4: Roupas de verão | D4: 2 | E4: 296.66667 | F4: fev/2025 | G4: 45721.125 | H4: Crédito Banco A - Carlos
A5: 2 | B5: 45667 | C5: Roupas de verão | D5: 3 | E5: 296.66667 | F5: mar/2025 | G5: 45752.125 | H5: Crédito Banco A - Carlos
A6: 3 | B6: 45672 | C6: Passagens férias julho | D6: 1 | E6: 600 | F6: fev/2025 | G6: 45707.125 | H6: Crédito Banco B - Maria
A7: 3 | B7: 45672 | C7: Passagens férias julho | D7: 2 | E7: 600 | F7: mar/2025 | G7: 45735.125 | H7: Crédito Banco B - Maria
A8: 3 | B8: 45672 | C8: Passagens férias julho | D8: 3 | E8: 600 | F8: abr/2025 | G8: 45766.125 | H8: Crédito Banco B - Maria
A9: 3 | B9: 45672 | C9: Passagens férias julho | D9: 4 | E9: 600 | F9: mai/2025 | G9: 45796.125 | H9: Crédito Banco B - Maria
A10: 3 | B10: 45672 | C10: Passagens férias julho | D10: 5 | E10: 600 | F10: jun/2025 | G10: 45827.125 | H10: Crédito Banco B - Maria
A11: 3 | B11: 45672 | C11: Passagens férias julho | D11: 6 | E11: 600 | F11: jul/2025 | G11: 45857.125 | H11: Crédito Banco B - Maria
A12: 4 | B12: 45677 | C12: Sofá novo sala | D12: 1 | E12: 450 | F12: fev/2025 | G12: 45703.125 | H12: Crédito Banco A - Maria
A13: 4 | B13: 45677 | C13: Sofá novo sala | D13: 2 | E13: 450 | F13: mar/2025 | G13: 45731.125 | H13: Crédito Banco A - Maria
... A96: 37 | B96: 46011 | C96: Festa Réveillon | D96: 2 | E96: 225 | F96: fev/2026 | G96: 46068.125 | H96: Crédito Banco A - Maria
